Workbook

Sheet Privat
A1: Udgifter/Indtægter | B1: 2026 | C1: 2027 | D1: 2028 | E1: 2029 | F1: 2030 | G1: Kategori
A2: Kreditlån | B2: =-48000/3 -> -16000 | C2: =B2 -> -16000 | D2: =C2 -> -16000 | E2: =D2 -> -16000 | F2: =E2 -> -16000 | G2: Bygning
A3: Banklån | B3: -1000 | C3: =B3 -> -1000 | D3: =C3 -> -1000 | E3: =D3 -> -1000 | F3: =E3 -> -1000 | G3: Bygning
A4: Grundskyld, ejendomsværdiskat og offentlige afgifter | B4: =-((1606/12)+(4500/12)) -> -508.83333 | C4: =B4 -> -508.83333 | D4: =C4 -> -508.83333 | E4: =D4 -> -508.83333 | F4: =E4 -> -508.83333 | G4: Bygning
A5: Studiegæld | B5: =-2950/2 -> -1475 | C5: =B5 -> -1475 | D5: =C5 -> -1475 | E5: =D5 -> -1475 | F5: =E5 -> -1475 | G5: Gæld
A6: Billån (Afbetaling + renter) | B6: -3475 | C6: =B6 -> -3475 | D6: =C6 -> -3475 | E6: =D6 -> -3475 | F6: =E6 -> -3475 | G6: Bil
A7: Sygeforsikring + medicin | B7: =-(((99+419)/3)+250) -> -422.66667 | C7: =B7 -> -422.66667 | D7: =C7 -> -422.66667 | E7: =D7 -> -422.66667 | F7: =E7 -> -422.66667 | G7: Forsikring
A8: A-kasse (Det faglige hus) | B8: -528 | C8: =B8 -> -528 | D8: =C8 -> -528 | E8: =D8 -> -528 | F8: =E8 -> -528 | G8: Andet
A9: Fagforening | B9: 0 | C9: =B9 -> 0 | D9: =C9 -> 0 | E9: =D9 -> 0 | F9: =E9 -> 0 | G9: Andet
A10: Hund (Foder og flåtpiller) | B10: =-((348/2)+500/12) -> -215.66667 | C10: =B10 -> -215.66667 | D10: =C10 -> -215.66667 | E10: =D10 -> -215.66667 | F10: =E10 -> -215.66667 | G10: Dyr
A11: Ponyer (Wrap om vinteren) | B11: =-400*6/12 -> -200 | C11: =B11 -> -200 | D11: =C11 -> -200 | E11: =D11 -> -200 | F11: =E11 -> -200 | G11: Dyr
A12: Vestjylland forsikring | B12: =-((27550+997+855)/12) -> -2450.1667 | C12: =B12 -> -2450.1667 | D12: =C12 -> -2450.1667 | E12: =D12 -> -2450.1667 | F12: =E12 -> -2450.1667 | G12: Forsikring
A13: Livsforsikring | B13: =-((3312+2760)/12) -> -506 | C13: =B13 -> -506 | D13: =C13 -> -506 | E13: =D13 -> -506 | F13: =E13 -> -506 | G13: Forsikring
A14: Tab af erhvervsevne | B14: =-(2*1656)/12 -> -276 | C14: =B14 -> -276 | D14: =C14 -> -276 | E14: =D14 -> -276 | F14: =E14 -> -276 | G14: Forsikring
A15: Sundhedsforsikring | B15: =-2996/12 -> -249.66667 | C15: =B15 -> -249.66667 | D15: =C15 -> -249.66667 | E15: =D15 -> -249.66667 | F15: =E15 -> -249.66667 | G15: Forsikring
A16: Vand | B16: =-1500/3 -> -500 | C16: =B16 -> -500 | D16: =C16 -> -500 | E16: =D16 -> -500 | F16: =E16 -> -500 | G16: Forbrug
A17: Grøn ejerafgift | B17: =-((1210/6)+(800/12)) -> -268.33333 | C17: =B17 -> -268.33333 | D17: =C17 -> -268.33333 | E17: =D17 -> -268.33333 | F17: =E17 -> -268.33333 | G17: Bil
A18: El-forbrug (inkl. ladning) | B18: -1300 | C18: =B18 -> -1300 | D18: =C18 -> -1300 | E18: =D18 -> -1300 | F18: =E18 -> -1300 | G18: Forbrug
A19: Daginstitution | B19: 0 | C19: -3200 | D19: =C19 -> -3200 | E19: -5200 | F19: =E19 -> -5200 | G19: Børn
A20: (Streaming)tjenester (Netflix, Disney, Lifesum) | B20: =-(114+130+149+39) -> -432 | C20: =B20 -> -432 | D20: =C20 -> -432 | E20: =D20 -> -432 | F20: =E20 -> -432 | G20: Fritid
A21: Mobil | B21: =-(1000/12) -> -83.333333 | C21: =-(1000/12) -> -83.333333 | D21: =-(1000/12) -> -83.333333 | E21: =-(1000/12) -> -83.333333 | F21: =-(1000/12) -> -83.333333 | G21: Andet
A22: Tandlæge | B22: =-((99+114)) -> -213 | C22: =B22 -> -213 | D22: =C22 -> -213 | E22: =D22 -> -213 | F22: =E22 -> -213 | G22: Andet
A23: Jagttegn | B23: =-(2*676)/12 -> -112.66667 | C23: =B23 -> -112.66667 | D23: =C23 -> -112.66667 | E23: =D23 -> -112.66667 | F23: =E23 -> -112.66667 | G23: Fritid
A24: Træpiller | B24: =-(9*2400/12) -> -1800 | C24: =B24 -> -1800 | D24: =C24 -> -1800 | E24: =D24 -> -1800 | F24: =E24 -> -1800 | G24: Forbrug
A25: RønGårdens driftomkostninger - gennemsnit over året (u. moms) | B25: 0 | C25: =-SUM('Udgifter (Forecast)'!M23:M43)/12 -> -3266.59 | D25: =-SUM('Udgifter (Forecast)'!M44:M64)/12 -> -3976.09 | E25: {=-SUM('Udgifter (Forecast)'!M65:M85/12)} -> -4738.9233 | F25: =-SUM('Udgifter (Forecast)'!M86:M106)/12 -> -5740.7667 | G25: Drift
A26: RønGårdens overskud (u. moms + efter skat) - gennemsnit over året | B26: 0 | C26: =((((SUM('Indtægter (Forecast)'!N7:N11)/12)-C25)-12000)*(1-0.39))+12000 -> 15792.12 | D26: {=(((SUM('Indtægter (Forecast)'!N17:N21/12)-D25)-12000)*(1-0.39))+12000} -> 21308.248 | E26: {=(((SUM('Indtægter (Forecast)'!N17:N21/12)-E25)-12000)*(1-0.39))+12000} -> 21773.577 | F26: =((((SUM('Indtægter (Forecast)'!N17:N21)/12)-F25)-12000)*(1-0.39))+12000 -> 22384.701 | G26: Drift
A27: Lønoverførsel fra RønGården (Inden skat) | B27: 0 | C27: 15000 | D27: 20000 | E27: 20000 | F27: 20000 | G27: Drift
A28: Alexander løn | B28: 32000 | C28: 32000 | D28: 32000 | E28: 32000 | F28: 32000 | G28: Indkomst
A29: Hjemmepasningstillæg | B29: 5500 | C29: 0 | D29: 0 | E29: 0 | F29: 0 | G29: Indkomst
A30: Børnepenge | B30: 1500 | C30: 1500 | D30: 3000 | E30: 3000 | F30: 3000 | G30: Indkomst
A31: Overføres til budgetkonto | B31: =SUM(B2:B24) -> -32016.333 | C31: =SUM(C2:C24) -> -35216.333 | D31: =SUM(D2:D24) -> -35216.333 | E31: =SUM(E2:E24) -> -37216.333 | F31: =SUM(F2:F24) -> -37216.333 | G31: Budget
A32: Overføres til "Mad og diverse" | B32: -4000 | C32: -5000 | D32: -5000 | E32: -5000 | F32: -5000 | G32: Budget
A33: Overføres til opsparingskontoen | B33: =B27+B28+B29+B30+B31+B32 -> 2983.6667 | C33: =C27+C28+C29+C30+C31+C32 -> 8283.6667 | D33: =D27+D28+D29+D30+D31+D32 -> 14783.667 | E33: =E27+E28+E29+E30+E31+E32 -> 12783.667 | F33: =F27+F28+F29+F30+F31+F32 -> 12783.667 | G33: Opsparing
A34: Difference erhvervskonto | B34: =B26-B27 -> 0 | C34: =C26-C27 -> 792.1199 | D34: =D26-D27 -> 1308.2482 | E34: =E26-E27 -> 1773.5766 | F34: =F26-F27 -> 2384.701 | G34: Erhvervsopsparing
A35: Formue ultimo (Saldo på opsparing) | B35: 85000 | C35: =B35+(12*C33) -> 184404 | D35: =C35+(12*D33) -> 361808 | E35: =D35+(12*E33) -> 515212 | F35: =E35+(12*F33) -> 668616 | G35: Formue
A36: Formue (Saldo på erhvervskonto) | B36: 20000 | C36: =B36+(12*C34) -> 29505.439 | D36: =C36+(12*D34) -> 45204.418 | E36: =D36+(12*E34) -> 66487.336 | F36: =E36+(12*F34) -> 95103.748 | G36: Formue
A37: Formue i alt | B37: =B35+B36 -> 105000 | C37: =C35+C36 -> 213909.44 | D37: =D35+D36 -> 407012.42 | E37: =E35+E36 -> 581699.34 | F37: =F35+F36 -> 763719.75 | G37: Formue

Sheet Indtægter (Forecast)
A1: Aktivitet | B1: Månede start | C1: Månede slut | D1: Postering | E1: Type indtægt/ udgift | F1: Kategori | G1: Enhed | H1: Enhedspris i DKK (m. moms) | I1: Enheder total | J1: Fordelt på antal mdr | K1: Indtægt pr mdr (m. moms) | L1: Indtægt pr mdr (u. moms) | M1: Indtægt total (m. moms) | N1: Indtægt total (u. moms) | O1: Mandetimer pr enhed/år | P1: Mandetimer total | Q1: Resultat pr produkt (u. moms) | R1: Timesats pr produkt | S1: Årstal
A2: Kyllinger | B2: 46327 | C2: =EDATE(B2,0) -> 46327 | D2: Indtægt | E2: Variabel | F2: Kyllinger | G2: Stk | H2: 150 | I2: 25 | J2: =DATEDIF(B2,C2,"m")+1 -> 1 | K2: =I2*H2/J2 -> 3750 | L2: =K2-(K2/5) -> 3000 | M2: =IF(D2="Indtægt",K2*J2,-K2*J2) -> 3750 | N2: =L2*J2 -> 3000 | O2: =40/60 -> 0.66666667 | P2: =O2*I2 -> 16.666667 | Q2: =N2-('Udgifter (Forecast)'!M4+'Udgifter (Forecast)'!M9+'Udgifter (Forecast)'!M11) -> 0 | R2: =Q2/P2 -> 0 | S2: 2026
A3: Æg | B3: =C2 -> 46327 | C3: =EDATE(B3,1) -> 46357 | D3: Indtægt | E3: Variabel | F3: Æg | G3: Stk | H3: 2.5 | I3: ='Udgifter (Forecast)'!H10*(250/365)*45 -> 2527.3973 | J3: =DATEDIF(B3,C3,"m")+1 -> 2 | K3: =I3*H3/J3 -> 3159.2466 | L3: =K3-(K3/5) -> 2527.3973 | M3: =IF(D3="Indtægt",K3*J3,-K3*J3) -> 6318.4932 | N3: =L3*J3 -> 5054.7945 | O3: =3/60 -> 0.05 | P3: =O3*I3 -> 126.36986 | Q3: =N3-'Udgifter (Forecast)'!M2-'Udgifter (Forecast)'!M10-'Udgifter (Forecast)'!M12-'Udgifter (Forecast)'!M19-'Udgifter (Forecast)'!M21-'Udgifter (Forecast)'!M22 -> 2019.9145 | R3: =Q3/P3 -> 15.984147 | S3: 2026
A4: Kvæg | B4: 46143 | C4: =EDATE(B4,0) -> 46143 | D4: Indtægt | E4: Variabel | F4: Kvæg | G4: Stk | H4: 12500 | I4: 2 | J4: =DATEDIF(B4,C4,"m")+1 -> 1 | K4: =I4*H4/J4 -> 25000 | L4: =K4-(K4/5) -> 20000 | M4: =IF(D4="Indtægt",K4*J4,-K4*J4) -> 25000 | N4: =L4*J4 -> 20000 | O4: =160/10 -> 16 | P4: =(('Udgifter (Forecast)'!H14+'Udgifter (Forecast)'!H15)/2)*O4 -> 40 | Q4: =N4-'Udgifter (Forecast)'!M3-'Udgifter (Forecast)'!M8-'Udgifter (Forecast)'!M13-'Udgifter (Forecast)'!M14-'Udgifter (Forecast)'!M15 -> 8208 | R4: =Q4/P4 -> 205.2 | S4: 2026
A5: Jordbær | B5: 46174 | C5: =EDATE(B5,3) -> 46266 | D5: Indtægt | E5: Variabel | F5: Jordbær | G5: kg | H5: 50 | I5: 0 | J5: =DATEDIF(B5,C5,"m")+1 -> 4 | K5: =I5*H5/J5 -> 0 | L5: =K5-(K5/5) -> 0 | M5: =IF(D5="Indtægt",K5*J5,-K5*J5) -> 0 | N5: =L5*J5 -> 0 | O5: =50/1000 -> 0.05 | P5: 0.01 | Q5: =N5-('Udgifter (Forecast)'!M16+'Udgifter (Forecast)'!M17) -> 0 | R5: =Q5/P5 -> 0 | S5: 2026
A6: Kartofler | B6: 46174 | C6: =EDATE(B6,3) -> 46266 | D6: Indtægt | E6: Variabel | F6: Kartofler | G6: kg | H6: 12 | I6: 0 | J6: =DATEDIF(B6,C6,"m")+1 -> 4 | K6: =I6*H6/J6 -> 0 | L6: =K6-(K6/5) -> 0 | M6: =IF(D6="Indtægt",K6*J6,-K6*J6) -> 0 | N6: =L6*J6 -> 0 | O6: =5/60 -> 0.083333333 | P6: 0.01 | Q6: =N6-('Udgifter (Forecast)'!M18+'Udgifter (Forecast)'!M20) -> 0 | R6: =Q6/P6 -> 0 | S6: 2026
A7: Kyllinger | B7: 46692 | C7: =EDATE(B7,0) -> 46692 | D7: Indtægt | E7: Variabel | F7: Kyllinger | G7: Stk | H7: 200 | I7: ='Udgifter (Forecast)'!H30/2 -> 100 | J7: =DATEDIF(B7,C7,"m")+1 -> 1 | K7: =I7*H7/J7 -> 20000 | L7: =K7-(K7/5) -> 16000 | M7: =IF(D7="Indtægt",K7*J7,-K7*J7) -> 20000 | N7: =L7*J7 -> 16000 | O7: =40/60 -> 0.66666667 | P7: =O7*I7 -> 66.666667 | Q7: =N7-('Udgifter (Forecast)'!M25+'Udgifter (Forecast)'!M30+'Udgifter (Forecast)'!M32) -> 6400 | R7: =Q7/P7 -> 96 | S7: 2027
A8: Æg | B8: 46388 | C8: =EDATE(B8,12) -> 46753 | D8: Indtægt | E8: Variabel | F8: Æg | G8: Stk | H8: 2.5 | I8: ='Udgifter (Forecast)'!H31*250 -> 20500 | J8: =DATEDIF(B8,C8,"m") -> 12 | K8: =I8*H8/J8 -> 4270.8333 | L8: =K8-(K8/5) -> 3416.6667 | M8: =IF(D8="Indtægt",K8*J8,-K8*J8) -> 51250 | N8: =L8*J8 -> 41000 | O8: =3/60 -> 0.05 | P8: =O8*I8 -> 1025 | Q8: =N8-('Udgifter (Forecast)'!M23+'Udgifter (Forecast)'!M31+'Udgifter (Forecast)'!M33+'Udgifter (Forecast)'!M40+'Udgifter (Forecast)'!M42+'Udgifter (Forecast)'!M43) -> 32172.12 | R8: =Q8/P8 -> 31.387434 | S8: 2027
A9: Kvæg | B9: 46722 | C9: =EDATE(B9,0) -> 46722 | D9: Indtægt | E9: Variabel | F9: Kvæg | G9: Stk | H9: 12000 | I9: 1 | J9: =DATEDIF(B9,C9,"m")+1 -> 1 | K9: =I9*H9/J9 -> 12000 | L9: =K9-(K9/5) -> 9600 | M9: =IF(D9="Indtægt",K9*J9,-K9*J9) -> 12000 | N9: =L9*J9 -> 9600 | O9: =160/10 -> 16 | P9: =(('Udgifter (Forecast)'!H35+'Udgifter (Forecast)'!H36)/2)*O9 -> 72 | Q9: =N9-('Udgifter (Forecast)'!M24+'Udgifter (Forecast)'!M29+'Udgifter (Forecast)'!M34+'Udgifter (Forecast)'!M35+'Udgifter (Forecast)'!M36) -> 928 | R9: =Q9/P9 -> 12.888889 | S9: 2027
A10: Jordbær | B10: 46539 | C10: =EDATE(B10,3) -> 46631 | D10: Indtægt | E10: Variabel | F10: Jordbær | G10: kg | H10: 50 | I10: =3500*0.6 -> 2100 | J10: =DATEDIF(B10,C10,"m")+1 -> 4 | K10: =I10*H10/J10 -> 26250 | L10: =K10-(K10/5) -> 21000 | M10: =IF(D10="Indtægt",K10*J10,-K10*J10) -> 105000 | N10: =L10*J10 -> 84000 | O10: =50/1000 -> 0.05 | P10: =O10*(I10/60%) -> 175 | Q10: =N10-('Udgifter (Forecast)'!M37+'Udgifter (Forecast)'!M38) -> 80928 | R10: =Q10/P10 -> 462.44571 | S10: 2027
A11: Kartofler | B11: 46539 | C11: =EDATE(B11,3) -> 46631 | D11: Indtægt | E11: Variabel | F11: Kartofler | G11: kg | H11: 12 | I11: 3000 | J11: =DATEDIF(B11,C11,"m")+1 -> 4 | K11: =I11*H11/J11 -> 9000 | L11: =K11-(K11/5) -> 7200 | M11: =IF(D11="Indtægt",K11*J11,-K11*J11) -> 36000 | N11: =L11*J11 -> 28800 | O11: =5/60 -> 0.083333333 | P11: =O11*I11 -> 250 | Q11: =N11-('Udgifter (Forecast)'!M39+'Udgifter (Forecast)'!M41) -> 27000 | R11: =Q11/P11 -> 108 | S11: 2027
A12: Kyllinger | B12: =B7+366 -> 47058 | C12: =EDATE(B12,0) -> 47058 | D12: Indtægt | E12: Variabel | F12: Kyllinger | G12: Stk | H12: 175 | I12: ='Udgifter (Forecast)'!H51/2 -> 100 | J12: =DATEDIF(B12,C12,"m")+1 -> 1 | K12: =I12*H12/J12 -> 17500 | L12: =K12-(K12/5) -> 14000 | M12: =IF(D12="Indtægt",K12*J12,-K12*J12) -> 17500 | N12: =L12*J12 -> 14000 | O12: =40/60 -> 0.66666667 | P12: =O12*I12 -> 66.666667 | Q12: =N12-('Udgifter (Forecast)'!M46+'Udgifter (Forecast)'!M51+'Udgifter (Forecast)'!M53) -> 4400 | R12: =Q12/P12 -> 66 | S12: 2028
A13: Æg | B13: =B8+366 -> 46754 | C13: =EDATE(B13,12) -> 47120 | D13: Indtægt | E13: Variabel | F13: Æg | G13: Stk | H13: 2.5 | I13: ='Udgifter (Forecast)'!H52*250 -> 45500 | J13: =DATEDIF(B13,C13,"m")+1 -> 13 | K13: =I13*H13/J13 -> 8750 | L13: =K13-(K13/5) -> 7000 | M13: =IF(D13="Indtægt",K13*J13,-K13*J13) -> 113750 | N13: =L13*J13 -> 91000 | O13: =3/60 -> 0.05 | P13: =O13*I13 -> 2275 | Q13: =N13-('Udgifter (Forecast)'!M44+'Udgifter (Forecast)'!M52+'Udgifter (Forecast)'!M54++'Udgifter (Forecast)'!M61+'Udgifter (Forecast)'!M63+'Udgifter (Forecast)'!M64) -> 74938.12 | R13: =Q13/P13 -> 32.939833 | S13: 2028
A14: Kvæg | B14: =B9+366 -> 47088 | C14: =EDATE(B14,0) -> 47088 | D14: Indtægt | E14: Variabel | F14: Kvæg | G14: Stk | H14: 12000 | I14: 1 | J14: =DATEDIF(B14,C14,"m")+1 -> 1 | K14: =I14*H14/J14 -> 12000 | L14: =K14-(K14/5) -> 9600 | M14: =IF(D14="Indtægt",K14*J14,-K14*J14) -> 12000 | N14: =L14*J14 -> 9600 | O14: =160/10 -> 16 | P14: =(('Udgifter (Forecast)'!H56+'Udgifter (Forecast)'!H57)/2)*O14 -> 104 | Q14: =N14-('Udgifter (Forecast)'!M45+'Udgifter (Forecast)'!M50+'Udgifter (Forecast)'!M55+'Udgifter (Forecast)'!M56+'Udgifter (Forecast)'!M57) -> -352 | R14: =Q14/P14 -> -3.3846154 | S14: 2028
A15: Jordbær | B15: =B10+366 -> 46905 | C15: =EDATE(B15,3) -> 46997 | D15: Indtægt | E15: Variabel | F15: Jordbær | G15: kg | H15: 50 | I15: =3500*0.6 -> 2100 | J15: =DATEDIF(B15,C15,"m")+1 -> 4 | K15: =I15*H15/J15 -> 26250 | L15: =K15-(K15/5) -> 21000 | M15: =IF(D15="Indtægt",K15*J15,-K15*J15) -> 105000 | N15: =L15*J15 -> 84000 | O15: =50/1000 -> 0.05 | P15: =O15*(I15/60%) -> 175 | Q15: =N15-('Udgifter (Forecast)'!M58+'Udgifter (Forecast)'!M59) -> 80928 | R15: =Q15/P15 -> 462.44571 | S15: 2028
A16: Kartofler | B16: =B11+366 -> 46905 | C16: =EDATE(B16,3) -> 46997 | D16: Indtægt | E16: Variabel | F16: Kartofler | G16: kg | H16: 12 | I16: 3000 | J16: =DATEDIF(B16,C16,"m")+1 -> 4 | K16: =I16*H16/J16 -> 9000 | L16: =K16-(K16/5) -> 7200 | M16: =IF(D16="Indtægt",K16*J16,-K16*J16) -> 36000 | N16: =L16*J16 -> 28800 | O16: =5/60 -> 0.083333333 | P16: =O16*I16 -> 250 | Q16: =N16-('Udgifter (Forecast)'!M60+'Udgifter (Forecast)'!M62) -> 27000 | R16: =Q16/P16 -> 108 | S16: 2028
A17: Kyllinger | B17: =B12+365 -> 47423 | C17: =EDATE(B17,0) -> 47423 | D17: Indtægt | E17: Variabel | F17: Kyllinger | G17: Stk | H17: 200 | I17: ='Udgifter (Forecast)'!H72/2 -> 100 | J17: =DATEDIF(B17,C17,"m")+1 -> 1 | K17: =I17*H17/J17 -> 20000 | L17: =K17-(K17/5) -> 16000 | M17: =IF(D17="Indtægt",K17*J17,-K17*J17) -> 20000 | N17: =L17*J17 -> 16000 | O17: =40/60 -> 0.66666667 | P17: =O17*I17 -> 66.666667 | Q17: =N17-('Udgifter (Forecast)'!M67+'Udgifter (Forecast)'!M72+'Udgifter (Forecast)'!M74) -> 6400 | R17: =Q17/P17 -> 96 | S17: 2029
A18: Æg | B18: =B13+365 -> 47119 | C18: =EDATE(B18,12) -> 47484 | D18: Indtægt | E18: Variabel | F18: Æg | G18: Stk | H18: 2.5 | I18: ='Udgifter (Forecast)'!H73*250 -> 70500 | J18: =DATEDIF(B18,C18,"m")+1 -> 13 | K18: =I18*H18/J18 -> 13557.692 | L18: =K18-(K18/5) -> 10846.154 | M18: =IF(D18="Indtægt",K18*J18,-K18*J18) -> 176250 | N18: =L18*J18 -> 141000 | O18: =3/60 -> 0.05 | P18: =O18*I18 -> 3525 | Q18: =N18-('Udgifter (Forecast)'!M65+'Udgifter (Forecast)'!M73+'Udgifter (Forecast)'!M75+'Udgifter (Forecast)'!M82+'Udgifter (Forecast)'!M84+'Udgifter (Forecast)'!M85) -> 117704.12 | R18: =Q18/P18 -> 33.39124 | S18: 2029
A19: Kvæg | B19: =B14+365 -> 47453 | C19: =EDATE(B19,0) -> 47453 | D19: Indtægt | E19: Variabel | F19: Kvæg | G19: Stk | H19: 12000 | I19: 1 | J19: =DATEDIF(B19,C19,"m")+1 -> 1 | K19: =I19*H19/J19 -> 12000 | L19: =K19-(K19/5) -> 9600 | M19: =IF(D19="Indtægt",K19*J19,-K19*J19) -> 12000 | N19: =L19*J19 -> 9600 | O19: =160/10 -> 16 | P19: =(('Udgifter (Forecast)'!H77+'Udgifter (Forecast)'!H78)/2)*O19 -> 152 | Q19: =N19-('Udgifter (Forecast)'!M66+'Udgifter (Forecast)'!M71+'Udgifter (Forecast)'!M76+'Udgifter (Forecast)'!M77+'Udgifter (Forecast)'!M78) -> -2272 | R19: =Q19/P19 -> -14.947368 | S19: 2029
A20: Jordbær | B20: =B15+365 -> 47270 | C20: =EDATE(B20,3) -> 47362 | D20: Indtægt | E20: Variabel | F20: Jordbær | G20: kg | H20: 50 | I20: =3500*0.6 -> 2100 | J20: =DATEDIF(B20,C20,"m")+1 -> 4 | K20: =I20*H20/J20 -> 26250 | L20: =K20-(K20/5) -> 21000 | M20: =IF(D20="Indtægt",K20*J20,-K20*J20) -> 105000 | N20: =L20*J20 -> 84000 | O20: =50/1000 -> 0.05 | P20: =O20*(I20/60%) -> 175 | Q20: =N20-('Udgifter (Forecast)'!M79+'Udgifter (Forecast)'!M80) -> 80928 | R20: =Q20/P20 -> 462.44571 | S20: 2029
A21: Kartofler | B21: =B16+365 -> 47270 | C21: =EDATE(B21,3) -> 47362 | D21: Indtægt | E21: Variabel | F21: Kartofler | G21: kg | H21: 12 | I21: 3000 | J21: =DATEDIF(B21,C21,"m")+1 -> 4 | K21: =I21*H21/J21 -> 9000 | L21: =K21-(K21/5) -> 7200 | M21: =IF(D21="Indtægt",K21*J21,-K21*J21) -> 36000 | N21: =L21*J21 -> 28800 | O21: =5/60 -> 0.083333333 | P21: =O21*I21 -> 250 | Q21: =N21-('Udgifter (Forecast)'!M81+'Udgifter (Forecast)'!M83) -> 27000 | R21: =Q21/P21 -> 108 | S21: 2029
A22: Kyllinger | B22: =B17+365 -> 47788 | C22: =EDATE(B22,0) -> 47788 | D22: Indtægt | E22: Variabel | F22: Kyllinger | G22: Stk | H22: 200 | I22: ='Udgifter (Forecast)'!H93/2 -> 100 | J22: =DATEDIF(B22,C22,"m")+1 -> 1 | K22: =I22*H22/J22 -> 20000 | L22: =K22-(K22/5) -> 16000 | M22: =IF(D22="Indtægt",K22*J22,-K22*J22) -> 20000 | N22: =L22*J22 -> 16000 | O22: =40/60 -> 0.66666667 | P22: =O22*I22 -> 66.666667 | Q22: =N22-('Udgifter (Forecast)'!M88+'Udgifter (Forecast)'!M93+'Udgifter (Forecast)'!M95) -> 6400 | R22: =Q22/P22 -> 96 | S22: 2030
A23: Æg | B23: =B18+365 -> 47484 | C23: =EDATE(B23,12) -> 47849 | D23: Indtægt | E23: Variabel | F23: Æg | G23: Stk | H23: 2.5 | I23: ='Udgifter (Forecast)'!H94*250 -> 75000 | J23: =DATEDIF(B23,C23,"m")+1 -> 13 | K23: =I23*H23/J23 -> 14423.077 | L23: =K23-(K23/5) -> 11538.462 | M23: =IF(D23="Indtægt",K23*J23,-K23*J23) -> 187500 | N23: =L23*J23 -> 150000 | O23: =3/60 -> 0.05 | P23: =O23*I23 -> 3750 | Q23: =N23-('Udgifter (Forecast)'!M86+'Udgifter (Forecast)'!M94+'Udgifter (Forecast)'!M96+'Udgifter (Forecast)'!M103+'Udgifter (Forecast)'!M105+'Udgifter (Forecast)'!M106) -> 125402 | R23: =Q23/P23 -> 33.440533 | S23: 2030
A24: Kvæg | B24: =B19+365 -> 47818 | C24: =EDATE(B24,0) -> 47818 | D24: Indtægt | E24: Variabel | F24: Kvæg | G24: Stk | H24: 12000 | I24: 3 | J24: =DATEDIF(B24,C24,"m")+1 -> 1 | K24: =I24*H24/J24 -> 36000 | L24: =K24-(K24/5) -> 28800 | M24: =IF(D24="Indtægt",K24*J24,-K24*J24) -> 36000 | N24: =L24*J24 -> 28800 | O24: =160/10 -> 16 | P24: =(('Udgifter (Forecast)'!H98+'Udgifter (Forecast)'!H99)/2)*O24 -> 200 | Q24: =N24-('Udgifter (Forecast)'!M87+'Udgifter (Forecast)'!M92+'Udgifter (Forecast)'!M97+'Udgifter (Forecast)'!M98+'Udgifter (Forecast)'!M99) -> 6208 | R24: =Q24/P24 -> 31.04 | S24: 2030
A25: Jordbær | B25: =B20+365 -> 47635 | C25: =EDATE(B25,3) -> 47727 | D25: Indtægt | E25: Variabel | F25: Jordbær | G25: kg | H25: 50 | I25: =3500*0.6 -> 2100 | J25: =DATEDIF(B25,C25,"m")+1 -> 4 | K25: =I25*H25/J25 -> 26250 | L25: =K25-(K25/5) -> 21000 | M25: =IF(D25="Indtægt",K25*J25,-K25*J25) -> 105000 | N25: =L25*J25 -> 84000 | O25: =50/1000 -> 0.05 | P25: =O25*(I25/60%) -> 175 | Q25: =N25-('Udgifter (Forecast)'!M100+'Udgifter (Forecast)'!M101) -> 80928 | R25: =Q25/P25 -> 462.44571 | S25: 2030
A26: Kartofler | B26: =B21+365 -> 47635 | C26: =EDATE(B26,3) -> 47727 | D26: Indtægt | E26: Variabel | F26: Kartofler | G26: kg | H26: 12 | I26: 3000 | J26: =DATEDIF(B26,C26,"m")+1 -> 4 | K26: =I26*H26/J26 -> 9000 | L26: =K26-(K26/5) -> 7200 | M26: =IF(D26="Indtægt",K26*J26,-K26*J26) -> 36000 | N26: =L26*J26 -> 28800 | O26: =5/60 -> 0.083333333 | P26: =O26*I26 -> 250 | Q26: =N26-('Udgifter (Forecast)'!M102+'Udgifter (Forecast)'!M104) -> 27000 | R26: =Q26/P26 -> 108 | S26: 2030
A27: Kyllinger | B27: =B22+365 -> 48153 | C27: =EDATE(B27,0) -> 48153 | D27: Indtægt | E27: Variabel | F27: Kyllinger | G27: Stk | H27: 200 | I27: ='Udgifter (Forecast)'!H114/2 -> 100 | J27: =DATEDIF(B27,C27,"m")+1 -> 1 | K27: =I27*H27/J27 -> 20000 | L27: =K27-(K27/5) -> 16000 | M27: =IF(D27="Indtægt",K27*J27,-K27*J27) -> 20000 | N27: =L27*J27 -> 16000 | O27: =40/60 -> 0.66666667 | P27: =O27*I27 -> 66.666667 | Q27: =N27-('Udgifter (Forecast)'!M77+'Udgifter (Forecast)'!M82+'Udgifter (Forecast)'!M84) -> 1227 | R27: =Q27/P27 -> 18.405 | S27: 2031
A28: Æg | B28: =B23+365 -> 47849 | C28: =EDATE(B28,12) -> 48214 | D28: Indtægt | E28: Variabel | F28: Æg | G28: Stk | H28: 2.5 | I28: ='Udgifter (Forecast)'!H115*250 -> 75000 | J28: =DATEDIF(B28,C28,"m")+1 -> 13 | K28: =I28*H28/J28 -> 14423.077 | L28: =K28-(K28/5) -> 11538.462 | M28: =IF(D28="Indtægt",K28*J28,-K28*J28) -> 187500 | N28: =L28*J28 -> 150000 | O28: =3/60 -> 0.05 | P28: =O28*I28 -> 3750 | Q28: =N28-('Udgifter (Forecast)'!M75+'Udgifter (Forecast)'!M83+'Udgifter (Forecast)'!M85+'Udgifter (Forecast)'!M92+'Udgifter (Forecast)'!M94+'Udgifter (Forecast)'!M95) -> 136038.4 | R28: =Q28/P28 -> 36.276907 | S28: 2031
A29: Kvæg | B29: =B24+365 -> 48183 | C29: =EDATE(B29,0) -> 48183 | D29: Indtægt | E29: Variabel | F29: Kvæg | G29: Stk | H29: 12000 | J29: =DATEDIF(B29,C29,"m")+1 -> 1 | K29: =I29*H29/J29 -> 0 | L29: =K29-(K29/5) -> 0 | M29: =IF(D29="Indtægt",K29*J29,-K29*J29) -> 0 | N29: =L29*J29 -> 0 | O29: =160/10 -> 16 | P29: =(('Udgifter (Forecast)'!H87+'Udgifter (Forecast)'!H88)/2)*O29 -> 3968 | Q29: =N29-('Udgifter (Forecast)'!M76+'Udgifter (Forecast)'!M81+'Udgifter (Forecast)'!M86+'Udgifter (Forecast)'!M87+'Udgifter (Forecast)'!M88) -> -6888 | R29: =Q29/P29 -> -1.7358871 | S29: 2031
A30: Jordbær | B30: =B25+365 -> 48000 | C30: =EDATE(B30,3) -> 48092 | D30: Indtægt | E30: Variabel | F30: Jordbær | G30: kg | H30: 50 | I30: =3500*0.6 -> 2100 | J30: =DATEDIF(B30,C30,"m")+1 -> 4 | K30: =I30*H30/J30 -> 26250 | L30: =K30-(K30/5) -> 21000 | M30: =IF(D30="Indtægt",K30*J30,-K30*J30) -> 105000 | N30: =L30*J30 -> 84000 | O30: =50/1000 -> 0.05 | P30: =O30*(I30/60%) -> 175 | Q30: =N30-('Udgifter (Forecast)'!M89+'Udgifter (Forecast)'!M90) -> 79972.8 | R30: =Q30/P30 -> 456.98743 | S30: 2031
A31: Kartofler | B31: =B26+365 -> 48000 | C31: =EDATE(B31,3) -> 48092 | D31: Indtægt | E31: Variabel | F31: Kartofler | G31: kg | H31: 12 | I31: 3000 | J31: =DATEDIF(B31,C31,"m")+1 -> 4 | K31: =I31*H31/J31 -> 9000 | L31: =K31-(K31/5) -> 7200 | M31: =IF(D31="Indtægt",K31*J31,-K31*J31) -> 36000 | N31: =L31*J31 -> 28800 | O31: =5/60 -> 0.083333333 | P31: =O31*I31 -> 250 | Q31: =N31-('Udgifter (Forecast)'!M91+'Udgifter (Forecast)'!M93) -> 17120 | R31: =Q31/P31 -> 68.48 | S31: 2031

Sheet Udgifter (Forecast)
A1: Aktivitet | B1: Månede start | C1: Månede slut | D1: Type indtægt/ udgift | E1: Kategori | F1: Enhed | G1: Enhedspris i DKK (m. moms) | H1: Enheder total | I1: Enheder fordelt på antal mdr | J1: Udgift pr mdr (m. moms) | K1: Udgift pr mdr (u. moms) | L1: Udgift pr år (m. moms) | M1: Udgift pr år (u. moms) | N1: Årstal
A2: El til hegn (Høns) | B2: 46023 | C2: =EDATE(B2,12) -> 46388 | D2: Kapacitet | E2: Æg | F2: kWh | G2: 2.5 | H2: =4*12 -> 48 | I2: =DATEDIF(B2,C2,"m") -> 12 | J2: =H2*G2/I2 -> 10 | K2: =J2-(J2/5) -> 8 | L2: =J2*I2 -> 120 | M2: =K2*I2 -> 96 | N2: 2026
A3: El til hegn (Kvæg) | B3: 46023 | C3: =EDATE(B3,12) -> 46388 | D3: Kapacitet | E3: Kvæg | F3: kWh | G3: 2.5 | H3: =8*12 -> 96 | I3: =DATEDIF(B3,C3,"m") -> 12 | J3: =H3*G3/I3 -> 20 | K3: =J3-(J3/5) -> 16 | L3: =J3*I3 -> 240 | M3: =K3*I3 -> 192 | N3: 2026
A4: El til 2 varmelamper (Kyllinger) | B4: 46174 | C4: =EDATE(B4,2) -> 46235 | D4: Kapacitet | E4: Kyllinger | F4: kWh | G4: 2.5 | H4: 400 | I4: =DATEDIF(B4,C4,"m") -> 2 | J4: =H4*G4/I4 -> 500 | K4: =J4-(J4/5) -> 400 | L4: =J4*I4 -> 1000 | M4: =K4*I4 -> 800 | N4: 2026
A5: Administrativt (Dinero og erhvervskonto) | B5: 46023 | C5: =EDATE(B5,12) -> 46388 | D5: Kapacitet | E5: Generelt | F5: Stk | G5: 1500 | H5: 1 | I5: =DATEDIF(B5,C5,"m") -> 12 | J5: =H5*G5/I5 -> 125 | K5: =J5-(J5/5) -> 100 | L5: =J5*I5 -> 1500 | M5: =K5*I5 -> 1200 | N5: 2026
A6: Hjemmeside og webshop | B6: 46023 | C6: =EDATE(B6,12) -> 46388 | D6: Kapacitet | E6: Generelt | F6: Stk | G6: =(35*6.7)+5 -> 239.5 | H6: 5 | I6: =DATEDIF(B6,C6,"m") -> 12 | J6: =H6*G6/I6 -> 99.791667 | K6: =J6-(J6/5) -> 79.833333 | L6: =J6*I6 -> 1197.5 | M6: =K6*I6 -> 958 | N6: 2026
A7: Forsikringer | B7: 46023 | C7: =EDATE(B7,12) -> 46388 | D7: Kapacitet | E7: Generelt | F7: Stk | G7: 4000 | H7: 1 | I7: =DATEDIF(B7,C7,"m") -> 12 | J7: =H7*G7/I7 -> 333.33333 | K7: =J7-(J7/5) -> 266.66667 | L7: =J7*I7 -> 4000 | M7: =K7*I7 -> 3200 | N7: 2026
A8: Veterinær og medicin (Årsrapport) | B8: 46357 | C8: =EDATE(B8,1) -> 46388 | D8: Kapacitet | E8: Kvæg | F8: Stk | G8: 1500 | H8: 1 | I8: =DATEDIF(B8,C8,"m") -> 1 | J8: =H8*G8/I8 -> 1500 | K8: =J8-(J8/5) -> 1200 | L8: =J8*I8 -> 1500 | M8: =K8*I8 -> 1200 | N8: 2026
A9: Foder til kyllinger (Hele perioden) | B9: 46174 | C9: =EDATE(B9,4) -> 46296 | D9: Variabel | E9: Kyllinger | F9: Årligt forbrug/kylling | G9: =53 -> 53 | H9: ='Indtægter (Forecast)'!I2*2 -> 50 | I9: =DATEDIF(B9,C9,"m") -> 4 | J9: =H9*G9/I9 -> 662.5 | K9: =(J9-J9/5) -> 530 | L9: =J9*I9 -> 2650 | M9: =K9*I9 -> 2120 | N9: 2026
A10: Foder til høns (Gule foderærter og østers) | B10: ='Indtægter (Forecast)'!B3 -> 46327 | C10: =EDATE(B10,1) -> 46357 | D10: Variabel | E10: Æg | F10: Årligt forbrug/høne | G10: =2.4*12 -> 28.8 | H10: 82 | I10: =DATEDIF(B10,C10,"m") -> 1 | J10: =H10*G10/I10 -> 2361.6 | K10: =(J10-J10/5) -> 1889.28 | L10: =J10*I10 -> 2361.6 | M10: =K10*I10 -> 1889.28 | N10: 2026
A11: Strøelse til kyllinger (Spåner de første 2 uger) | B11: =B9 -> 46174 | C11: =EDATE(B11,2) -> 46235 | D11: Variabel | E11: Kyllinger | F11: Årligt forbrug/kylling | G11: 2 | H11: =H9 -> 50 | I11: =DATEDIF(B11,C11,"m") -> 2 | J11: =H11*G11/I11 -> 50 | K11: =(J11-J11/5) -> 40 | L11: =J11*I11 -> 100 | M11: =K11*I11 -> 80 | N11: 2026
A12: Strøelse til høns (Sand og eget halm) | B12: =B10 -> 46327 | C12: =EDATE(B12,1) -> 46357 | D12: Variabel | E12: Æg | F12: Årligt forbrug/høne | G12: 16 | H12: =H10 -> 82 | I12: =DATEDIF(B12,C12,"m") -> 1 | J12: =H12*G12/I12 -> 1312 | K12: =(J12-J12/5) -> 1049.6 | L12: =J12*I12 -> 1312 | M12: =K12*I12 -> 1049.6 | N12: 2026
A13: Slagt af kvæg | B13: ='Indtægter (Forecast)'!B4 -> 46143 | C13: =EDATE(B13,1) -> 46174 | D13: Variabel | E13: Kvæg | F13: Stk | G13: 5500 | H13: 2 | I13: =DATEDIF(B13,C13,"m") -> 1 | J13: =H13*G13/I13 -> 11000 | K13: =(J13-J13/5) -> 8800 | L13: =J13*I13 -> 11000 | M13: =K13*I13 -> 8800 | N13: 2026
A14: Foder til kvæg (Inden slagt) | B14: 46023 | C14: =EDATE(B14,4) -> 46143 | D14: Variabel | E14: Kvæg | F14: Stk | G14: 400 | H14: 2 | I14: =DATEDIF(B14,C14,"m") -> 4 | J14: =H14*G14/I14 -> 200 | K14: =(J14-J14/5) -> 160 | L14: =J14*I14 -> 800 | M14: =K14*I14 -> 640 | N14: 2026
A15: Foder til kvæg (Efter slagt) | B15: 46296 | C15: =EDATE(B15,3) -> 46388 | D15: Variabel | E15: Kvæg | F15: Stk | G15: 400 | H15: 3 | I15: =DATEDIF(B15,C15,"m") -> 3 | J15: =H15*G15/I15 -> 400 | K15: =(J15-J15/5) -> 320 | L15: =J15*I15 -> 1200 | M15: =K15*I15 -> 960 | N15: 2026
A16: Halm til jordbær | B16: ='Indtægter (Forecast)'!B5 -> 46174 | C16: =EDATE(B16,3) -> 46266 | D16: Variabel | E16: Jordbær | F16: Stk | G16: 0.12 | H16: ='Indtægter (Forecast)'!I5 -> 0 | I16: =DATEDIF(B16,C16,"m") -> 3 | J16: =H16*G16/I16 -> 0 | K16: =(J16-J16/5) -> 0 | L16: =J16*I16 -> 0 | M16: =K16*I16 -> 0 | N16: 2026
A17: Emballage til jordbær | B17: 46357 | C17: =EDATE(B17,1) -> 46388 | D17: Variabel | E17: Jordbær | F17: Stk | G17: 0.7 | H17: =2*'Indtægter (Forecast)'!I5 -> 0 | I17: =DATEDIF(B17,C17,"m") -> 1 | J17: =H17*G17/I17 -> 0 | K17: =(J17-J17/5) -> 0 | L17: =J17*I17 -> 0 | M17: =K17*I17 -> 0 | N17: 2026
A18: Emballage til kartofler | B18: =B17 -> 46357 | C18: =EDATE(B18,1) -> 46388 | D18: Variabel | E18: Kartofler | F18: Stk | G18: 0.7 | H18: ='Indtægter (Forecast)'!I6/2 -> 0 | I18: =DATEDIF(B18,C18,"m") -> 1 | J18: =H18*G18/I18 -> 0 | K18: =(J18-J18/5) -> 0 | L18: =J18*I18 -> 0 | M18: =K18*I18 -> 0 | N18: 2026
A19: Emballage til æg | B19: =B18 -> 46357 | C19: =EDATE(B19,1) -> 46388 | D19: Variabel | E19: Æg | F19: Stk | G19: 1.8 | H19: 0 | I19: =DATEDIF(B19,C19,"m") -> 1 | J19: =H19*G19/I19 -> 0 | K19: =(J19-J19/5) -> 0 | L19: =J19*I19 -> 0 | M19: =K19*I19 -> 0 | N19: 2026
A20: Indkøb af læggekartofler | B20: 46054 | C20: =EDATE(B20,1) -> 46082 | D20: Variabel | E20: Kartofler | F20: Stk | G20: 0.2 | H20: 0 | I20: =DATEDIF(B20,C20,"m") -> 1 | J20: =H20*G20/I20 -> 0 | K20: =(J20-J20/5) -> 0 | L20: =J20*I20 -> 0 | M20: =K20*I20 -> 0 | N20: 2026
A21: Diesel + indkøb af korn (Såsæd) | B21: 46054 | C21: =EDATE(B21,1) -> 46082 | D21: Variabel | E21: Æg | F21: ha | G21: 1600 | H21: 0 | I21: =DATEDIF(B21,C21,"m") -> 1 | J21: =H21*G21/I21 -> 0 | K21: =(J21-J21/5) -> 0 | L21: =J21*I21 -> 0 | M21: =K21*I21 -> 0 | N21: 2026
A22: Diesel + indkøb af honningurt (Såsæd) | B22: 46054 | C22: =EDATE(B22,1) -> 46082 | D22: Variabel | E22: Æg | F22: ha | G22: 1900 | H22: 0 | I22: =DATEDIF(B22,C22,"m") -> 1 | J22: =H22*G22/I22 -> 0 | K22: =(J22-J22/5) -> 0 | L22: =J22*I22 -> 0 | M22: =K22*I22 -> 0 | N22: 2026
A23: El til hegn (Høns) | B23: 46388 | C23: =EDATE(B23,12) -> 46753 | D23: Kapacitet | E23: Æg | F23: kWh | G23: 2.5 | H23: =4*12 -> 48 | I23: =DATEDIF(B23,C23,"m") -> 12 | J23: =H23*G23/I23 -> 10 | K23: =J23-(J23/5) -> 8 | L23: =J23*I23 -> 120 | M23: =K23*I23 -> 96 | N23: 2027
A24: El til hegn (Kvæg) | B24: 46388 | C24: =EDATE(B24,12) -> 46753 | D24: Kapacitet | E24: Kvæg | F24: kWh | G24: 2.5 | H24: =8*12 -> 96 | I24: =DATEDIF(B24,C24,"m") -> 12 | J24: =H24*G24/I24 -> 20 | K24: =J24-(J24/5) -> 16 | L24: =J24*I24 -> 240 | M24: =K24*I24 -> 192 | N24: 2027
A25: El til 2 varmelamper (Kyllinger) | B25: 46539 | C25: =EDATE(B25,2) -> 46600 | D25: Kapacitet | E25: Kyllinger | F25: kWh | G25: 2.5 | H25: 400 | I25: =DATEDIF(B25,C25,"m") -> 2 | J25: =H25*G25/I25 -> 500 | K25: =J25-(J25/5) -> 400 | L25: =J25*I25 -> 1000 | M25: =K25*I25 -> 800 | N25: 2027
A26: Administrativt (Dinero og erhvervskonto) | B26: 46388 | C26: =EDATE(B26,12) -> 46753 | D26: Kapacitet | E26: Generelt | F26: Stk | G26: 1500 | H26: 1 | I26: =DATEDIF(B26,C26,"m") -> 12 | J26: =H26*G26/I26 -> 125 | K26: =J26-(J26/5) -> 100 | L26: =J26*I26 -> 1500 | M26: =K26*I26 -> 1200 | N26: 2027
A27: Hjemmeside og webshop | B27: 46388 | C27: =EDATE(B27,12) -> 46753 | D27: Kapacitet | E27: Generelt | F27: Stk | G27: =(35*6.7)+60 -> 294.5 | H27: 12 | I27: =DATEDIF(B27,C27,"m") -> 12 | J27: =H27*G27/I27 -> 294.5 | K27: =J27-(J27/5) -> 235.6 | L27: =J27*I27 -> 3534 | M27: =K27*I27 -> 2827.2 | N27: 2027
A28: Forsikringer | B28: 46388 | C28: =EDATE(B28,12) -> 46753 | D28: Kapacitet | E28: Generelt | F28: Stk | G28: 4000 | H28: 1 | I28: =DATEDIF(B28,C28,"m") -> 12 | J28: =H28*G28/I28 -> 333.33333 | K28: =J28-(J28/5) -> 266.66667 | L28: =J28*I28 -> 4000 | M28: =K28*I28 -> 3200 | N28: 2027
A29: Veterinær og medicin (Årsrapport) | B29: 46722 | C29: =EDATE(B29,1) -> 46753 | D29: Kapacitet | E29: Kvæg | F29: Stk | G29: 1500 | H29: 1 | I29: =DATEDIF(B29,C29,"m") -> 1 | J29: =H29*G29/I29 -> 1500 | K29: =J29-(J29/5) -> 1200 | L29: =J29*I29 -> 1500 | M29: =K29*I29 -> 1200 | N29: 2027
A30: Foder til kyllinger (Hele perioden) | B30: 46539 | C30: =EDATE(B30,4) -> 46661 | D30: Variabel | E30: Kyllinger | F30: Årligt forbrug/kylling | G30: =53 -> 53 | H30: 200 | I30: =DATEDIF(B30,C30,"m") -> 4 | J30: =H30*G30/I30 -> 2650 | K30: =(J30-J30/5) -> 2120 | L30: =J30*I30 -> 10600 | M30: =K30*I30 -> 8480 | N30: 2027
A31: Foder til høns (Gule foderærter og østers) | B31: 46388 | C31: =EDATE(B31,12) -> 46753 | D31: Variabel | E31: Æg | F31: Årligt forbrug/høne | G31: =2.4*12 -> 28.8 | H31: 82 | I31: =DATEDIF(B31,C31,"m") -> 12 | J31: =H31*G31/I31 -> 196.8 | K31: =(J31-J31/5) -> 157.44 | L31: =J31*I31 -> 2361.6 | M31: =K31*I31 -> 1889.28 | N31: 2027
A32: Strøelse til kyllinger (Spåner de første 2 uger) | B32: =B30 -> 46539 | C32: =EDATE(B32,2) -> 46600 | D32: Variabel | E32: Kyllinger | F32: Årligt forbrug/kylling | G32: 2 | H32: =H30 -> 200 | I32: =DATEDIF(B32,C32,"m") -> 2 | J32: =H32*G32/I32 -> 200 | K32: =(J32-J32/5) -> 160 | L32: =J32*I32 -> 400 | M32: =K32*I32 -> 320 | N32: 2027
A33: Strøelse til høns (Sand og eget halm) | B33: 46388 | C33: =EDATE(B33,12) -> 46753 | D33: Variabel | E33: Æg | F33: Årligt forbrug/høne | G33: 16 | H33: =H31 -> 82 | I33: =DATEDIF(B33,C33,"m") -> 12 | J33: =H33*G33/I33 -> 109.33333 | K33: =(J33-J33/5) -> 87.466667 | L33: =J33*I33 -> 1312 | M33: =K33*I33 -> 1049.6 | N33: 2027
A34: Slagt af kvæg | B34: 46722 | C34: =EDATE(B34,1) -> 46753 | D34: Variabel | E34: Kvæg | F34: Stk | G34: 5500 | H34: 1 | I34: =DATEDIF(B34,C34,"m") -> 1 | J34: =H34*G34/I34 -> 5500 | K34: =(J34-J34/5) -> 4400 | L34: =J34*I34 -> 5500 | M34: =K34*I34 -> 4400 | N34: 2027
A35: Foder til kvæg (Inden slagt) | B35: 46388 | C35: =EDATE(B35,4) -> 46508 | D35: Variabel | E35: Kvæg | F35: Stk | G35: 400 | H35: 5 | I35: =DATEDIF(B35,C35,"m") -> 4 | J35: =H35*G35/I35 -> 500 | K35: =(J35-J35/5) -> 400 | L35: =J35*I35 -> 2000 | M35: =K35*I35 -> 1600 | N35: 2027
A36: Foder til kvæg (Efter slagt) | B36: 46661 | C36: =EDATE(B36,3) -> 46753 | D36: Variabel | E36: Kvæg | F36: Stk | G36: 400 | H36: =H35-H34 -> 4 | I36: =DATEDIF(B36,C36,"m") -> 3 | J36: =H36*G36/I36 -> 533.33333 | K36: =(J36-J36/5) -> 426.66667 | L36: =J36*I36 -> 1600 | M36: =K36*I36 -> 1280 | N36: 2027
A37: Halm til jordbær | B37: 46508 | C37: =EDATE(B37,3) -> 46600 | D37: Variabel | E37: Jordbær | F37: Stk | G37: 0.12 | H37: 4000 | I37: =DATEDIF(B37,C37,"m") -> 3 | J37: =H37*G37/I37 -> 160 | K37: =(J37-J37/5) -> 128 | L37: =J37*I37 -> 480 | M37: =K37*I37 -> 384 | N37: 2027
A38: Emballage til jordbær | B38: 46722 | C38: =EDATE(B38,1) -> 46753 | D38: Variabel | E38: Jordbær | F38: Stk | G38: 0.7 | H38: =0.6*H37*2 -> 4800 | I38: =DATEDIF(B38,C38,"m") -> 1 | J38: =H38*G38/I38 -> 3360 | K38: =(J38-J38/5) -> 2688 | L38: =J38*I38 -> 3360 | M38: =K38*I38 -> 2688 | N38: 2027
A39: Emballage til kartofler | B39: =B38 -> 46722 | C39: =EDATE(B39,1) -> 46753 | D39: Variabel | E39: Kartofler | F39: Stk | G39: 0.7 | H39: =H41 -> 2500 | I39: =DATEDIF(B39,C39,"m") -> 1 | J39: =H39*G39/I39 -> 1750 | K39: =(J39-J39/5) -> 1400 | L39: =J39*I39 -> 1750 | M39: =K39*I39 -> 1400 | N39: 2027
A40: Emballage til æg | B40: =B39 -> 46722 | C40: =EDATE(B40,1) -> 46753 | D40: Variabel | E40: Æg | F40: Stk | G40: 1.8 | H40: =H31*(250/300)*365/12 -> 2078.4722 | I40: =DATEDIF(B40,C40,"m") -> 1 | J40: =H40*G40/I40 -> 3741.25 | K40: =(J40-J40/5) -> 2993 | L40: =J40*I40 -> 3741.25 | M40: =K40*I40 -> 2993 | N40: 2027
A41: Indkøb af læggekartofler | B41: 46419 | C41: =EDATE(B41,1) -> 46447 | D41: Variabel | E41: Kartofler | F41: Stk | G41: 0.2 | H41: 2500 | I41: =DATEDIF(B41,C41,"m") -> 1 | J41: =H41*G41/I41 -> 500 | K41: =(J41-J41/5) -> 400 | L41: =J41*I41 -> 500 | M41: =K41*I41 -> 400 | N41: 2027
A42: Diesel + indkøb af korn (Såsæd) | B42: 46419 | C42: =EDATE(B42,1) -> 46447 | D42: Variabel | E42: Æg | F42: ha | G42: 1600 | H42: 1 | I42: =DATEDIF(B42,C42,"m") -> 1 | J42: =H42*G42/I42 -> 1600 | K42: =(J42-J42/5) -> 1280 | L42: =J42*I42 -> 1600 | M42: =K42*I42 -> 1280 | N42: 2027
A43: Diesel + indkøb af honningurt (Såsæd) | B43: 46419 | C43: =EDATE(B43,1) -> 46447 | D43: Variabel | E43: Æg | F43: ha | G43: 1900 | H43: 1 | I43: =DATEDIF(B43,C43,"m") -> 1 | J43: =H43*G43/I43 -> 1900 | K43: =(J43-J43/5) -> 1520 | L43: =J43*I43 -> 1900 | M43: =K43*I43 -> 1520 | N43: 2027
A44: El til hegn (Høns) | B44: =B23+365 -> 46753 | C44: =EDATE(B44,12) -> 47119 | D44: Kapacitet | E44: Æg | F44: kWh | G44: 2.5 | H44: =4*12 -> 48 | I44: =DATEDIF(B44,C44,"m") -> 12 | J44: =H44*G44/I44 -> 10 | K44: =J44-(J44/5) -> 8 | L44: =J44*I44 -> 120 | M44: =K44*I44 -> 96 | N44: 2028
A45: El til hegn (Kvæg) | B45: =B24+365 -> 46753 | C45: =EDATE(B45,12) -> 47119 | D45: Kapacitet | E45: Kvæg | F45: kWh | G45: 2.5 | H45: =8*12 -> 96 | I45: =DATEDIF(B45,C45,"m") -> 12 | J45: =H45*G45/I45 -> 20 | K45: =J45-(J45/5) -> 16 | L45: =J45*I45 -> 240 | M45: =K45*I45 -> 192 | N45: 2028
A46: El til 2 varmelamper (Kyllinger) | B46: =B25+365 -> 46904 | C46: =EDATE(B46,2) -> 46965 | D46: Kapacitet | E46: Kyllinger | F46: kWh | G46: 2.5 | H46: 400 | I46: =DATEDIF(B46,C46,"m") -> 2 | J46: =H46*G46/I46 -> 500 | K46: =J46-(J46/5) -> 400 | L46: =J46*I46 -> 1000 | M46: =K46*I46 -> 800 | N46: 2028
A47: Administrativt (Dinero og erhvervskonto) | B47: =B26+365 -> 46753 | C47: =EDATE(B47,12) -> 47119 | D47: Kapacitet | E47: Generelt | F47: Stk | G47: 1500 | H47: 1 | I47: =DATEDIF(B47,C47,"m") -> 12 | J47: =H47*G47/I47 -> 125 | K47: =J47-(J47/5) -> 100 | L47: =J47*I47 -> 1500 | M47: =K47*I47 -> 1200 | N47: 2028
A48: Hjemmeside og webshop | B48: =B27+365 -> 46753 | C48: =EDATE(B48,12) -> 47119 | D48: Kapacitet | E48: Generelt | F48: Stk | G48: =(35*6.7)+60 -> 294.5 | H48: 12 | I48: =DATEDIF(B48,C48,"m") -> 12 | J48: =H48*G48/I48 -> 294.5 | K48: =J48-(J48/5) -> 235.6 | L48: =J48*I48 -> 3534 | M48: =K48*I48 -> 2827.2 | N48: 2028
A49: Forsikringer | B49: =B28+365 -> 46753 | C49: =EDATE(B49,12) -> 47119 | D49: Kapacitet | E49: Generelt | F49: Stk | G49: 4000 | H49: 1 | I49: =DATEDIF(B49,C49,"m") -> 12 | J49: =H49*G49/I49 -> 333.33333 | K49: =J49-(J49/5) -> 266.66667 | L49: =J49*I49 -> 4000 | M49: =K49*I49 -> 3200 | N49: 2028
A50: Veterinær og medicin (Årsrapport) | B50: =B29+365 -> 47087 | C50: =EDATE(B50,1) -> 47117 | D50: Kapacitet | E50: Kvæg | F50: Stk | G50: 1500 | H50: 1 | I50: =DATEDIF(B50,C50,"m") -> 1 | J50: =H50*G50/I50 -> 1500 | K50: =J50-(J50/5) -> 1200 | L50: =J50*I50 -> 1500 | M50: =K50*I50 -> 1200 | N50: 2028
A51: Foder til kyllinger (Hele perioden) | B51: =B30+365 -> 46904 | C51: =EDATE(B51,4) -> 47026 | D51: Variabel | E51: Kyllinger | F51: Årligt forbrug/kylling | G51: =53 -> 53 | H51: 200 | I51: =DATEDIF(B51,C51,"m") -> 3 | J51: =H51*G51/I51 -> 3533.3333 | K51: =(J51-J51/5) -> 2826.6667 | L51: =J51*I51 -> 10600 | M51: =K51*I51 -> 8480 | N51: 2028
A52: Foder til høns (Gule foderærter og østers) | B52: =B31+365 -> 46753 | C52: =EDATE(B52,12) -> 47119 | D52: Variabel | E52: Æg | F52: Årligt forbrug/høne | G52: =2.4*12 -> 28.8 | H52: 182 | I52: =DATEDIF(B52,C52,"m") -> 12 | J52: =H52*G52/I52 -> 436.8 | K52: =(J52-J52/5) -> 349.44 | L52: =J52*I52 -> 5241.6 | M52: =K52*I52 -> 4193.28 | N52: 2028
A53: Strøelse til kyllinger (Spåner de første 2 uger) | B53: =B32+365 -> 46904 | C53: =EDATE(B53,2) -> 46965 | D53: Variabel | E53: Kyllinger | F53: Årligt forbrug/kylling | G53: 2 | H53: =H51 -> 200 | I53: =DATEDIF(B53,C53,"m") -> 2 | J53: =H53*G53/I53 -> 200 | K53: =(J53-J53/5) -> 160 | L53: =J53*I53 -> 400 | M53: =K53*I53 -> 320 | N53: 2028
A54: Strøelse til høns (Sand og eget halm) | B54: =B33+365 -> 46753 | C54: =EDATE(B54,12) -> 47119 | D54: Variabel | E54: Æg | F54: Årligt forbrug/høne | G54: 16 | H54: =H52 -> 182 | I54: =DATEDIF(B54,C54,"m") -> 12 | J54: =H54*G54/I54 -> 242.66667 | K54: =(J54-J54/5) -> 194.13333 | L54: =J54*I54 -> 2912 | M54: =K54*I54 -> 2329.6 | N54: 2028
A55: Slagt af kvæg | B55: =B34+365 -> 47087 | C55: =EDATE(B55,1) -> 47117 | D55: Variabel | E55: Kvæg | F55: Stk | G55: 5500 | H55: 1 | I55: =DATEDIF(B55,C55,"m") -> 1 | J55: =H55*G55/I55 -> 5500 | K55: =(J55-J55/5) -> 4400 | L55: =J55*I55 -> 5500 | M55: =K55*I55 -> 4400 | N55: 2028
A56: Foder til kvæg (Inden slagt) | B56: =B35+365 -> 46753 | C56: =EDATE(B56,4) -> 46874 | D56: Variabel | E56: Kvæg | F56: Stk | G56: 400 | H56: 7 | I56: =DATEDIF(B56,C56,"m") -> 4 | J56: =H56*G56/I56 -> 700 | K56: =(J56-J56/5) -> 560 | L56: =J56*I56 -> 2800 | M56: =K56*I56 -> 2240 | N56: 2028
A57: Foder til kvæg (Efter slagt) | B57: =B36+365 -> 47026 | C57: =EDATE(B57,3) -> 47117 | D57: Variabel | E57: Kvæg | F57: Stk | G57: 400 | H57: =H56-H55 -> 6 | I57: =DATEDIF(B57,C57,"m") -> 3 | J57: =H57*G57/I57 -> 800 | K57: =(J57-J57/5) -> 640 | L57: =J57*I57 -> 2400 | M57: =K57*I57 -> 1920 | N57: 2028
A58: Halm til jordbær | B58: =B37+365 -> 46873 | C58: =EDATE(B58,3) -> 46964 | D58: Variabel | E58: Jordbær | F58: Stk | G58: 0.12 | H58: 4000 | I58: =DATEDIF(B58,C58,"m") -> 3 | J58: =H58*G58/I58 -> 160 | K58: =(J58-J58/5) -> 128 | L58: =J58*I58 -> 480 | M58: =K58*I58 -> 384 | N58: 2028
A59: Emballage til jordbær | B59: =B38+365 -> 47087 | C59: =EDATE(B59,1) -> 47117 | D59: Variabel | E59: Jordbær | F59: Stk | G59: 0.7 | H59: =0.6*H58*2 -> 4800 | I59: =DATEDIF(B59,C59,"m") -> 1 | J59: =H59*G59/I59 -> 3360 | K59: =(J59-J59/5) -> 2688 | L59: =J59*I59 -> 3360 | M59: =K59*I59 -> 2688 | N59: 2028
A60: Emballage til kartofler | B60: =B39+365 -> 47087 | C60: =EDATE(B60,1) -> 47117 | D60: Variabel | E60: Kartofler | F60: Stk | G60: 0.7 | H60: =H62 -> 2500 | I60: =DATEDIF(B60,C60,"m") -> 1 | J60: =H60*G60/I60 -> 1750 | K60: =(J60-J60/5) -> 1400 | L60: =J60*I60 -> 1750 | M60: =K60*I60 -> 1400 | N60: 2028
A61: Emballage til æg | B61: =B40+365 -> 47087 | C61: =EDATE(B61,1) -> 47117 | D61: Variabel | E61: Æg | F61: Stk | G61: 1.8 | H61: =H52*(250/300)*365/12 -> 4613.1944 | I61: =DATEDIF(B61,C61,"m") -> 1 | J61: =H61*G61/I61 -> 8303.75 | K61: =(J61-J61/5) -> 6643 | L61: =J61*I61 -> 8303.75 | M61: =K61*I61 -> 6643 | N61: 2028
A62: Indkøb af læggekartofler | B62: =B41+365 -> 46784 | C62: =EDATE(B62,1) -> 46813 | D62: Variabel | E62: Kartofler | F62: Stk | G62: 0.2 | H62: 2500 | I62: =DATEDIF(B62,C62,"m") -> 1 | J62: =H62*G62/I62 -> 500 | K62: =(J62-J62/5) -> 400 | L62: =J62*I62 -> 500 | M62: =K62*I62 -> 400 | N62: 2028
A63: Diesel + indkøb af korn (Såsæd) | B63: =B42+365 -> 46784 | C63: =EDATE(B63,1) -> 46813 | D63: Variabel | E63: Æg | F63: ha | G63: 1600 | H63: 1 | I63: =DATEDIF(B63,C63,"m") -> 1 | J63: =H63*G63/I63 -> 1600 | K63: =(J63-J63/5) -> 1280 | L63: =J63*I63 -> 1600 | M63: =K63*I63 -> 1280 | N63: 2028
A64: Diesel + indkøb af honningurt (Såsæd) | B64: =B43+365 -> 46784 | C64: =EDATE(B64,1) -> 46813 | D64: Variabel | E64: Æg | F64: ha | G64: 1900 | H64: 1 | I64: =DATEDIF(B64,C64,"m") -> 1 | J64: =H64*G64/I64 -> 1900 | K64: =(J64-J64/5) -> 1520 | L64: =J64*I64 -> 1900 | M64: =K64*I64 -> 1520 | N64: 2028
A65: El til hegn (Høns) | B65: =B44+366 -> 47119 | C65: =EDATE(B65,12) -> 47484 | D65: Kapacitet | E65: Æg | F65: kWh | G65: 2.5 | H65: =4*12 -> 48 | I65: =DATEDIF(B65,C65,"m") -> 12 | J65: =H65*G65/I65 -> 10 | K65: =J65-(J65/5) -> 8 | L65: =J65*I65 -> 120 | M65: =K65*I65 -> 96 | N65: 2029
A66: El til hegn (Kvæg) | B66: =B45+366 -> 47119 | C66: =EDATE(B66,12) -> 47484 | D66: Kapacitet | E66: Kvæg | F66: kWh | G66: 2.5 | H66: =8*12 -> 96 | I66: =DATEDIF(B66,C66,"m") -> 12 | J66: =H66*G66/I66 -> 20 | K66: =J66-(J66/5) -> 16 | L66: =J66*I66 -> 240 | M66: =K66*I66 -> 192 | N66: 2029
A67: El til 2 varmelamper (Kyllinger) | B67: =B46+366 -> 47270 | C67: =EDATE(B67,2) -> 47331 | D67: Kapacitet | E67: Kyllinger | F67: kWh | G67: 2.5 | H67: 400 | I67: =DATEDIF(B67,C67,"m") -> 2 | J67: =H67*G67/I67 -> 500 | K67: =J67-(J67/5) -> 400 | L67: =J67*I67 -> 1000 | M67: =K67*I67 -> 800 | N67: 2029
A68: Administrativt (Dinero og erhvervskonto) | B68: =B47+366 -> 47119 | C68: =EDATE(B68,12) -> 47484 | D68: Kapacitet | E68: Generelt | F68: Stk | G68: 1500 | H68: 1 | I68: =DATEDIF(B68,C68,"m") -> 12 | J68: =H68*G68/I68 -> 125 | K68: =J68-(J68/5) -> 100 | L68: =J68*I68 -> 1500 | M68: =K68*I68 -> 1200 | N68: 2029
A69: Hjemmeside og webshop | B69: =B48+366 -> 47119 | C69: =EDATE(B69,12) -> 47484 | D69: Kapacitet | E69: Generelt | F69: Stk | G69: =(35*6.7)+60 -> 294.5 | H69: 12 | I69: =DATEDIF(B69,C69,"m") -> 12 | J69: =H69*G69/I69 -> 294.5 | K69: =J69-(J69/5) -> 235.6 | L69: =J69*I69 -> 3534 | M69: =K69*I69 -> 2827.2 | N69: 2029
A70: Forsikringer | B70: =B49+366 -> 47119 | C70: =EDATE(B70,12) -> 47484 | D70: Kapacitet | E70: Generelt | F70: Stk | G70: 4000 | H70: 1 | I70: =DATEDIF(B70,C70,"m") -> 12 | J70: =H70*G70/I70 -> 333.33333 | K70: =J70-(J70/5) -> 266.66667 | L70: =J70*I70 -> 4000 | M70: =K70*I70 -> 3200 | N70: 2029
A71: Veterinær og medicin (Årsrapport) | B71: =B50+366 -> 47453 | C71: =EDATE(B71,1) -> 47484 | D71: Kapacitet | E71: Kvæg | F71: Stk | G71: 1500 | H71: 1 | I71: =DATEDIF(B71,C71,"m") -> 1 | J71: =H71*G71/I71 -> 1500 | K71: =J71-(J71/5) -> 1200 | L71: =J71*I71 -> 1500 | M71: =K71*I71 -> 1200 | N71: 2029
A72: Foder til kyllinger (Hele perioden) | B72: =B51+366 -> 47270 | C72: =EDATE(B72,4) -> 47392 | D72: Variabel | E72: Kyllinger | F72: Årligt forbrug/kylling | G72: =53 -> 53 | H72: 200 | I72: =DATEDIF(B72,C72,"m") -> 4 | J72: =H72*G72/I72 -> 2650 | K72: =(J72-J72/5) -> 2120 | L72: =J72*I72 -> 10600 | M72: =K72*I72 -> 8480 | N72: 2029
A73: Foder til høns (Gule foderærter og østers) | B73: =B52+366 -> 47119 | C73: =EDATE(B73,12) -> 47484 | D73: Variabel | E73: Æg | F73: Årligt forbrug/høne | G73: =2.4*12 -> 28.8 | H73: 282 | I73: =DATEDIF(B73,C73,"m") -> 12 | J73: =H73*G73/I73 -> 676.8 | K73: =(J73-J73/5) -> 541.44 | L73: =J73*I73 -> 8121.6 | M73: =K73*I73 -> 6497.28 | N73: 2029
A74: Strøelse til kyllinger (Spåner de første 2 uger) | B74: =B53+366 -> 47270 | C74: =EDATE(B74,2) -> 47331 | D74: Variabel | E74: Kyllinger | F74: Årligt forbrug/kylling | G74: 2 | H74: =H72 -> 200 | I74: =DATEDIF(B74,C74,"m") -> 2 | J74: =H74*G74/I74 -> 200 | K74: =(J74-J74/5) -> 160 | L74: =J74*I74 -> 400 | M74: =K74*I74 -> 320 | N74: 2029
A75: Strøelse til høns (Sand og eget halm) | B75: =B54+366 -> 47119 | C75: =EDATE(B75,12) -> 47484 | D75: Variabel | E75: Æg | F75: Årligt forbrug/høne | G75: 16 | H75: =H73 -> 282 | I75: =DATEDIF(B75,C75,"m") -> 12 | J75: =H75*G75/I75 -> 376 | K75: =(J75-J75/5) -> 300.8 | L75: =J75*I75 -> 4512 | M75: =K75*I75 -> 3609.6 | N75: 2029
A76: Slagt af kvæg | B76: =B55+366 -> 47453 | C76: =EDATE(B76,1) -> 47484 | D76: Variabel | E76: Kvæg | F76: Stk | G76: 5500 | H76: 1 | I76: =DATEDIF(B76,C76,"m") -> 1 | J76: =H76*G76/I76 -> 5500 | K76: =(J76-J76/5) -> 4400 | L76: =J76*I76 -> 5500 | M76: =K76*I76 -> 4400 | N76: 2029
A77: Foder til kvæg (Inden slagt) | B77: =B56+366 -> 47119 | C77: =EDATE(B77,4) -> 47239 | D77: Variabel | E77: Kvæg | F77: Stk | G77: 400 | H77: 10 | I77: =DATEDIF(B77,C77,"m") -> 4 | J77: =H77*G77/I77 -> 1000 | K77: =(J77-J77/5) -> 800 | L77: =J77*I77 -> 4000 | M77: =K77*I77 -> 3200 | N77: 2029
A78: Foder til kvæg (Efter slagt) | B78: =B57+366 -> 47392 | C78: =EDATE(B78,3) -> 47484 | D78: Variabel | E78: Kvæg | F78: Stk | G78: 400 | H78: =H77-H76 -> 9 | I78: =DATEDIF(B78,C78,"m") -> 3 | J78: =H78*G78/I78 -> 1200 | K78: =(J78-J78/5) -> 960 | L78: =J78*I78 -> 3600 | M78: =K78*I78 -> 2880 | N78: 2029
A79: Halm til jordbær | B79: =B58+366 -> 47239 | C79: =EDATE(B79,3) -> 47331 | D79: Variabel | E79: Jordbær | F79: Stk | G79: 0.12 | H79: 4000 | I79: =DATEDIF(B79,C79,"m") -> 3 | J79: =H79*G79/I79 -> 160 | K79: =(J79-J79/5) -> 128 | L79: =J79*I79 -> 480 | M79: =K79*I79 -> 384 | N79: 2029
A80: Emballage til jordbær | B80: =B59+366 -> 47453 | C80: =EDATE(B80,1) -> 47484 | D80: Variabel | E80: Jordbær | F80: Stk | G80: 0.7 | H80: =0.6*H79*2 -> 4800 | I80: =DATEDIF(B80,C80,"m") -> 1 | J80: =H80*G80/I80 -> 3360 | K80: =(J80-J80/5) -> 2688 | L80: =J80*I80 -> 3360 | M80: =K80*I80 -> 2688 | N80: 2029
A81: Emballage til kartofler | B81: =B60+366 -> 47453 | C81: =EDATE(B81,1) -> 47484 | D81: Variabel | E81: Kartofler | F81: Stk | G81: 0.7 | H81: =H83 -> 2500 | I81: =DATEDIF(B81,C81,"m") -> 1 | J81: =H81*G81/I81 -> 1750 | K81: =(J81-J81/5) -> 1400 | L81: =J81*I81 -> 1750 | M81: =K81*I81 -> 1400 | N81: 2029
A82: Emballage til æg | B82: =B61+366 -> 47453 | C82: =EDATE(B82,1) -> 47484 | D82: Variabel | E82: Æg | F82: Stk | G82: 1.8 | H82: =H73*(250/300)*365/12 -> 7147.9167 | I82: =DATEDIF(B82,C82,"m") -> 1 | J82: =H82*G82/I82 -> 12866.25 | K82: =(J82-J82/5) -> 10293 | L82: =J82*I82 -> 12866.25 | M82: =K82*I82 -> 10293 | N82: 2029
A83: Indkøb af læggekartofler | B83: =B62+366 -> 47150 | C83: =EDATE(B83,1) -> 47178 | D83: Variabel | E83: Kartofler | F83: Stk | G83: 0.2 | H83: 2500 | I83: =DATEDIF(B83,C83,"m") -> 1 | J83: =H83*G83/I83 -> 500 | K83: =(J83-J83/5) -> 400 | L83: =J83*I83 -> 500 | M83: =K83*I83 -> 400 | N83: 2029
A84: Diesel + indkøb af korn (Såsæd) | B84: =B63+366 -> 47150 | C84: =EDATE(B84,1) -> 47178 | D84: Variabel | E84: Æg | F84: ha | G84: 1600 | H84: 1 | I84: =DATEDIF(B84,C84,"m") -> 1 | J84: =H84*G84/I84 -> 1600 | K84: =(J84-J84/5) -> 1280 | L84: =J84*I84 -> 1600 | M84: =K84*I84 -> 1280 | N84: 2029
A85: Diesel + indkøb af honningurt (Såsæd) | B85: =B64+366 -> 47150 | C85: =EDATE(B85,1) -> 47178 | D85: Variabel | E85: Æg | F85: ha | G85: 1900 | H85: 1 | I85: =DATEDIF(B85,C85,"m") -> 1 | J85: =H85*G85/I85 -> 1900 | K85: =(J85-J85/5) -> 1520 | L85: =J85*I85 -> 1900 | M85: =K85*I85 -> 1520 | N85: 2029
A86: El til hegn (Høns) | B86: =B65+365 -> 47484 | C86: =EDATE(B86,12) -> 47849 | D86: Kapacitet | E86: Æg | F86: kWh | G86: 2.5 | H86: =4*12 -> 48 | I86: =DATEDIF(B86,C86,"m") -> 12 | J86: =H86*G86/I86 -> 10 | K86: =J86-(J86/5) -> 8 | L86: =J86*I86 -> 120 | M86: =K86*I86 -> 96 | N86: 2030
A87: El til hegn (Kvæg) | B87: =B66+365 -> 47484 | C87: =EDATE(B87,12) -> 47849 | D87: Kapacitet | E87: Kvæg | F87: kWh | G87: 2.5 | H87: =8*12 -> 96 | I87: =DATEDIF(B87,C87,"m") -> 12 | J87: =H87*G87/I87 -> 20 | K87: =J87-(J87/5) -> 16 | L87: =J87*I87 -> 240 | M87: =K87*I87 -> 192 | N87: 2030
A88: El til 2 varmelamper (Kyllinger) | B88: =B67+365 -> 47635 | C88: =EDATE(B88,2) -> 47696 | D88: Kapacitet | E88: Kyllinger | F88: kWh | G88: 2.5 | H88: 400 | I88: =DATEDIF(B88,C88,"m") -> 2 | J88: =H88*G88/I88 -> 500 | K88: =J88-(J88/5) -> 400 | L88: =J88*I88 -> 1000 | M88: =K88*I88 -> 800 | N88: 2030
A89: Administrativt (Dinero og erhvervskonto) | B89: =B68+365 -> 47484 | C89: =EDATE(B89,12) -> 47849 | D89: Kapacitet | E89: Generelt | F89: Stk | G89: 1500 | H89: 1 | I89: =DATEDIF(B89,C89,"m") -> 12 | J89: =H89*G89/I89 -> 125 | K89: =J89-(J89/5) -> 100 | L89: =J89*I89 -> 1500 | M89: =K89*I89 -> 1200 | N89: 2030
A90: Hjemmeside og webshop | B90: =B69+365 -> 47484 | C90: =EDATE(B90,12) -> 47849 | D90: Kapacitet | E90: Generelt | F90: Stk | G90: =(35*6.7)+60 -> 294.5 | H90: 12 | I90: =DATEDIF(B90,C90,"m") -> 12 | J90: =H90*G90/I90 -> 294.5 | K90: =J90-(J90/5) -> 235.6 | L90: =J90*I90 -> 3534 | M90: =K90*I90 -> 2827.2 | N90: 2030
A91: Forsikringer | B91: =B70+365 -> 47484 | C91: =EDATE(B91,12) -> 47849 | D91: Kapacitet | E91: Generelt | F91: Stk | G91: 4000 | H91: 1 | I91: =DATEDIF(B91,C91,"m") -> 12 | J91: =H91*G91/I91 -> 333.33333 | K91: =J91-(J91/5) -> 266.66667 | L91: =J91*I91 -> 4000 | M91: =K91*I91 -> 3200 | N91: 2030
A92: Veterinær og medicin (Årsrapport) | B92: =B71+365 -> 47818 | C92: =EDATE(B92,1) -> 47849 | D92: Kapacitet | E92: Kvæg | F92: Stk | G92: 1500 | H92: 1 | I92: =DATEDIF(B92,C92,"m") -> 1 | J92: =H92*G92/I92 -> 1500 | K92: =J92-(J92/5) -> 1200 | L92: =J92*I92 -> 1500 | M92: =K92*I92 -> 1200 | N92: 2030
A93: Foder til kyllinger (Hele perioden) | B93: =B72+365 -> 47635 | C93: =EDATE(B93,4) -> 47757 | D93: Variabel | E93: Kyllinger | F93: Årligt forbrug/kylling | G93: =53 -> 53 | H93: 200 | I93: =DATEDIF(B93,C93,"m") -> 4 | J93: =H93*G93/I93 -> 2650 | K93: =(J93-J93/5) -> 2120 | L93: =J93*I93 -> 10600 | M93: =K93*I93 -> 8480 | N93: 2030
A94: Foder til høns (Gule foderærter og østers) | B94: =B73+365 -> 47484 | C94: =EDATE(B94,12) -> 47849 | D94: Variabel | E94: Æg | F94: Årligt forbrug/høne | G94: =2.4*12 -> 28.8 | H94: 300 | I94: =DATEDIF(B94,C94,"m") -> 12 | J94: =H94*G94/I94 -> 720 | K94: =(J94-J94/5) -> 576 | L94: =J94*I94 -> 8640 | M94: =K94*I94 -> 6912 | N94: 2030
A95: Strøelse til kyllinger (Spåner de første 2 uger) | B95: =B74+365 -> 47635 | C95: =EDATE(B95,2) -> 47696 | D95: Variabel | E95: Kyllinger | F95: Årligt forbrug/kylling | G95: 2 | H95: =H93 -> 200 | I95: =DATEDIF(B95,C95,"m") -> 2 | J95: =H95*G95/I95 -> 200 | K95: =(J95-J95/5) -> 160 | L95: =J95*I95 -> 400 | M95: =K95*I95 -> 320 | N95: 2030
A96: Strøelse til høns (Sand og eget halm) | B96: =B75+365 -> 47484 | C96: =EDATE(B96,12) -> 47849 | D96: Variabel | E96: Æg | F96: Årligt forbrug/høne | G96: 16 | H96: =H94 -> 300 | I96: =DATEDIF(B96,C96,"m") -> 12 | J96: =H96*G96/I96 -> 400 | K96: =(J96-J96/5) -> 320 | L96: =J96*I96 -> 4800 | M96: =K96*I96 -> 3840 | N96: 2030
A97: Slagt af kvæg | B97: =B76+365 -> 47818 | C97: =EDATE(B97,1) -> 47849 | D97: Variabel | E97: Kvæg | F97: Stk | G97: 5500 | H97: 3 | I97: =DATEDIF(B97,C97,"m") -> 1 | J97: =H97*G97/I97 -> 16500 | K97: =(J97-J97/5) -> 13200 | L97: =J97*I97 -> 16500 | M97: =K97*I97 -> 13200 | N97: 2030
A98: Foder til kvæg (Inden slagt) | B98: =B77+365 -> 47484 | C98: =EDATE(B98,4) -> 47604 | D98: Variabel | E98: Kvæg | F98: Stk | G98: 400 | H98: 14 | I98: =DATEDIF(B98,C98,"m") -> 4 | J98: =H98*G98/I98 -> 1400 | K98: =(J98-J98/5) -> 1120 | L98: =J98*I98 -> 5600 | M98: =K98*I98 -> 4480 | N98: 2030
A99: Foder til kvæg (Efter slagt) | B99: =B78+365 -> 47757 | C99: =EDATE(B99,3) -> 47849 | D99: Variabel | E99: Kvæg | F99: Stk | G99: 400 | H99: =H98-H97 -> 11 | I99: =DATEDIF(B99,C99,"m") -> 3 | J99: =H99*G99/I99 -> 1466.6667 | K99: =(J99-J99/5) -> 1173.3333 | L99: =J99*I99 -> 4400 | M99: =K99*I99 -> 3520 | N99: 2030
A100: Halm til jordbær | B100: =B79+365 -> 47604 | C100: =EDATE(B100,3) -> 47696 | D100: Variabel | E100: Jordbær | F100: Stk | G100: 0.12 | H100: 4000 | I100: =DATEDIF(B100,C100,"m") -> 3 | J100: =H100*G100/I100 -> 160 | K100: =(J100-J100/5) -> 128 | L100: =J100*I100 -> 480 | M100: =K100*I100 -> 384 | N100: 2030
...

Sheet Etablering_2026
A1: Aktivitet | B1: Månede start | C1: Månede slut | D1: Postering | E1: Type indtægt/ udgift | F1: Kategori | G1: Enhed | H1: Enhedspris i DKK (m. moms) | I1: Enheder total | J1: Fordelt på antal mdr | K1: Indtægt/ Udgift pr mdr (m. moms) | L1: Indtægt/ Udgift pr mdr (u. moms)
A2: Indkøb af blåbærbuske | B2: 46266 | C2: =EDATE(B2,0) -> 46266 | D2: Udgift | E2: Etablering | F2: Blåbær | G2: Stk | H2: 30 | I2: 0 | J2: =DATEDIF(B2,C2,"m")+1 -> 1 | K2: =I2*H2/J2 -> 0 | L2: =(K2-K2/5) -> 0
A3: Indkøb af hindbærbuske | B3: =B2 -> 46266 | C3: =EDATE(B3,0) -> 46266 | D3: Udgift | E3: Etablering | F3: Hindbær | G3: Stk | H3: 30 | I3: 0 | J3: =DATEDIF(B3,C3,"m")+1 -> 1 | K3: =I3*H3/J3 -> 0 | L3: =(K3-K3/5) -> 0
A4: Indkøb af kirsebærtræer | B4: =B3 -> 46266 | C4: =EDATE(B4,0) -> 46266 | D4: Udgift | E4: Etablering | F4: Kirsebær | G4: Stk | H4: 50 | I4: 0 | J4: =DATEDIF(B4,C4,"m")+1 -> 1 | K4: =I4*H4/J4 -> 0 | L4: =(K4-K4/5) -> 0
A5: Indkøb af jordbærplanter | B5: 46204 | C5: =EDATE(B5,0) -> 46204 | D5: Udgift | E5: Etablering | F5: Jordbær | G5: Stk | H5: 1 | I5: 4000 | J5: =DATEDIF(B5,C5,"m")+1 -> 1 | K5: =I5*H5/J5 -> 4000 | L5: =(K5-K5/5) -> 3200
A6: Indkøb af Galloway | B6: 46204 | C6: =EDATE(B6,0) -> 46204 | D6: Udgift | E6: Etablering | F6: Kvæg | G6: Stk | H6: =32300/3 -> 10766.667 | I6: 3 | J6: =DATEDIF(B6,C6,"m")+1 -> 1 | K6: =I6*H6/J6 -> 32300 | L6: =(K6-K6/5) -> 25840
A7: Indkøb af rendegraver | B7: 46266 | C7: =EDATE(B7,0) -> 46266 | D7: Udgift | E7: Etablering | F7: Generelt | G7: Stk | H7: 250000 | I7: 1 | J7: =DATEDIF(B7,C7,"m")+1 -> 1 | K7: =I7*H7/J7 -> 250000 | L7: =(K7-K7/5) -> 200000
A8: Hønsehus | B8: 46204 | C8: =EDATE(B8,0) -> 46204 | D8: Udgift | E8: Etablering | F8: Æg | G8: Stk | H8: =23262-H17 -> 20762 | I8: 1 | J8: =DATEDIF(B8,C8,"m")+1 -> 1 | K8: =I8*H8/J8 -> 20762 | L8: =(K8-K8/5) -> 16609.6
A9: Lokale til ægpakkeri | B9: 46266 | C9: =EDATE(B9,0) -> 46266 | D9: Udgift | E9: Etablering | F9: Æg | G9: Stk | H9: 2000 | I9: 1 | J9: =DATEDIF(B9,C9,"m")+1 -> 1 | K9: =I9*H9/J9 -> 2000 | L9: =(K9-K9/5) -> 1600
A10: Udekøkken til håndtering af frugt og grønt | B10: 46296 | C10: =EDATE(B10,0) -> 46296 | D10: Udgift | E10: Etablering | F10: Generelt | G10: Stk | H10: 10000 | I10: 1 | J10: =DATEDIF(B10,C10,"m")+1 -> 1 | K10: =I10*H10/J10 -> 10000 | L10: =(K10-K10/5) -> 8000
A11: Rugemaskine | B11: 46478 | C11: =EDATE(B11,0) -> 46478 | D11: Udgift | E11: Etablering | F11: Kyllinger | G11: Stk | H11: 4500 | I11: 1 | J11: =DATEDIF(B11,C11,"m")+1 -> 1 | K11: =I11*H11/J11 -> 4500 | L11: =(K11-K11/5) -> 3600
A12: Køleskab til æg | B12: 46327 | C12: =EDATE(B12,0) -> 46327 | D12: Udgift | E12: Etablering | F12: Æg | G12: Stk | H12: 4000 | I12: 1 | J12: =DATEDIF(B12,C12,"m")+1 -> 1 | K12: =I12*H12/J12 -> 4000 | L12: =(K12-K12/5) -> 3200
A13: Frysere | B13: 46143 | C13: =EDATE(B13,0) -> 46143 | D13: Udgift | E13: Etablering | F13: Kvæg | G13: Stk | H13: 4900 | I13: 1 | J13: =DATEDIF(B13,C13,"m")+1 -> 1 | K13: =I13*H13/J13 -> 4900 | L13: =(K13-K13/5) -> 3920
A14: Vejbod - Materialer | B14: 46266 | C14: =EDATE(B14,0) -> 46266 | D14: Udgift | E14: Etablering | F14: Jordbær | G14: Stk | H14: 5000 | I14: 1 | J14: =DATEDIF(B14,C14,"m")+1 -> 1 | K14: =I14*H14/J14 -> 5000 | L14: =(K14-K14/5) -> 4000
A15: Kontorartikler og emballage | B15: 46143 | C15: =EDATE(B15,0) -> 46143 | D15: Udgift | E15: Etablering | F15: Generelt | G15: Stk | H15: 1500 | I15: 1 | J15: =DATEDIF(B15,C15,"m")+1 -> 1 | K15: =I15*H15/J15 -> 1500 | L15: =(K15-K15/5) -> 1200
A16: Hegnsmateriale (Kvæg) | B16: 46143 | C16: =EDATE(B16,0) -> 46143 | D16: Udgift | E16: Etablering | F16: Kvæg | G16: Stk | H16: 1177 | I16: 1 | J16: =DATEDIF(B16,C16,"m")+1 -> 1 | K16: =I16*H16/J16 -> 1177 | L16: =(K16-K16/5) -> 941.6
A17: Hegnsmateriale (Høns) | B17: 46143 | C17: =EDATE(B17,0) -> 46143 | D17: Udgift | E17: Etablering | F17: Æg | G17: Stk | H17: 2500 | I17: 1 | J17: =DATEDIF(B17,C17,"m")+1 -> 1 | K17: =I17*H17/J17 -> 2500 | L17: =(K17-K17/5) -> 2000

Sheet Likviditetsbudget
A5: LIKVIDITETSBUDGET | B5: Skabelonen til likviditetsbudgettet er fra Dinero Regnskabsprogram
A6: 2026 | B6: Januar | C6: Februar | D6: Marts | E6: April | F6: maj | G6: Juni | H6: Juli | I6: August | J6: September | K6: Oktober | L6: November | M6: December | N6: I alt
A8: Likvider midler primo | B8: =35000+150000 -> 185000 | C8: =B27 -> 177142.5 | D8: =C27 -> 169285 | E8: =D27 -> 161427.5 | F8: =E27 -> 153570 | G8: =F27 -> 151135.5 | H8: =G27 -> 129428 | I8: =H27 -> 61658.5 | J8: =I27 -> 50951 | ... M8: =L27 -> -204412.25 | N8: =M8+M12 -> -201253.01
A10: Indbetalinger - incl. moms
A11: Kontant varesalg | B11: =1.25*Driftsbudget!B15 -> 0 | C11: =1.25*Driftsbudget!C15 -> 0 | D11: =1.25*Driftsbudget!D15 -> 0 | E11: =1.25*Driftsbudget!E15 -> 0 | F11: =1.25*Driftsbudget!F15 -> 25000 | G11: =1.25*Driftsbudget!G15 -> 0 | H11: =1.25*Driftsbudget!H15 -> 0 | I11: =1.25*Driftsbudget!I15 -> 0 | ... M11: =1.25*Driftsbudget!M15 -> 3159.2466 | N11: =SUM(B11:M11) -> 35068.493
A12: Indbetalinger i alt: | B12: =SUM(B11:B11) -> 0 | C12: =SUM(C10:C11) -> 0 | D12: =SUM(D10:D11) -> 0 | E12: =SUM(E10:E11) -> 0 | F12: =SUM(F10:F11) -> 25000 | G12: =SUM(G10:G11) -> 0 | H12: =SUM(H10:H11) -> 0 | I12: =SUM(I10:I11) -> 0 | J12: =SUM(J10:J11) -> 0 | ... M12: =SUM(M10:M11) -> 3159.2466 | N12: =SUM(B12:M12) -> 35068.493
A14: Udbetalinger - incl. moms
A15: Moms at betale | B15: 0 | C15: 0 | D15: 0 | E15: 0 | F15: 0 | G15: 0 | H15: 0 | I15: 0 | J15: -3000 | K15: 0 | L15: 0 | M15: 0 | N15: =SUM(B15:M15) -> -3000
A16: Hævet privat | B16: 0 | C16: 0 | D16: 0 | E16: 0 | F16: 0 | G16: 0 | H16: 0 | I16: 0 | J16: 0 | K16: 0 | L16: 0 | M16: 0 | N16: =SUM(B16:M16) -> 0
A17: Variable omkostninger | B17: =1.25*Driftsbudget!B35 -> 800 | C17: =1.25*Driftsbudget!C35 -> 800 | D17: =1.25*Driftsbudget!D35 -> 800 | E17: =1.25*Driftsbudget!E35 -> 800 | F17: =1.25*Driftsbudget!F35 -> 11800 | G17: =1.25*Driftsbudget!G35 -> 13650 | H17: =1.25*Driftsbudget!H35 -> 2650 | I17: =1.25*Driftsbudget!I35 -> 2650 | ... M17: =1.25*Driftsbudget!M35 -> 1200 | N17: =SUM(B17:M17) -> 42850
A18: Kapacitetsomkostninger | B18: =Driftsbudget!B48*1.25 -> 7057.5 | C18: =Driftsbudget!C48*1.25 -> 7057.5 | D18: =Driftsbudget!D48*1.25 -> 7057.5 | E18: =Driftsbudget!E48*1.25 -> 7057.5 | F18: =Driftsbudget!F48*1.25 -> 7057.5 | G18: =Driftsbudget!G48*1.25 -> 8057.5 | H18: =Driftsbudget!H48*1.25 -> 8057.5 | I18: =Driftsbudget!I48*1.25 -> 8057.5 | ... M18: =Driftsbudget!M48*1.25 -> 8557.5 | N18: =SUM(B18:M18) -> 89190
A19: Etableringsomkostninger | B19: =1.25*Driftsbudget!B76 -> 0 | C19: =1.25*Driftsbudget!C76 -> 0 | D19: =1.25*Driftsbudget!D76 -> 0 | E19: =1.25*Driftsbudget!E76 -> 0 | F19: =1.25*Driftsbudget!F76 -> 8577 | G19: =1.25*Driftsbudget!G76 -> 0 | H19: =1.25*Driftsbudget!H76 -> 57062 | I19: =1.25*Driftsbudget!I76 -> 0 | J19: =4*Driftsbudget!J76 -> 222400 | K19: =1.25*Driftsbudget!K76 -> 10000 | L19: =1.25*Driftsbudget!L76 -> 4000 | M19: =1.25*Driftsbudget!M76 -> 0 | N19: =SUM(B19:M19) -> 302039
A20: Udbetalinger i alt | B20: =SUM(B15:B19) -> 7857.5 | C20: =SUM(C15:C19) -> 7857.5 | D20: =SUM(D15:D19) -> 7857.5 | E20: =SUM(E15:E19) -> 7857.5 | F20: =SUM(F15:F19) -> 27434.5 | G20: =SUM(G15:G19) -> 21707.5 | H20: =SUM(H15:H19) -> 67769.5 | I20: =SUM(I15:I19) -> 10707.5 | ... N20: =SUM(N15:N19) -> 431079
A22: Ændring
A23: Kontanter i kassen | B23: 0 | C23: 0 | D23: 0 | E23: 0 | F23: 0 | G23: 0 | H23: 0 | I23: 0 | J23: 0 | K23: 0 | L23: 0 | M23: 0 | N23: =M23 -> 0
A24: Likvider i bank | B24: 0 | C24: 0 | D24: 0 | E24: 0 | F24: 0 | G24: 0 | H24: 0 | I24: 0 | J24: 0 | K24: 0 | L24: 0 | M24: 0 | N24: =M24 -> 0
A25: Disponibel kassekredit | B25: 0 | C25: 0 | D25: 0 | E25: 0 | F25: 0 | G25: 0 | H25: 0 | I25: 0 | J25: 0 | K25: 0 | L25: 0 | M25: 0 | N25: =M25 -> 0
A26: Minus likvide midler primo | B26: =B8 -> 185000 | C26: =B27 -> 177142.5 | D26: =C27 -> 169285 | E26: =D27 -> 161427.5 | F26: =E27 -> 153570 | G26: =F27 -> 151135.5 | H26: =G27 -> 129428 | I26: =H27 -> 61658.5 | J26: =I27 -> 50951 | ... M26: =L27 -> -204412.25 | N26: =M26 -> -204412.25
A27: Kassekredit ultimo | B27: =(B12-B20+B23+B24+B25)+B26 -> 177142.5 | C27: =(C12-C20+C23+C24+C25)+C26 -> 169285 | D27: =(D12-D20+D23+D24+D25)+D26 -> 161427.5 | E27: =(E12-E20+E23+E24+E25)+E26 -> 153570 | F27: =(F12-F20+F23+F24+F25)+F26 -> 151135.5 | G27: =(G12-G20+G23+G24+G25)+G26 -> 129428 | H27: =(H12-H20+H23+H24+H25)+H26 -> 61658.5 | I27: =(I12-I20+I23+I24+I25)+I26 -> 50951 | ... M27: =(M12-M20+M23+M24+M25)+M26 -> -211010.51 | N27: =M27 -> -211010.51

Sheet Driftsbudget
A6: DRIFTSBUDGET (u. moms) | B6: Skabelonen til driftsbudgettet er fra Dinero Regnskabsprogram
A7: 2026 | B7: Januar | C7: Februar | D7: Marts | E7: April | F7: Maj | G7: Juni | H7: Juli | I7: August | J7: September | K7: Oktober | L7: November | M7: December | N7: I alt
B8: 1 | C8: 2 | D8: 3 | E8: 4 | F8: 5 | G8: 6 | H8: 7 | I8: 8 | J8: 9 | K8: 10 | L8: 11 | M8: 12
A9: Nettoomsætning (u. moms):
A10: Æg | B10: =SUMIFS('Indtægter (Forecast)'!$L:$L,'Indtægter (Forecast)'!$A:$A,$A10,'Indtægter (Forecast)'!$B:$B,"<="&DATE($A$7,B$8,1),'Indtægter (Forecast)'!$C:$C,">="&DATE($A$7,B$8,1)) -> 0 | C10: =SUMIFS('Indtægter (Forecast)'!$L:$L,'Indtægter (Forecast)'!$A:$A,$A10,'Indtægter (Forecast)'!$B:$B,"<="&DATE($A$7,C$8,1),'Indtægter (Forecast)'!$C:$C,">="&DATE($A$7,C$8,1)) -> 0 | D10: =SUMIFS('Indtægter (Forecast)'!$L:$L,'Indtægter (Forecast)'!$A:$A,$A10,'Indtægter (Forecast)'!$B:$B,"<="&DATE($A$7,D$8,1),'Indtægter (Forecast)'!$C:$C,">="&DATE($A$7,D$8,1)) -> 0 | E10: =SUMIFS('Indtægter (Forecast)'!$L:$L,'Indtægter (Forecast)'!$A:$A,$A10,'Indtægter (Forecast)'!$B:$B,"<="&DATE($A$7,E$8,1),'Indtægter (Forecast)'!$C:$C,">="&DATE($A$7,E$8,1)) -> 0 | F10: =SUMIFS('Indtægter (Forecast)'!$L:$L,'Indtægter (Forecast)'!$A:$A,$A10,'Indtægter (Forecast)'!$B:$B,"<="&DATE($A$7,F$8,1),'Indtægter (Forecast)'!$C:$C,">="&DATE($A$7,F$8,1)) -> 0 | G10: =SUMIFS('Indtægter (Forecast)'!$L:$L,'Indtægter (Forecast)'!$A:$A,$A10,'Indtægter (Forecast)'!$B:$B,"<="&DATE($A$7,G$8,1),'Indtægter (Forecast)'!$C:$C,">="&DATE($A$7,G$8,1)) -> 0 | H10: =SUMIFS('Indtægter (Forecast)'!$L:$L,'Indtægter (Forecast)'!$A:$A,$A10,'Indtægter (Forecast)'!$B:$B,"<="&DATE($A$7,H$8,1),'Indtægter (Forecast)'!$C:$C,">="&DATE($A$7,H$8,1)) -> 0 | I10: =SUMIFS('Indtægter (Forecast)'!$L:$L,'Indtægter (Forecast)'!$A:$A,$A10,'Indtægter (Forecast)'!$B:$B,"<="&DATE($A$7,I$8,1),'Indtægter (Forecast)'!$C:$C,">="&DATE($A$7,I$8,1)) -> 0 | ... M10: =SUMIFS('Indtægter (Forecast)'!$L:$L,'Indtægter (Forecast)'!$A:$A,$A10,'Indtægter (Forecast)'!$B:$B,"<="&DATE($A$7,M$8,1),'Indtægter (Forecast)'!$C:$C,">="&DATE($A$7,M$8,1)) -> 2527.3973 | N10: =SUM(B10:M10) -> 5054.7945
A11: Jordbær | B11: =SUMIFS('Indtægter (Forecast)'!$L:$L,'Indtægter (Forecast)'!$A:$A,$A11,'Indtægter (Forecast)'!$B:$B,"<="&DATE($A$7,B$8,1),'Indtægter (Forecast)'!$C:$C,">="&DATE($A$7,B$8,1)) -> 0 | C11: =SUMIFS('Indtægter (Forecast)'!$L:$L,'Indtægter (Forecast)'!$A:$A,$A11,'Indtægter (Forecast)'!$B:$B,"<="&DATE($A$7,C$8,1),'Indtægter (Forecast)'!$C:$C,">="&DATE($A$7,C$8,1)) -> 0 | D11: =SUMIFS('Indtægter (Forecast)'!$L:$L,'Indtægter (Forecast)'!$A:$A,$A11,'Indtægter (Forecast)'!$B:$B,"<="&DATE($A$7,D$8,1),'Indtægter (Forecast)'!$C:$C,">="&DATE($A$7,D$8,1)) -> 0 | E11: =SUMIFS('Indtægter (Forecast)'!$L:$L,'Indtægter (Forecast)'!$A:$A,$A11,'Indtægter (Forecast)'!$B:$B,"<="&DATE($A$7,E$8,1),'Indtægter (Forecast)'!$C:$C,">="&DATE($A$7,E$8,1)) -> 0 | F11: =SUMIFS('Indtægter (Forecast)'!$L:$L,'Indtægter (Forecast)'!$A:$A,$A11,'Indtægter (Forecast)'!$B:$B,"<="&DATE($A$7,F$8,1),'Indtægter (Forecast)'!$C:$C,">="&DATE($A$7,F$8,1)) -> 0 | G11: =SUMIFS('Indtægter (Forecast)'!$L:$L,'Indtægter (Forecast)'!$A:$A,$A11,'Indtægter (Forecast)'!$B:$B,"<="&DATE($A$7,G$8,1),'Indtægter (Forecast)'!$C:$C,">="&DATE($A$7,G$8,1)) -> 0 | H11: =SUMIFS('Indtægter (Forecast)'!$L:$L,'Indtægter (Forecast)'!$A:$A,$A11,'Indtægter (Forecast)'!$B:$B,"<="&DATE($A$7,H$8,1),'Indtægter (Forecast)'!$C:$C,">="&DATE($A$7,H$8,1)) -> 0 | I11: =SUMIFS('Indtægter (Forecast)'!$L:$L,'Indtægter (Forecast)'!$A:$A,$A11,'Indtægter (Forecast)'!$B:$B,"<="&DATE($A$7,I$8,1),'Indtægter (Forecast)'!$C:$C,">="&DATE($A$7,I$8,1)) -> 0 | ... M11: =SUMIFS('Indtægter (Forecast)'!$L:$L,'Indtægter (Forecast)'!$A:$A,$A11,'Indtægter (Forecast)'!$B:$B,"<="&DATE($A$7,M$8,1),'Indtægter (Forecast)'!$C:$C,">="&DATE($A$7,M$8,1)) -> 0 | N11: =SUM(B11:M11) -> 0
A12: Kartofler | B12: =SUMIFS('Indtægter (Forecast)'!$L:$L,'Indtægter (Forecast)'!$A:$A,$A12,'Indtægter (Forecast)'!$B:$B,"<="&DATE($A$7,B$8,1),'Indtægter (Forecast)'!$C:$C,">="&DATE($A$7,B$8,1)) -> 0 | C12: =SUMIFS('Indtægter (Forecast)'!$L:$L,'Indtægter (Forecast)'!$A:$A,$A12,'Indtægter (Forecast)'!$B:$B,"<="&DATE($A$7,C$8,1),'Indtægter (Forecast)'!$C:$C,">="&DATE($A$7,C$8,1)) -> 0 | D12: =SUMIFS('Indtægter (Forecast)'!$L:$L,'Indtægter (Forecast)'!$A:$A,$A12,'Indtægter (Forecast)'!$B:$B,"<="&DATE($A$7,D$8,1),'Indtægter (Forecast)'!$C:$C,">="&DATE($A$7,D$8,1)) -> 0 | E12: =SUMIFS('Indtægter (Forecast)'!$L:$L,'Indtægter (Forecast)'!$A:$A,$A12,'Indtægter (Forecast)'!$B:$B,"<="&DATE($A$7,E$8,1),'Indtægter (Forecast)'!$C:$C,">="&DATE($A$7,E$8,1)) -> 0 | F12: =SUMIFS('Indtægter (Forecast)'!$L:$L,'Indtægter (Forecast)'!$A:$A,$A12,'Indtægter (Forecast)'!$B:$B,"<="&DATE($A$7,F$8,1),'Indtægter (Forecast)'!$C:$C,">="&DATE($A$7,F$8,1)) -> 0 | G12: =SUMIFS('Indtægter (Forecast)'!$L:$L,'Indtægter (Forecast)'!$A:$A,$A12,'Indtægter (Forecast)'!$B:$B,"<="&DATE($A$7,G$8,1),'Indtægter (Forecast)'!$C:$C,">="&DATE($A$7,G$8,1)) -> 0 | H12: =SUMIFS('Indtægter (Forecast)'!$L:$L,'Indtægter (Forecast)'!$A:$A,$A12,'Indtægter (Forecast)'!$B:$B,"<="&DATE($A$7,H$8,1),'Indtægter (Forecast)'!$C:$C,">="&DATE($A$7,H$8,1)) -> 0 | I12: =SUMIFS('Indtægter (Forecast)'!$L:$L,'Indtægter (Forecast)'!$A:$A,$A12,'Indtægter (Forecast)'!$B:$B,"<="&DATE($A$7,I$8,1),'Indtægter (Forecast)'!$C:$C,">="&DATE($A$7,I$8,1)) -> 0 | ... M12: =SUMIFS('Indtægter (Forecast)'!$L:$L,'Indtægter (Forecast)'!$A:$A,$A12,'Indtægter (Forecast)'!$B:$B,"<="&DATE($A$7,M$8,1),'Indtægter (Forecast)'!$C:$C,">="&DATE($A$7,M$8,1)) -> 0 | N12: =SUM(B12:M12) -> 0
A13: Kyllinger | B13: =SUMIFS('Indtægter (Forecast)'!$L:$L,'Indtægter (Forecast)'!$A:$A,$A13,'Indtægter (Forecast)'!$B:$B,"<="&DATE($A$7,B$8,1),'Indtægter (Forecast)'!$C:$C,">="&DATE($A$7,B$8,1)) -> 0 | C13: =SUMIFS('Indtægter (Forecast)'!$L:$L,'Indtægter (Forecast)'!$A:$A,$A13,'Indtægter (Forecast)'!$B:$B,"<="&DATE($A$7,C$8,1),'Indtægter (Forecast)'!$C:$C,">="&DATE($A$7,C$8,1)) -> 0 | D13: =SUMIFS('Indtægter (Forecast)'!$L:$L,'Indtægter (Forecast)'!$A:$A,$A13,'Indtægter (Forecast)'!$B:$B,"<="&DATE($A$7,D$8,1),'Indtægter (Forecast)'!$C:$C,">="&DATE($A$7,D$8,1)) -> 0 | E13: =SUMIFS('Indtægter (Forecast)'!$L:$L,'Indtægter (Forecast)'!$A:$A,$A13,'Indtægter (Forecast)'!$B:$B,"<="&DATE($A$7,E$8,1),'Indtægter (Forecast)'!$C:$C,">="&DATE($A$7,E$8,1)) -> 0 | F13: =SUMIFS('Indtægter (Forecast)'!$L:$L,'Indtægter (Forecast)'!$A:$A,$A13,'Indtægter (Forecast)'!$B:$B,"<="&DATE($A$7,F$8,1),'Indtægter (Forecast)'!$C:$C,">="&DATE($A$7,F$8,1)) -> 0 | G13: =SUMIFS('Indtægter (Forecast)'!$L:$L,'Indtægter (Forecast)'!$A:$A,$A13,'Indtægter (Forecast)'!$B:$B,"<="&DATE($A$7,G$8,1),'Indtægter (Forecast)'!$C:$C,">="&DATE($A$7,G$8,1)) -> 0 | H13: =SUMIFS('Indtægter (Forecast)'!$L:$L,'Indtægter (Forecast)'!$A:$A,$A13,'Indtægter (Forecast)'!$B:$B,"<="&DATE($A$7,H$8,1),'Indtægter (Forecast)'!$C:$C,">="&DATE($A$7,H$8,1)) -> 0 | I13: =SUMIFS('Indtægter (Forecast)'!$L:$L,'Indtægter (Forecast)'!$A:$A,$A13,'Indtægter (Forecast)'!$B:$B,"<="&DATE($A$7,I$8,1),'Indtægter (Forecast)'!$C:$C,">="&DATE($A$7,I$8,1)) -> 0 | ... M13: =SUMIFS('Indtægter (Forecast)'!$L:$L,'Indtægter (Forecast)'!$A:$A,$A13,'Indtægter (Forecast)'!$B:$B,"<="&DATE($A$7,M$8,1),'Indtægter (Forecast)'!$C:$C,">="&DATE($A$7,M$8,1)) -> 0 | N13: =SUM(B13:M13) -> 3000
A14: Kvæg | B14: =SUMIFS('Indtægter (Forecast)'!$L:$L,'Indtægter (Forecast)'!$A:$A,$A14,'Indtægter (Forecast)'!$B:$B,"<="&DATE($A$7,B$8,1),'Indtægter (Forecast)'!$C:$C,">="&DATE($A$7,B$8,1)) -> 0 | C14: =SUMIFS('Indtægter (Forecast)'!$L:$L,'Indtægter (Forecast)'!$A:$A,$A14,'Indtægter (Forecast)'!$B:$B,"<="&DATE($A$7,C$8,1),'Indtægter (Forecast)'!$C:$C,">="&DATE($A$7,C$8,1)) -> 0 | D14: =SUMIFS('Indtægter (Forecast)'!$L:$L,'Indtægter (Forecast)'!$A:$A,$A14,'Indtægter (Forecast)'!$B:$B,"<="&DATE($A$7,D$8,1),'Indtægter (Forecast)'!$C:$C,">="&DATE($A$7,D$8,1)) -> 0 | E14: =SUMIFS('Indtægter (Forecast)'!$L:$L,'Indtægter (Forecast)'!$A:$A,$A14,'Indtægter (Forecast)'!$B:$B,"<="&DATE($A$7,E$8,1),'Indtægter (Forecast)'!$C:$C,">="&DATE($A$7,E$8,1)) -> 0 | F14: =SUMIFS('Indtægter (Forecast)'!$L:$L,'Indtægter (Forecast)'!$A:$A,$A14,'Indtægter (Forecast)'!$B:$B,"<="&DATE($A$7,F$8,1),'Indtægter (Forecast)'!$C:$C,">="&DATE($A$7,F$8,1)) -> 20000 | G14: =SUMIFS('Indtægter (Forecast)'!$L:$L,'Indtægter (Forecast)'!$A:$A,$A14,'Indtægter (Forecast)'!$B:$B,"<="&DATE($A$7,G$8,1),'Indtægter (Forecast)'!$C:$C,">="&DATE($A$7,G$8,1)) -> 0 | H14: =SUMIFS('Indtægter (Forecast)'!$L:$L,'Indtægter (Forecast)'!$A:$A,$A14,'Indtægter (Forecast)'!$B:$B,"<="&DATE($A$7,H$8,1),'Indtægter (Forecast)'!$C:$C,">="&DATE($A$7,H$8,1)) -> 0 | I14: =SUMIFS('Indtægter (Forecast)'!$L:$L,'Indtægter (Forecast)'!$A:$A,$A14,'Indtægter (Forecast)'!$B:$B,"<="&DATE($A$7,I$8,1),'Indtægter (Forecast)'!$C:$C,">="&DATE($A$7,I$8,1)) -> 0 | ... M14: =SUMIFS('Indtægter (Forecast)'!$L:$L,'Indtægter (Forecast)'!$A:$A,$A14,'Indtægter (Forecast)'!$B:$B,"<="&DATE($A$7,M$8,1),'Indtægter (Forecast)'!$C:$C,">="&DATE($A$7,M$8,1)) -> 0 | N14: =SUM(B14:M14) -> 20000
A15: Omsætning i alt: | B15: =SUM(B10:B14) -> 0 | C15: =SUM(C10:C14) -> 0 | D15: =SUM(D10:D14) -> 0 | E15: =SUM(E10:E14) -> 0 | F15: =SUM(F10:F14) -> 20000 | G15: =SUM(G10:G14) -> 0 | H15: =SUM(H10:H14) -> 0 | I15: =SUM(I10:I14) -> 0 | ... N15: =SUM(N10:N14) -> 28054.795
A17: Variable omkostninger (u. moms):
A18: Foder til kyllinger (Hele perioden) | B18: =SUMIFS('Udgifter (Forecast)'!$M:$M,'Udgifter (Forecast)'!$A:$A,$A18,'Udgifter (Forecast)'!$B:$B,"<="&DATE($A$7,B$8,1),'Udgifter (Forecast)'!$C:$C,">="&DATE($A$7,B$8,1)) -> 0 | C18: =SUMIFS('Udgifter (Forecast)'!$M:$M,'Udgifter (Forecast)'!$A:$A,$A18,'Udgifter (Forecast)'!$B:$B,"<="&DATE($A$7,C$8,1),'Udgifter (Forecast)'!$C:$C,">="&DATE($A$7,C$8,1)) -> 0 | D18: =SUMIFS('Udgifter (Forecast)'!$M:$M,'Udgifter (Forecast)'!$A:$A,$A18,'Udgifter (Forecast)'!$B:$B,"<="&DATE($A$7,D$8,1),'Udgifter (Forecast)'!$C:$C,">="&DATE($A$7,D$8,1)) -> 0 | E18: =SUMIFS('Udgifter (Forecast)'!$M:$M,'Udgifter (Forecast)'!$A:$A,$A18,'Udgifter (Forecast)'!$B:$B,"<="&DATE($A$7,E$8,1),'Udgifter (Forecast)'!$C:$C,">="&DATE($A$7,E$8,1)) -> 0 | F18: =SUMIFS('Udgifter (Forecast)'!$M:$M,'Udgifter (Forecast)'!$A:$A,$A18,'Udgifter (Forecast)'!$B:$B,"<="&DATE($A$7,F$8,1),'Udgifter (Forecast)'!$C:$C,">="&DATE($A$7,F$8,1)) -> 0 | G18: =SUMIFS('Udgifter (Forecast)'!$M:$M,'Udgifter (Forecast)'!$A:$A,$A18,'Udgifter (Forecast)'!$B:$B,"<="&DATE($A$7,G$8,1),'Udgifter (Forecast)'!$C:$C,">="&DATE($A$7,G$8,1)) -> 2120 | H18: =SUMIFS('Udgifter (Forecast)'!$M:$M,'Udgifter (Forecast)'!$A:$A,$A18,'Udgifter (Forecast)'!$B:$B,"<="&DATE($A$7,H$8,1),'Udgifter (Forecast)'!$C:$C,">="&DATE($A$7,H$8,1)) -> 2120 | I18: =SUMIFS('Udgifter (Forecast)'!$M:$M,'Udgifter (Forecast)'!$A:$A,$A18,'Udgifter (Forecast)'!$B:$B,"<="&DATE($A$7,I$8,1),'Udgifter (Forecast)'!$C:$C,">="&DATE($A$7,I$8,1)) -> 2120 | ... M18: =SUMIFS('Udgifter (Forecast)'!$M:$M,'Udgifter (Forecast)'!$A:$A,$A18,'Udgifter (Forecast)'!$B:$B,"<="&DATE($A$7,M$8,1),'Udgifter (Forecast)'!$C:$C,">="&DATE($A$7,M$8,1)) -> 0 | N18: =SUM(B18:M18) -> 10600
A19: Foder til høns (Gule foderærter) | B19: =SUMIFS('Udgifter (Forecast)'!$M:$M,'Udgifter (Forecast)'!$A:$A,$A19,'Udgifter (Forecast)'!$B:$B,"<="&DATE($A$7,B$8,1),'Udgifter (Forecast)'!$C:$C,">="&DATE($A$7,B$8,1)) -> 0 | C19: =SUMIFS('Udgifter (Forecast)'!$M:$M,'Udgifter (Forecast)'!$A:$A,$A19,'Udgifter (Forecast)'!$B:$B,"<="&DATE($A$7,C$8,1),'Udgifter (Forecast)'!$C:$C,">="&DATE($A$7,C$8,1)) -> 0 | D19: =SUMIFS('Udgifter (Forecast)'!$M:$M,'Udgifter (Forecast)'!$A:$A,$A19,'Udgifter (Forecast)'!$B:$B,"<="&DATE($A$7,D$8,1),'Udgifter (Forecast)'!$C:$C,">="&DATE($A$7,D$8,1)) -> 0 | E19: =SUMIFS('Udgifter (Forecast)'!$M:$M,'Udgifter (Forecast)'!$A:$A,$A19,'Udgifter (Forecast)'!$B:$B,"<="&DATE($A$7,E$8,1),'Udgifter (Forecast)'!$C:$C,">="&DATE($A$7,E$8,1)) -> 0 | F19: =SUMIFS('Udgifter (Forecast)'!$M:$M,'Udgifter (Forecast)'!$A:$A,$A19,'Udgifter (Forecast)'!$B:$B,"<="&DATE($A$7,F$8,1),'Udgifter (Forecast)'!$C:$C,">="&DATE($A$7,F$8,1)) -> 0 | G19: =SUMIFS('Udgifter (Forecast)'!$M:$M,'Udgifter (Forecast)'!$A:$A,$A19,'Udgifter (Forecast)'!$B:$B,"<="&DATE($A$7,G$8,1),'Udgifter (Forecast)'!$C:$C,">="&DATE($A$7,G$8,1)) -> 0 | H19: =SUMIFS('Udgifter (Forecast)'!$M:$M,'Udgifter (Forecast)'!$A:$A,$A19,'Udgifter (Forecast)'!$B:$B,"<="&DATE($A$7,H$8,1),'Udgifter (Forecast)'!$C:$C,">="&DATE($A$7,H$8,1)) -> 0 | I19: =SUMIFS('Udgifter (Forecast)'!$M:$M,'Udgifter (Forecast)'!$A:$A,$A19,'Udgifter (Forecast)'!$B:$B,"<="&DATE($A$7,I$8,1),'Udgifter (Forecast)'!$C:$C,">="&DATE($A$7,I$8,1)) -> 0 | ... M19: =SUMIFS('Udgifter (Forecast)'!$M:$M,'Udgifter (Forecast)'!$A:$A,$A19,'Udgifter (Forecast)'!$B:$B,"<="&DATE($A$7,M$8,1),'Udgifter (Forecast)'!$C:$C,">="&DATE($A$7,M$8,1)) -> 0 | N19: =SUM(B19:M19) -> 0
A20: Strøelse til kyllinger (Spåner) | B20: =SUMIFS('Udgifter (Forecast)'!$M:$M,'Udgifter (Forecast)'!$A:$A,$A20,'Udgifter (Forecast)'!$B:$B,"<="&DATE($A$7,B$8,1),'Udgifter (Forecast)'!$C:$C,">="&DATE($A$7,B$8,1)) -> 0 | C20: =SUMIFS('Udgifter (Forecast)'!$M:$M,'Udgifter (Forecast)'!$A:$A,$A20,'Udgifter (Forecast)'!$B:$B,"<="&DATE($A$7,C$8,1),'Udgifter (Forecast)'!$C:$C,">="&DATE($A$7,C$8,1)) -> 0 | D20: =SUMIFS('Udgifter (Forecast)'!$M:$M,'Udgifter (Forecast)'!$A:$A,$A20,'Udgifter (Forecast)'!$B:$B,"<="&DATE($A$7,D$8,1),'Udgifter (Forecast)'!$C:$C,">="&DATE($A$7,D$8,1)) -> 0 | E20: =SUMIFS('Udgifter (Forecast)'!$M:$M,'Udgifter (Forecast)'!$A:$A,$A20,'Udgifter (Forecast)'!$B:$B,"<="&DATE($A$7,E$8,1),'Udgifter (Forecast)'!$C:$C,">="&DATE($A$7,E$8,1)) -> 0 | F20: =SUMIFS('Udgifter (Forecast)'!$M:$M,'Udgifter (Forecast)'!$A:$A,$A20,'Udgifter (Forecast)'!$B:$B,"<="&DATE($A$7,F$8,1),'Udgifter (Forecast)'!$C:$C,">="&DATE($A$7,F$8,1)) -> 0 | G20: =SUMIFS('Udgifter (Forecast)'!$M:$M,'Udgifter (Forecast)'!$A:$A,$A20,'Udgifter (Forecast)'!$B:$B,"<="&DATE($A$7,G$8,1),'Udgifter (Forecast)'!$C:$C,">="&DATE($A$7,G$8,1)) -> 0 | H20: =SUMIFS('Udgifter (Forecast)'!$M:$M,'Udgifter (Forecast)'!$A:$A,$A20,'Udgifter (Forecast)'!$B:$B,"<="&DATE($A$7,H$8,1),'Udgifter (Forecast)'!$C:$C,">="&DATE($A$7,H$8,1)) -> 0 | I20: =SUMIFS('Udgifter (Forecast)'!$M:$M,'Udgifter (Forecast)'!$A:$A,$A20,'Udgifter (Forecast)'!$B:$B,"<="&DATE($A$7,I$8,1),'Udgifter (Forecast)'!$C:$C,">="&DATE($A$7,I$8,1)) -> 0 | ... M20: =SUMIFS('Udgifter (Forecast)'!$M:$M,'Udgifter (Forecast)'!$A:$A,$A20,'Udgifter (Forecast)'!$B:$B,"<="&DATE($A$7,M$8,1),'Udgifter (Forecast)'!$C:$C,">="&DATE($A$7,M$8,1)) -> 0 | N20: =SUM(B20:M20) -> 0
A21: Strøelse til store kyllinger (Halm) | B21: =SUMIFS('Udgifter (Forecast)'!$M:$M,'Udgifter (Forecast)'!$A:$A,$A21,'Udgifter (Forecast)'!$B:$B,"<="&DATE($A$7,B$8,1),'Udgifter (Forecast)'!$C:$C,">="&DATE($A$7,B$8,1)) -> 0 | C21: =SUMIFS('Udgifter (Forecast)'!$M:$M,'Udgifter (Forecast)'!$A:$A,$A21,'Udgifter (Forecast)'!$B:$B,"<="&DATE($A$7,C$8,1),'Udgifter (Forecast)'!$C:$C,">="&DATE($A$7,C$8,1)) -> 0 | D21: =SUMIFS('Udgifter (Forecast)'!$M:$M,'Udgifter (Forecast)'!$A:$A,$A21,'Udgifter (Forecast)'!$B:$B,"<="&DATE($A$7,D$8,1),'Udgifter (Forecast)'!$C:$C,">="&DATE($A$7,D$8,1)) -> 0 | E21: =SUMIFS('Udgifter (Forecast)'!$M:$M,'Udgifter (Forecast)'!$A:$A,$A21,'Udgifter (Forecast)'!$B:$B,"<="&DATE($A$7,E$8,1),'Udgifter (Forecast)'!$C:$C,">="&DATE($A$7,E$8,1)) -> 0 | F21: =SUMIFS('Udgifter (Forecast)'!$M:$M,'Udgifter (Forecast)'!$A:$A,$A21,'Udgifter (Forecast)'!$B:$B,"<="&DATE($A$7,F$8,1),'Udgifter (Forecast)'!$C:$C,">="&DATE($A$7,F$8,1)) -> 0 | G21: =SUMIFS('Udgifter (Forecast)'!$M:$M,'Udgifter (Forecast)'!$A:$A,$A21,'Udgifter (Forecast)'!$B:$B,"<="&DATE($A$7,G$8,1),'Udgifter (Forecast)'!$C:$C,">="&DATE($A$7,G$8,1)) -> 0 | H21: =SUMIFS('Udgifter (Forecast)'!$M:$M,'Udgifter (Forecast)'!$A:$A,$A21,'Udgifter (Forecast)'!$B:$B,"<="&DATE($A$7,H$8,1),'Udgifter (Forecast)'!$C:$C,">="&DATE($A$7,H$8,1)) -> 0 | I21: =SUMIFS('Udgifter (Forecast)'!$M:$M,'Udgifter (Forecast)'!$A:$A,$A21,'Udgifter (Forecast)'!$B:$B,"<="&DATE($A$7,I$8,1),'Udgifter (Forecast)'!$C:$C,">="&DATE($A$7,I$8,1)) -> 0 | ... M21: =SUMIFS('Udgifter (Forecast)'!$M:$M,'Udgifter (Forecast)'!$A:$A,$A21,'Udgifter (Forecast)'!$B:$B,"<="&DATE($A$7,M$8,1),'Udgifter (Forecast)'!$C:$C,">="&DATE($A$7,M$8,1)) -> 0 | N21: =SUM(B21:M21) -> 0
A22: Strøelse til høns (Halm) | B22: =SUMIFS('Udgifter (Forecast)'!$M:$M,'Udgifter (Forecast)'!$A:$A,$A22,'Udgifter (Forecast)'!$B:$B,"<="&DATE($A$7,B$8,1),'Udgifter (Forecast)'!$C:$C,">="&DATE($A$7,B$8,1)) -> 0 | C22: =SUMIFS('Udgifter (Forecast)'!$M:$M,'Udgifter (Forecast)'!$A:$A,$A22,'Udgifter (Forecast)'!$B:$B,"<="&DATE($A$7,C$8,1),'Udgifter (Forecast)'!$C:$C,">="&DATE($A$7,C$8,1)) -> 0 | D22: =SUMIFS('Udgifter (Forecast)'!$M:$M,'Udgifter (Forecast)'!$A:$A,$A22,'Udgifter (Forecast)'!$B:$B,"<="&DATE($A$7,D$8,1),'Udgifter (Forecast)'!$C:$C,">="&DATE($A$7,D$8,1)) -> 0 | E22: =SUMIFS('Udgifter (Forecast)'!$M:$M,'Udgifter (Forecast)'!$A:$A,$A22,'Udgifter (Forecast)'!$B:$B,"<="&DATE($A$7,E$8,1),'Udgifter (Forecast)'!$C:$C,">="&DATE($A$7,E$8,1)) -> 0 | F22: =SUMIFS('Udgifter (Forecast)'!$M:$M,'Udgifter (Forecast)'!$A:$A,$A22,'Udgifter (Forecast)'!$B:$B,"<="&DATE($A$7,F$8,1),'Udgifter (Forecast)'!$C:$C,">="&DATE($A$7,F$8,1)) -> 0 | G22: =SUMIFS('Udgifter (Forecast)'!$M:$M,'Udgifter (Forecast)'!$A:$A,$A22,'Udgifter (Forecast)'!$B:$B,"<="&DATE($A$7,G$8,1),'Udgifter (Forecast)'!$C:$C,">="&DATE($A$7,G$8,1)) -> 0 | H22: =SUMIFS('Udgifter (Forecast)'!$M:$M,'Udgifter (Forecast)'!$A:$A,$A22,'Udgifter (Forecast)'!$B:$B,"<="&DATE($A$7,H$8,1),'Udgifter (Forecast)'!$C:$C,">="&DATE($A$7,H$8,1)) -> 0 | I22: =SUMIFS('Udgifter (Forecast)'!$M:$M,'Udgifter (Forecast)'!$A:$A,$A22,'Udgifter (Forecast)'!$B:$B,"<="&DATE($A$7,I$8,1),'Udgifter (Forecast)'!$C:$C,">="&DATE($A$7,I$8,1)) -> 0 | ... M22: =SUMIFS('Udgifter (Forecast)'!$M:$M,'Udgifter (Forecast)'!$A:$A,$A22,'Udgifter (Forecast)'!$B:$B,"<="&DATE($A$7,M$8,1),'Udgifter (Forecast)'!$C:$C,">="&DATE($A$7,M$8,1)) -> 0 | N22: =SUM(B22:M22) -> 0
A23: Slagt af kvæg | B23: =SUMIFS('Udgifter (Forecast)'!$M:$M,'Udgifter (Forecast)'!$A:$A,$A23,'Udgifter (Forecast)'!$B:$B,"<="&DATE($A$7,B$8,1),'Udgifter (Forecast)'!$C:$C,">="&DATE($A$7,B$8,1)) -> 0 | C23: =SUMIFS('Udgifter (Forecast)'!$M:$M,'Udgifter (Forecast)'!$A:$A,$A23,'Udgifter (Forecast)'!$B:$B,"<="&DATE($A$7,C$8,1),'Udgifter (Forecast)'!$C:$C,">="&DATE($A$7,C$8,1)) -> 0 | D23: =SUMIFS('Udgifter (Forecast)'!$M:$M,'Udgifter (Forecast)'!$A:$A,$A23,'Udgifter (Forecast)'!$B:$B,"<="&DATE($A$7,D$8,1),'Udgifter (Forecast)'!$C:$C,">="&DATE($A$7,D$8,1)) -> 0 | E23: =SUMIFS('Udgifter (Forecast)'!$M:$M,'Udgifter (Forecast)'!$A:$A,$A23,'Udgifter (Forecast)'!$B:$B,"<="&DATE($A$7,E$8,1),'Udgifter (Forecast)'!$C:$C,">="&DATE($A$7,E$8,1)) -> 0 | F23: =SUMIFS('Udgifter (Forecast)'!$M:$M,'Udgifter (Forecast)'!$A:$A,$A23,'Udgifter (Forecast)'!$B:$B,"<="&DATE($A$7,F$8,1),'Udgifter (Forecast)'!$C:$C,">="&DATE($A$7,F$8,1)) -> 8800 | G23: =SUMIFS('Udgifter (Forecast)'!$M:$M,'Udgifter (Forecast)'!$A:$A,$A23,'Udgifter (Forecast)'!$B:$B,"<="&DATE($A$7,G$8,1),'Udgifter (Forecast)'!$C:$C,">="&DATE($A$7,G$8,1)) -> 8800 | H23: =SUMIFS('Udgifter (Forecast)'!$M:$M,'Udgifter (Forecast)'!$A:$A,$A23,'Udgifter (Forecast)'!$B:$B,"<="&DATE($A$7,H$8,1),'Udgifter (Forecast)'!$C:$C,">="&DATE($A$7,H$8,1)) -> 0 | I23: =SUMIFS('Udgifter (Forecast)'!$M:$M,'Udgifter (Forecast)'!$A:$A,$A23,'Udgifter (Forecast)'!$B:$B,"<="&DATE($A$7,I$8,1),'Udgifter (Forecast)'!$C:$C,">="&DATE($A$7,I$8,1)) -> 0 | ... M23: =SUMIFS('Udgifter (Forecast)'!$M:$M,'Udgifter (Forecast)'!$A:$A,$A23,'Udgifter (Forecast)'!$B:$B,"<="&DATE($A$7,M$8,1),'Udgifter (Forecast)'!$C:$C,">="&DATE($A$7,M$8,1)) -> 0 | N23: =SUM(B23:M23) -> 17600
A24: Foder til kvæg (Inden slagt) | B24: =SUMIFS('Udgifter (Forecast)'!$M:$M,'Udgifter (Forecast)'!$A:$A,$A24,'Udgifter (Forecast)'!$B:$B,"<="&DATE($A$7,B$8,1),'Udgifter (Forecast)'!$C:$C,">="&DATE($A$7,B$8,1)) -> 640 | C24: =SUMIFS('Udgifter (Forecast)'!$M:$M,'Udgifter (Forecast)'!$A:$A,$A24,'Udgifter (Forecast)'!$B:$B,"<="&DATE($A$7,C$8,1),'Udgifter (Forecast)'!$C:$C,">="&DATE($A$7,C$8,1)) -> 640 | D24: =SUMIFS('Udgifter (Forecast)'!$M:$M,'Udgifter (Forecast)'!$A:$A,$A24,'Udgifter (Forecast)'!$B:$B,"<="&DATE($A$7,D$8,1),'Udgifter (Forecast)'!$C:$C,">="&DATE($A$7,D$8,1)) -> 640 | E24: =SUMIFS('Udgifter (Forecast)'!$M:$M,'Udgifter (Forecast)'!$A:$A,$A24,'Udgifter (Forecast)'!$B:$B,"<="&DATE($A$7,E$8,1),'Udgifter (Forecast)'!$C:$C,">="&DATE($A$7,E$8,1)) -> 640 | F24: =SUMIFS('Udgifter (Forecast)'!$M:$M,'Udgifter (Forecast)'!$A:$A,$A24,'Udgifter (Forecast)'!$B:$B,"<="&DATE($A$7,F$8,1),'Udgifter (Forecast)'!$C:$C,">="&DATE($A$7,F$8,1)) -> 640 | G24: =SUMIFS('Udgifter (Forecast)'!$M:$M,'Udgifter (Forecast)'!$A:$A,$A24,'Udgifter (Forecast)'!$B:$B,"<="&DATE($A$7,G$8,1),'Udgifter (Forecast)'!$C:$C,">="&DATE($A$7,G$8,1)) -> 0 | H24: =SUMIFS('Udgifter (Forecast)'!$M:$M,'Udgifter (Forecast)'!$A:$A,$A24,'Udgifter (Forecast)'!$B:$B,"<="&DATE($A$7,H$8,1),'Udgifter (Forecast)'!$C:$C,">="&DATE($A$7,H$8,1)) -> 0 | I24: =SUMIFS('Udgifter (Forecast)'!$M:$M,'Udgifter (Forecast)'!$A:$A,$A24,'Udgifter (Forecast)'!$B:$B,"<="&DATE($A$7,I$8,1),'Udgifter (Forecast)'!$C:$C,">="&DATE($A$7,I$8,1)) -> 0 | ... M24: =SUMIFS('Udgifter (Forecast)'!$M:$M,'Udgifter (Forecast)'!$A:$A,$A24,'Udgifter (Forecast)'!$B:$B,"<="&DATE($A$7,M$8,1),'Udgifter (Forecast)'!$C:$C,">="&DATE($A$7,M$8,1)) -> 0 | N24: =SUM(B24:M24) -> 3200
A25: Foder til kvæg (Efter slagt) | B25: =SUMIFS('Udgifter (Forecast)'!$M:$M,'Udgifter (Forecast)'!$A:$A,$A25,'Udgifter (Forecast)'!$B:$B,"<="&DATE($A$7,B$8,1),'Udgifter (Forecast)'!$C:$C,">="&DATE($A$7,B$8,1)) -> 0 | C25: =SUMIFS('Udgifter (Forecast)'!$M:$M,'Udgifter (Forecast)'!$A:$A,$A25,'Udgifter (Forecast)'!$B:$B,"<="&DATE($A$7,C$8,1),'Udgifter (Forecast)'!$C:$C,">="&DATE($A$7,C$8,1)) -> 0 | D25: =SUMIFS('Udgifter (Forecast)'!$M:$M,'Udgifter (Forecast)'!$A:$A,$A25,'Udgifter (Forecast)'!$B:$B,"<="&DATE($A$7,D$8,1),'Udgifter (Forecast)'!$C:$C,">="&DATE($A$7,D$8,1)) -> 0 | E25: =SUMIFS('Udgifter (Forecast)'!$M:$M,'Udgifter (Forecast)'!$A:$A,$A25,'Udgifter (Forecast)'!$B:$B,"<="&DATE($A$7,E$8,1),'Udgifter (Forecast)'!$C:$C,">="&DATE($A$7,E$8,1)) -> 0 | F25: =SUMIFS('Udgifter (Forecast)'!$M:$M,'Udgifter (Forecast)'!$A:$A,$A25,'Udgifter (Forecast)'!$B:$B,"<="&DATE($A$7,F$8,1),'Udgifter (Forecast)'!$C:$C,">="&DATE($A$7,F$8,1)) -> 0 | G25: =SUMIFS('Udgifter (Forecast)'!$M:$M,'Udgifter (Forecast)'!$A:$A,$A25,'Udgifter (Forecast)'!$B:$B,"<="&DATE($A$7,G$8,1),'Udgifter (Forecast)'!$C:$C,">="&DATE($A$7,G$8,1)) -> 0 | H25: =SUMIFS('Udgifter (Forecast)'!$M:$M,'Udgifter (Forecast)'!$A:$A,$A25,'Udgifter (Forecast)'!$B:$B,"<="&DATE($A$7,H$8,1),'Udgifter (Forecast)'!$C:$C,">="&DATE($A$7,H$8,1)) -> 0 | I25: =SUMIFS('Udgifter (Forecast)'!$M:$M,'Udgifter (Forecast)'!$A:$A,$A25,'Udgifter (Forecast)'!$B:$B,"<="&DATE($A$7,I$8,1),'Udgifter (Forecast)'!$C:$C,">="&DATE($A$7,I$8,1)) -> 0 | ... M25: =SUMIFS('Udgifter (Forecast)'!$M:$M,'Udgifter (Forecast)'!$A:$A,$A25,'Udgifter (Forecast)'!$B:$B,"<="&DATE($A$7,M$8,1),'Udgifter (Forecast)'!$C:$C,">="&DATE($A$7,M$8,1)) -> 960 | N25: =SUM(B25:M25) -> 2880
A26: Halm til jordbær | B26: =SUMIFS('Udgifter (Forecast)'!$M:$M,'Udgifter (Forecast)'!$A:$A,$A26,'Udgifter (Forecast)'!$B:$B,"<="&DATE($A$7,B$8,1),'Udgifter (Forecast)'!$C:$C,">="&DATE($A$7,B$8,1)) -> 0 | C26: =SUMIFS('Udgifter (Forecast)'!$M:$M,'Udgifter (Forecast)'!$A:$A,$A26,'Udgifter (Forecast)'!$B:$B,"<="&DATE($A$7,C$8,1),'Udgifter (Forecast)'!$C:$C,">="&DATE($A$7,C$8,1)) -> 0 | D26: =SUMIFS('Udgifter (Forecast)'!$M:$M,'Udgifter (Forecast)'!$A:$A,$A26,'Udgifter (Forecast)'!$B:$B,"<="&DATE($A$7,D$8,1),'Udgifter (Forecast)'!$C:$C,">="&DATE($A$7,D$8,1)) -> 0 | E26: =SUMIFS('Udgifter (Forecast)'!$M:$M,'Udgifter (Forecast)'!$A:$A,$A26,'Udgifter (Forecast)'!$B:$B,"<="&DATE($A$7,E$8,1),'Udgifter (Forecast)'!$C:$C,">="&DATE($A$7,E$8,1)) -> 0 | F26: =SUMIFS('Udgifter (Forecast)'!$M:$M,'Udgifter (Forecast)'!$A:$A,$A26,'Udgifter (Forecast)'!$B:$B,"<="&DATE($A$7,F$8,1),'Udgifter (Forecast)'!$C:$C,">="&DATE($A$7,F$8,1)) -> 0 | G26: =SUMIFS('Udgifter (Forecast)'!$M:$M,'Udgifter (Forecast)'!$A:$A,$A26,'Udgifter (Forecast)'!$B:$B,"<="&DATE($A$7,G$8,1),'Udgifter (Forecast)'!$C:$C,">="&DATE($A$7,G$8,1)) -> 0 | H26: =SUMIFS('Udgifter (Forecast)'!$M:$M,'Udgifter (Forecast)'!$A:$A,$A26,'Udgifter (Forecast)'!$B:$B,"<="&DATE($A$7,H$8,1),'Udgifter (Forecast)'!$C:$C,">="&DATE($A$7,H$8,1)) -> 0 | I26: =SUMIFS('Udgifter (Forecast)'!$M:$M,'Udgifter (Forecast)'!$A:$A,$A26,'Udgifter (Forecast)'!$B:$B,"<="&DATE($A$7,I$8,1),'Udgifter (Forecast)'!$C:$C,">="&DATE($A$7,I$8,1)) -> 0 | ... M26: =SUMIFS('Udgifter (Forecast)'!$M:$M,'Udgifter (Forecast)'!$A:$A,$A26,'Udgifter (Forecast)'!$B:$B,"<="&DATE($A$7,M$8,1),'Udgifter (Forecast)'!$C:$C,">="&DATE($A$7,M$8,1)) -> 0 | N26: =SUM(B26:M26) -> 0
A27: Emballage til jordbær | B27: =SUMIFS('Udgifter (Forecast)'!$M:$M,'Udgifter (Forecast)'!$A:$A,$A27,'Udgifter (Forecast)'!$B:$B,"<="&DATE($A$7,B$8,1),'Udgifter (Forecast)'!$C:$C,">="&DATE($A$7,B$8,1)) -> 0 | C27: =SUMIFS('Udgifter (Forecast)'!$M:$M,'Udgifter (Forecast)'!$A:$A,$A27,'Udgifter (Forecast)'!$B:$B,"<="&DATE($A$7,C$8,1),'Udgifter (Forecast)'!$C:$C,">="&DATE($A$7,C$8,1)) -> 0 | D27: =SUMIFS('Udgifter (Forecast)'!$M:$M,'Udgifter (Forecast)'!$A:$A,$A27,'Udgifter (Forecast)'!$B:$B,"<="&DATE($A$7,D$8,1),'Udgifter (Forecast)'!$C:$C,">="&DATE($A$7,D$8,1)) -> 0 | E27: =SUMIFS('Udgifter (Forecast)'!$M:$M,'Udgifter (Forecast)'!$A:$A,$A27,'Udgifter (Forecast)'!$B:$B,"<="&DATE($A$7,E$8,1),'Udgifter (Forecast)'!$C:$C,">="&DATE($A$7,E$8,1)) -> 0 | F27: =SUMIFS('Udgifter (Forecast)'!$M:$M,'Udgifter (Forecast)'!$A:$A,$A27,'Udgifter (Forecast)'!$B:$B,"<="&DATE($A$7,F$8,1),'Udgifter (Forecast)'!$C:$C,">="&DATE($A$7,F$8,1)) -> 0 | G27: =SUMIFS('Udgifter (Forecast)'!$M:$M,'Udgifter (Forecast)'!$A:$A,$A27,'Udgifter (Forecast)'!$B:$B,"<="&DATE($A$7,G$8,1),'Udgifter (Forecast)'!$C:$C,">="&DATE($A$7,G$8,1)) -> 0 | H27: =SUMIFS('Udgifter (Forecast)'!$M:$M,'Udgifter (Forecast)'!$A:$A,$A27,'Udgifter (Forecast)'!$B:$B,"<="&DATE($A$7,H$8,1),'Udgifter (Forecast)'!$C:$C,">="&DATE($A$7,H$8,1)) -> 0 | I27: =SUMIFS('Udgifter (Forecast)'!$M:$M,'Udgifter (Forecast)'!$A:$A,$A27,'Udgifter (Forecast)'!$B:$B,"<="&DATE($A$7,I$8,1),'Udgifter (Forecast)'!$C:$C,">="&DATE($A$7,I$8,1)) -> 0 | ... M27: =SUMIFS('Udgifter (Forecast)'!$M:$M,'Udgifter (Forecast)'!$A:$A,$A27,'Udgifter (Forecast)'!$B:$B,"<="&DATE($A$7,M$8,1),'Udgifter (Forecast)'!$C:$C,">="&DATE($A$7,M$8,1)) -> 0 | N27: =SUM(B27:M27) -> 0
A28: Emballage til kartofler | B28: =SUMIFS('Udgifter (Forecast)'!$M:$M,'Udgifter (Forecast)'!$A:$A,$A28,'Udgifter (Forecast)'!$B:$B,"<="&DATE($A$7,B$8,1),'Udgifter (Forecast)'!$C:$C,">="&DATE($A$7,B$8,1)) -> 0 | C28: =SUMIFS('Udgifter (Forecast)'!$M:$M,'Udgifter (Forecast)'!$A:$A,$A28,'Udgifter (Forecast)'!$B:$B,"<="&DATE($A$7,C$8,1),'Udgifter (Forecast)'!$C:$C,">="&DATE($A$7,C$8,1)) -> 0 | D28: =SUMIFS('Udgifter (Forecast)'!$M:$M,'Udgifter (Forecast)'!$A:$A,$A28,'Udgifter (Forecast)'!$B:$B,"<="&DATE($A$7,D$8,1),'Udgifter (Forecast)'!$C:$C,">="&DATE($A$7,D$8,1)) -> 0 | E28: =SUMIFS('Udgifter (Forecast)'!$M:$M,'Udgifter (Forecast)'!$A:$A,$A28,'Udgifter (Forecast)'!$B:$B,"<="&DATE($A$7,E$8,1),'Udgifter (Forecast)'!$C:$C,">="&DATE($A$7,E$8,1)) -> 0 | F28: =SUMIFS('Udgifter (Forecast)'!$M:$M,'Udgifter (Forecast)'!$A:$A,$A28,'Udgifter (Forecast)'!$B:$B,"<="&DATE($A$7,F$8,1),'Udgifter (Forecast)'!$C:$C,">="&DATE($A$7,F$8,1)) -> 0 | G28: =SUMIFS('Udgifter (Forecast)'!$M:$M,'Udgifter (Forecast)'!$A:$A,$A28,'Udgifter (Forecast)'!$B:$B,"<="&DATE($A$7,G$8,1),'Udgifter (Forecast)'!$C:$C,">="&DATE($A$7,G$8,1)) -> 0 | H28: =SUMIFS('Udgifter (Forecast)'!$M:$M,'Udgifter (Forecast)'!$A:$A,$A28,'Udgifter (Forecast)'!$B:$B,"<="&DATE($A$7,H$8,1),'Udgifter (Forecast)'!$C:$C,">="&DATE($A$7,H$8,1)) -> 0 | I28: =SUMIFS('Udgifter (Forecast)'!$M:$M,'Udgifter (Forecast)'!$A:$A,$A28,'Udgifter (Forecast)'!$B:$B,"<="&DATE($A$7,I$8,1),'Udgifter (Forecast)'!$C:$C,">="&DATE($A$7,I$8,1)) -> 0 | ... M28: =SUMIFS('Udgifter (Forecast)'!$M:$M,'Udgifter (Forecast)'!$A:$A,$A28,'Udgifter (Forecast)'!$B:$B,"<="&DATE($A$7,M$8,1),'Udgifter (Forecast)'!$C:$C,">="&DATE($A$7,M$8,1)) -> 0 | N28: =SUM(B28:M28) -> 0
A29: Emballage til æg | B29: =SUMIFS('Udgifter (Forecast)'!$M:$M,'Udgifter (Forecast)'!$A:$A,$A29,'Udgifter (Forecast)'!$B:$B,"<="&DATE($A$7,B$8,1),'Udgifter (Forecast)'!$C:$C,">="&DATE($A$7,B$8,1)) -> 0 | C29: =SUMIFS('Udgifter (Forecast)'!$M:$M,'Udgifter (Forecast)'!$A:$A,$A29,'Udgifter (Forecast)'!$B:$B,"<="&DATE($A$7,C$8,1),'Udgifter (Forecast)'!$C:$C,">="&DATE($A$7,C$8,1)) -> 0 | D29: =SUMIFS('Udgifter (Forecast)'!$M:$M,'Udgifter (Forecast)'!$A:$A,$A29,'Udgifter (Forecast)'!$B:$B,"<="&DATE($A$7,D$8,1),'Udgifter (Forecast)'!$C:$C,">="&DATE($A$7,D$8,1)) -> 0 | E29: =SUMIFS('Udgifter (Forecast)'!$M:$M,'Udgifter (Forecast)'!$A:$A,$A29,'Udgifter (Forecast)'!$B:$B,"<="&DATE($A$7,E$8,1),'Udgifter (Forecast)'!$C:$C,">="&DATE($A$7,E$8,1)) -> 0 | F29: =SUMIFS('Udgifter (Forecast)'!$M:$M,'Udgifter (Forecast)'!$A:$A,$A29,'Udgifter (Forecast)'!$B:$B,"<="&DATE($A$7,F$8,1),'Udgifter (Forecast)'!$C:$C,">="&DATE($A$7,F$8,1)) -> 0 | G29: =SUMIFS('Udgifter (Forecast)'!$M:$M,'Udgifter (Forecast)'!$A:$A,$A29,'Udgifter (Forecast)'!$B:$B,"<="&DATE($A$7,G$8,1),'Udgifter (Forecast)'!$C:$C,">="&DATE($A$7,G$8,1)) -> 0 | H29: =SUMIFS('Udgifter (Forecast)'!$M:$M,'Udgifter (Forecast)'!$A:$A,$A29,'Udgifter (Forecast)'!$B:$B,"<="&DATE($A$7,H$8,1),'Udgifter (Forecast)'!$C:$C,">="&DATE($A$7,H$8,1)) -> 0 | I29: =SUMIFS('Udgifter (Forecast)'!$M:$M,'Udgifter (Forecast)'!$A:$A,$A29,'Udgifter (Forecast)'!$B:$B,"<="&DATE($A$7,I$8,1),'Udgifter (Forecast)'!$C:$C,">="&DATE($A$7,I$8,1)) -> 0 | ... M29: =SUMIFS('Udgifter (Forecast)'!$M:$M,'Udgifter (Forecast)'!$A:$A,$A29,'Udgifter (Forecast)'!$B:$B,"<="&DATE($A$7,M$8,1),'Udgifter (Forecast)'!$C:$C,">="&DATE($A$7,M$8,1)) -> 0 | N29: =SUM(B29:M29) -> 0
... A32: Diesel + indkøb af honningurt (Såsæd) | B32: =SUMIFS('Udgifter (Forecast)'!$M:$M,'Udgifter (Forecast)'!$A:$A,$A32,'Udgifter (Forecast)'!$B:$B,"<="&DATE($A$7,B$8,1),'Udgifter (Forecast)'!$C:$C,">="&DATE($A$7,B$8,1)) -> 0 | C32: =SUMIFS('Udgifter (Forecast)'!$M:$M,'Udgifter (Forecast)'!$A:$A,$A32,'Udgifter (Forecast)'!$B:$B,"<="&DATE($A$7,C$8,1),'Udgifter (Forecast)'!$C:$C,">="&DATE($A$7,C$8,1)) -> 0 | D32: =SUMIFS('Udgifter (Forecast)'!$M:$M,'Udgifter (Forecast)'!$A:$A,$A32,'Udgifter (Forecast)'!$B:$B,"<="&DATE($A$7,D$8,1),'Udgifter (Forecast)'!$C:$C,">="&DATE($A$7,D$8,1)) -> 0 | E32: =SUMIFS('Udgifter (Forecast)'!$M:$M,'Udgifter (Forecast)'!$A:$A,$A32,'Udgifter (Forecast)'!$B:$B,"<="&DATE($A$7,E$8,1),'Udgifter (Forecast)'!$C:$C,">="&DATE($A$7,E$8,1)) -> 0 | F32: =SUMIFS('Udgifter (Forecast)'!$M:$M,'Udgifter (Forecast)'!$A:$A,$A32,'Udgifter (Forecast)'!$B:$B,"<="&DATE($A$7,F$8,1),'Udgifter (Forecast)'!$C:$C,">="&DATE($A$7,F$8,1)) -> 0 | G32: =SUMIFS('Udgifter (Forecast)'!$M:$M,'Udgifter (Forecast)'!$A:$A,$A32,'Udgifter (Forecast)'!$B:$B,"<="&DATE($A$7,G$8,1),'Udgifter (Forecast)'!$C:$C,">="&DATE($A$7,G$8,1)) -> 0 | H32: =SUMIFS('Udgifter (Forecast)'!$M:$M,'Udgifter (Forecast)'!$A:$A,$A32,'Udgifter (Forecast)'!$B:$B,"<="&DATE($A$7,H$8,1),'Udgifter (Forecast)'!$C:$C,">="&DATE($A$7,H$8,1)) -> 0 | I32: =SUMIFS('Udgifter (Forecast)'!$M:$M,'Udgifter (Forecast)'!$A:$A,$A32,'Udgifter (Forecast)'!$B:$B,"<="&DATE($A$7,I$8,1),'Udgifter (Forecast)'!$C:$C,">="&DATE($A$7,I$8,1)) -> 0 | ... M32: =SUMIFS('Udgifter (Forecast)'!$M:$M,'Udgifter (Forecast)'!$A:$A,$A32,'Udgifter (Forecast)'!$B:$B,"<="&DATE($A$7,M$8,1),'Udgifter (Forecast)'!$C:$C,">="&DATE($A$7,M$8,1)) -> 0 | N32: =SUM(B32:M32) -> 0
A35: Variable omkostninger i alt: | B35: =SUM(B18:B34) -> 640 | C35: =SUM(C18:C34) -> 640 | D35: =SUM(D18:D34) -> 640 | E35: =SUM(E18:E34) -> 640 | F35: =SUM(F18:F34) -> 9440 | G35: =SUM(G18:G34) -> 10920 | H35: =SUM(H18:H34) -> 2120 | I35: =SUM(I18:I34) -> 2120 | ... M35: =SUM(M18:M34) -> 960 | N35: =SUM(B35:M35) -> 34280
A36: Dækningsbidrag: (Nettoomsætning - variable omkostninger) | B36: =B15-B35 -> -640 | C36: =C15-C35 -> -640 | D36: =D15-D35 -> -640 | E36: =E15-E35 -> -640 | F36: =F15-F35 -> 10560 | G36: =G15-G35 -> -10920 | H36: =H15-H35 -> -2120 | I36: =I15-I35 -> -2120 | ... M36: =M15-M35 -> 1567.3973 | N36: =SUM(B36:M36) -> -6225.2055
A38: Kapacitetsomkostninger (faste - u. moms)
A39: El til hegn (Høns) | B39: =SUMIFS('Udgifter (Forecast)'!$M:$M,'Udgifter (Forecast)'!$A:$A,$A39,'Udgifter (Forecast)'!$B:$B,"<="&DATE($A$7,B$8,1),'Udgifter (Forecast)'!$C:$C,">="&DATE($A$7,B$8,1)) -> 96 | C39: =SUMIFS('Udgifter (Forecast)'!$M:$M,'Udgifter (Forecast)'!$A:$A,$A39,'Udgifter (Forecast)'!$B:$B,"<="&DATE($A$7,C$8,1),'Udgifter (Forecast)'!$C:$C,">="&DATE($A$7,C$8,1)) -> 96 | D39: =SUMIFS('Udgifter (Forecast)'!$M:$M,'Udgifter (Forecast)'!$A:$A,$A39,'Udgifter (Forecast)'!$B:$B,"<="&DATE($A$7,D$8,1),'Udgifter (Forecast)'!$C:$C,">="&DATE($A$7,D$8,1)) -> 96 | E39: =SUMIFS('Udgifter (Forecast)'!$M:$M,'Udgifter (Forecast)'!$A:$A,$A39,'Udgifter (Forecast)'!$B:$B,"<="&DATE($A$7,E$8,1),'Udgifter (Forecast)'!$C:$C,">="&DATE($A$7,E$8,1)) -> 96 | F39: =SUMIFS('Udgifter (Forecast)'!$M:$M,'Udgifter (Forecast)'!$A:$A,$A39,'Udgifter (Forecast)'!$B:$B,"<="&DATE($A$7,F$8,1),'Udgifter (Forecast)'!$C:$C,">="&DATE($A$7,F$8,1)) -> 96 | G39: =SUMIFS('Udgifter (Forecast)'!$M:$M,'Udgifter (Forecast)'!$A:$A,$A39,'Udgifter (Forecast)'!$B:$B,"<="&DATE($A$7,G$8,1),'Udgifter (Forecast)'!$C:$C,">="&DATE($A$7,G$8,1)) -> 96 | H39: =SUMIFS('Udgifter (Forecast)'!$M:$M,'Udgifter (Forecast)'!$A:$A,$A39,'Udgifter (Forecast)'!$B:$B,"<="&DATE($A$7,H$8,1),'Udgifter (Forecast)'!$C:$C,">="&DATE($A$7,H$8,1)) -> 96 | I39: =SUMIFS('Udgifter (Forecast)'!$M:$M,'Udgifter (Forecast)'!$A:$A,$A39,'Udgifter (Forecast)'!$B:$B,"<="&DATE($A$7,I$8,1),'Udgifter (Forecast)'!$C:$C,">="&DATE($A$7,I$8,1)) -> 96 | ... M39: =SUMIFS('Udgifter (Forecast)'!$M:$M,'Udgifter (Forecast)'!$A:$A,$A39,'Udgifter (Forecast)'!$B:$B,"<="&DATE($A$7,M$8,1),'Udgifter (Forecast)'!$C:$C,">="&DATE($A$7,M$8,1)) -> 96 | N39: =SUM(B39:M39) -> 1152
A40: El til hegn (Kvæg) | B40: =SUMIFS('Udgifter (Forecast)'!$M:$M,'Udgifter (Forecast)'!$A:$A,$A40,'Udgifter (Forecast)'!$B:$B,"<="&DATE($A$7,B$8,1),'Udgifter (Forecast)'!$C:$C,">="&DATE($A$7,B$8,1)) -> 192 | C40: =SUMIFS('Udgifter (Forecast)'!$M:$M,'Udgifter (Forecast)'!$A:$A,$A40,'Udgifter (Forecast)'!$B:$B,"<="&DATE($A$7,C$8,1),'Udgifter (Forecast)'!$C:$C,">="&DATE($A$7,C$8,1)) -> 192 | D40: =SUMIFS('Udgifter (Forecast)'!$M:$M,'Udgifter (Forecast)'!$A:$A,$A40,'Udgifter (Forecast)'!$B:$B,"<="&DATE($A$7,D$8,1),'Udgifter (Forecast)'!$C:$C,">="&DATE($A$7,D$8,1)) -> 192 | E40: =SUMIFS('Udgifter (Forecast)'!$M:$M,'Udgifter (Forecast)'!$A:$A,$A40,'Udgifter (Forecast)'!$B:$B,"<="&DATE($A$7,E$8,1),'Udgifter (Forecast)'!$C:$C,">="&DATE($A$7,E$8,1)) -> 192 | F40: =SUMIFS('Udgifter (Forecast)'!$M:$M,'Udgifter (Forecast)'!$A:$A,$A40,'Udgifter (Forecast)'!$B:$B,"<="&DATE($A$7,F$8,1),'Udgifter (Forecast)'!$C:$C,">="&DATE($A$7,F$8,1)) -> 192 | G40: =SUMIFS('Udgifter (Forecast)'!$M:$M,'Udgifter (Forecast)'!$A:$A,$A40,'Udgifter (Forecast)'!$B:$B,"<="&DATE($A$7,G$8,1),'Udgifter (Forecast)'!$C:$C,">="&DATE($A$7,G$8,1)) -> 192 | H40: =SUMIFS('Udgifter (Forecast)'!$M:$M,'Udgifter (Forecast)'!$A:$A,$A40,'Udgifter (Forecast)'!$B:$B,"<="&DATE($A$7,H$8,1),'Udgifter (Forecast)'!$C:$C,">="&DATE($A$7,H$8,1)) -> 192 | I40: =SUMIFS('Udgifter (Forecast)'!$M:$M,'Udgifter (Forecast)'!$A:$A,$A40,'Udgifter (Forecast)'!$B:$B,"<="&DATE($A$7,I$8,1),'Udgifter (Forecast)'!$C:$C,">="&DATE($A$7,I$8,1)) -> 192 | ... M40: =SUMIFS('Udgifter (Forecast)'!$M:$M,'Udgifter (Forecast)'!$A:$A,$A40,'Udgifter (Forecast)'!$B:$B,"<="&DATE($A$7,M$8,1),'Udgifter (Forecast)'!$C:$C,">="&DATE($A$7,M$8,1)) -> 192 | N40: =SUM(B40:M40) -> 2304
A41: El til 2 varmelamper (Kyllinger) | B41: =SUMIFS('Udgifter (Forecast)'!$M:$M,'Udgifter (Forecast)'!$A:$A,$A41,'Udgifter (Forecast)'!$B:$B,"<="&DATE($A$7,B$8,1),'Udgifter (Forecast)'!$C:$C,">="&DATE($A$7,B$8,1)) -> 0 | C41: =SUMIFS('Udgifter (Forecast)'!$M:$M,'Udgifter (Forecast)'!$A:$A,$A41,'Udgifter (Forecast)'!$B:$B,"<="&DATE($A$7,C$8,1),'Udgifter (Forecast)'!$C:$C,">="&DATE($A$7,C$8,1)) -> 0 | D41: =SUMIFS('Udgifter (Forecast)'!$M:$M,'Udgifter (Forecast)'!$A:$A,$A41,'Udgifter (Forecast)'!$B:$B,"<="&DATE($A$7,D$8,1),'Udgifter (Forecast)'!$C:$C,">="&DATE($A$7,D$8,1)) -> 0 | E41: =SUMIFS('Udgifter (Forecast)'!$M:$M,'Udgifter (Forecast)'!$A:$A,$A41,'Udgifter (Forecast)'!$B:$B,"<="&DATE($A$7,E$8,1),'Udgifter (Forecast)'!$C:$C,">="&DATE($A$7,E$8,1)) -> 0 | F41: =SUMIFS('Udgifter (Forecast)'!$M:$M,'Udgifter (Forecast)'!$A:$A,$A41,'Udgifter (Forecast)'!$B:$B,"<="&DATE($A$7,F$8,1),'Udgifter (Forecast)'!$C:$C,">="&DATE($A$7,F$8,1)) -> 0 | G41: =SUMIFS('Udgifter (Forecast)'!$M:$M,'Udgifter (Forecast)'!$A:$A,$A41,'Udgifter (Forecast)'!$B:$B,"<="&DATE($A$7,G$8,1),'Udgifter (Forecast)'!$C:$C,">="&DATE($A$7,G$8,1)) -> 800 | H41: =SUMIFS('Udgifter (Forecast)'!$M:$M,'Udgifter (Forecast)'!$A:$A,$A41,'Udgifter (Forecast)'!$B:$B,"<="&DATE($A$7,H$8,1),'Udgifter (Forecast)'!$C:$C,">="&DATE($A$7,H$8,1)) -> 800 | I41: =SUMIFS('Udgifter (Forecast)'!$M:$M,'Udgifter (Forecast)'!$A:$A,$A41,'Udgifter (Forecast)'!$B:$B,"<="&DATE($A$7,I$8,1),'Udgifter (Forecast)'!$C:$C,">="&DATE($A$7,I$8,1)) -> 800 | ... M41: =SUMIFS('Udgifter (Forecast)'!$M:$M,'Udgifter (Forecast)'!$A:$A,$A41,'Udgifter (Forecast)'!$B:$B,"<="&DATE($A$7,M$8,1),'Udgifter (Forecast)'!$C:$C,">="&DATE($A$7,M$8,1)) -> 0 | N41: =SUM(B41:M41) -> 2400
A42: Administrativt (Dinero og erhvervskonto) | B42: =SUMIFS('Udgifter (Forecast)'!$M:$M,'Udgifter (Forecast)'!$A:$A,$A42,'Udgifter (Forecast)'!$B:$B,"<="&DATE($A$7,B$8,1),'Udgifter (Forecast)'!$C:$C,">="&DATE($A$7,B$8,1)) -> 1200 | C42: =SUMIFS('Udgifter (Forecast)'!$M:$M,'Udgifter (Forecast)'!$A:$A,$A42,'Udgifter (Forecast)'!$B:$B,"<="&DATE($A$7,C$8,1),'Udgifter (Forecast)'!$C:$C,">="&DATE($A$7,C$8,1)) -> 1200 | D42: =SUMIFS('Udgifter (Forecast)'!$M:$M,'Udgifter (Forecast)'!$A:$A,$A42,'Udgifter (Forecast)'!$B:$B,"<="&DATE($A$7,D$8,1),'Udgifter (Forecast)'!$C:$C,">="&DATE($A$7,D$8,1)) -> 1200 | E42: =SUMIFS('Udgifter (Forecast)'!$M:$M,'Udgifter (Forecast)'!$A:$A,$A42,'Udgifter (Forecast)'!$B:$B,"<="&DATE($A$7,E$8,1),'Udgifter (Forecast)'!$C:$C,">="&DATE($A$7,E$8,1)) -> 1200 | F42: =SUMIFS('Udgifter (Forecast)'!$M:$M,'Udgifter (Forecast)'!$A:$A,$A42,'Udgifter (Forecast)'!$B:$B,"<="&DATE($A$7,F$8,1),'Udgifter (Forecast)'!$C:$C,">="&DATE($A$7,F$8,1)) -> 1200 | G42: =SUMIFS('Udgifter (Forecast)'!$M:$M,'Udgifter (Forecast)'!$A:$A,$A42,'Udgifter (Forecast)'!$B:$B,"<="&DATE($A$7,G$8,1),'Udgifter (Forecast)'!$C:$C,">="&DATE($A$7,G$8,1)) -> 1200 | H42: =SUMIFS('Udgifter (Forecast)'!$M:$M,'Udgifter (Forecast)'!$A:$A,$A42,'Udgifter (Forecast)'!$B:$B,"<="&DATE($A$7,H$8,1),'Udgifter (Forecast)'!$C:$C,">="&DATE($A$7,H$8,1)) -> 1200 | I42: =SUMIFS('Udgifter (Forecast)'!$M:$M,'Udgifter (Forecast)'!$A:$A,$A42,'Udgifter (Forecast)'!$B:$B,"<="&DATE($A$7,I$8,1),'Udgifter (Forecast)'!$C:$C,">="&DATE($A$7,I$8,1)) -> 1200 | ... M42: =SUMIFS('Udgifter (Forecast)'!$M:$M,'Udgifter (Forecast)'!$A:$A,$A42,'Udgifter (Forecast)'!$B:$B,"<="&DATE($A$7,M$8,1),'Udgifter (Forecast)'!$C:$C,">="&DATE($A$7,M$8,1)) -> 1200 | N42: =SUM(B42:M42) -> 14400
A43: Hjemmeside og webshop | B43: =SUMIFS('Udgifter (Forecast)'!$M:$M,'Udgifter (Forecast)'!$A:$A,$A43,'Udgifter (Forecast)'!$B:$B,"<="&DATE($A$7,B$8,1),'Udgifter (Forecast)'!$C:$C,">="&DATE($A$7,B$8,1)) -> 958 | C43: =SUMIFS('Udgifter (Forecast)'!$M:$M,'Udgifter (Forecast)'!$A:$A,$A43,'Udgifter (Forecast)'!$B:$B,"<="&DATE($A$7,C$8,1),'Udgifter (Forecast)'!$C:$C,">="&DATE($A$7,C$8,1)) -> 958 | D43: =SUMIFS('Udgifter (Forecast)'!$M:$M,'Udgifter (Forecast)'!$A:$A,$A43,'Udgifter (Forecast)'!$B:$B,"<="&DATE($A$7,D$8,1),'Udgifter (Forecast)'!$C:$C,">="&DATE($A$7,D$8,1)) -> 958 | E43: =SUMIFS('Udgifter (Forecast)'!$M:$M,'Udgifter (Forecast)'!$A:$A,$A43,'Udgifter (Forecast)'!$B:$B,"<="&DATE($A$7,E$8,1),'Udgifter (Forecast)'!$C:$C,">="&DATE($A$7,E$8,1)) -> 958 | F43: =SUMIFS('Udgifter (Forecast)'!$M:$M,'Udgifter (Forecast)'!$A:$A,$A43,'Udgifter (Forecast)'!$B:$B,"<="&DATE($A$7,F$8,1),'Udgifter (Forecast)'!$C:$C,">="&DATE($A$7,F$8,1)) -> 958 | G43: =SUMIFS('Udgifter (Forecast)'!$M:$M,'Udgifter (Forecast)'!$A:$A,$A43,'Udgifter (Forecast)'!$B:$B,"<="&DATE($A$7,G$8,1),'Udgifter (Forecast)'!$C:$C,">="&DATE($A$7,G$8,1)) -> 958 | H43: =SUMIFS('Udgifter (Forecast)'!$M:$M,'Udgifter (Forecast)'!$A:$A,$A43,'Udgifter (Forecast)'!$B:$B,"<="&DATE($A$7,H$8,1),'Udgifter (Forecast)'!$C:$C,">="&DATE($A$7,H$8,1)) -> 958 | I43: =SUMIFS('Udgifter (Forecast)'!$M:$M,'Udgifter (Forecast)'!$A:$A,$A43,'Udgifter (Forecast)'!$B:$B,"<="&DATE($A$7,I$8,1),'Udgifter (Forecast)'!$C:$C,">="&DATE($A$7,I$8,1)) -> 958 | ... M43: =SUMIFS('Udgifter (Forecast)'!$M:$M,'Udgifter (Forecast)'!$A:$A,$A43,'Udgifter (Forecast)'!$B:$B,"<="&DATE($A$7,M$8,1),'Udgifter (Forecast)'!$C:$C,">="&DATE($A$7,M$8,1)) -> 958 | N43: =SUM(B43:M43) -> 11496
A44: Forsikringer | B44: =SUMIFS('Udgifter (Forecast)'!$M:$M,'Udgifter (Forecast)'!$A:$A,$A44,'Udgifter (Forecast)'!$B:$B,"<="&DATE($A$7,B$8,1),'Udgifter (Forecast)'!$C:$C,">="&DATE($A$7,B$8,1)) -> 3200 | C44: =SUMIFS('Udgifter (Forecast)'!$M:$M,'Udgifter (Forecast)'!$A:$A,$A44,'Udgifter (Forecast)'!$B:$B,"<="&DATE($A$7,C$8,1),'Udgifter (Forecast)'!$C:$C,">="&DATE($A$7,C$8,1)) -> 3200 | D44: =SUMIFS('Udgifter (Forecast)'!$M:$M,'Udgifter (Forecast)'!$A:$A,$A44,'Udgifter (Forecast)'!$B:$B,"<="&DATE($A$7,D$8,1),'Udgifter (Forecast)'!$C:$C,">="&DATE($A$7,D$8,1)) -> 3200 | E44: =SUMIFS('Udgifter (Forecast)'!$M:$M,'Udgifter (Forecast)'!$A:$A,$A44,'Udgifter (Forecast)'!$B:$B,"<="&DATE($A$7,E$8,1),'Udgifter (Forecast)'!$C:$C,">="&DATE($A$7,E$8,1)) -> 3200 | F44: =SUMIFS('Udgifter (Forecast)'!$M:$M,'Udgifter (Forecast)'!$A:$A,$A44,'Udgifter (Forecast)'!$B:$B,"<="&DATE($A$7,F$8,1),'Udgifter (Forecast)'!$C:$C,">="&DATE($A$7,F$8,1)) -> 3200 | G44: =SUMIFS('Udgifter (Forecast)'!$M:$M,'Udgifter (Forecast)'!$A:$A,$A44,'Udgifter (Forecast)'!$B:$B,"<="&DATE($A$7,G$8,1),'Udgifter (Forecast)'!$C:$C,">="&DATE($A$7,G$8,1)) -> 3200 | H44: =SUMIFS('Udgifter (Forecast)'!$M:$M,'Udgifter (Forecast)'!$A:$A,$A44,'Udgifter (Forecast)'!$B:$B,"<="&DATE($A$7,H$8,1),'Udgifter (Forecast)'!$C:$C,">="&DATE($A$7,H$8,1)) -> 3200 | I44: =SUMIFS('Udgifter (Forecast)'!$M:$M,'Udgifter (Forecast)'!$A:$A,$A44,'Udgifter (Forecast)'!$B:$B,"<="&DATE($A$7,I$8,1),'Udgifter (Forecast)'!$C:$C,">="&DATE($A$7,I$8,1)) -> 3200 | ... M44: =SUMIFS('Udgifter (Forecast)'!$M:$M,'Udgifter (Forecast)'!$A:$A,$A44,'Udgifter (Forecast)'!$B:$B,"<="&DATE($A$7,M$8,1),'Udgifter (Forecast)'!$C:$C,">="&DATE($A$7,M$8,1)) -> 3200 | N44: =SUM(B44:M44) -> 38400
A45: Veterinær og medicin (Årsrapport) | B45: =SUMIFS('Udgifter (Forecast)'!$M:$M,'Udgifter (Forecast)'!$A:$A,$A45,'Udgifter (Forecast)'!$B:$B,"<="&DATE($A$7,B$8,1),'Udgifter (Forecast)'!$C:$C,">="&DATE($A$7,B$8,1)) -> 0 | C45: =SUMIFS('Udgifter (Forecast)'!$M:$M,'Udgifter (Forecast)'!$A:$A,$A45,'Udgifter (Forecast)'!$B:$B,"<="&DATE($A$7,C$8,1),'Udgifter (Forecast)'!$C:$C,">="&DATE($A$7,C$8,1)) -> 0 | D45: =SUMIFS('Udgifter (Forecast)'!$M:$M,'Udgifter (Forecast)'!$A:$A,$A45,'Udgifter (Forecast)'!$B:$B,"<="&DATE($A$7,D$8,1),'Udgifter (Forecast)'!$C:$C,">="&DATE($A$7,D$8,1)) -> 0 | E45: =SUMIFS('Udgifter (Forecast)'!$M:$M,'Udgifter (Forecast)'!$A:$A,$A45,'Udgifter (Forecast)'!$B:$B,"<="&DATE($A$7,E$8,1),'Udgifter (Forecast)'!$C:$C,">="&DATE($A$7,E$8,1)) -> 0 | F45: =SUMIFS('Udgifter (Forecast)'!$M:$M,'Udgifter (Forecast)'!$A:$A,$A45,'Udgifter (Forecast)'!$B:$B,"<="&DATE($A$7,F$8,1),'Udgifter (Forecast)'!$C:$C,">="&DATE($A$7,F$8,1)) -> 0 | G45: =SUMIFS('Udgifter (Forecast)'!$M:$M,'Udgifter (Forecast)'!$A:$A,$A45,'Udgifter (Forecast)'!$B:$B,"<="&DATE($A$7,G$8,1),'Udgifter (Forecast)'!$C:$C,">="&DATE($A$7,G$8,1)) -> 0 | H45: =SUMIFS('Udgifter (Forecast)'!$M:$M,'Udgifter (Forecast)'!$A:$A,$A45,'Udgifter (Forecast)'!$B:$B,"<="&DATE($A$7,H$8,1),'Udgifter (Forecast)'!$C:$C,">="&DATE($A$7,H$8,1)) -> 0 | I45: =SUMIFS('Udgifter (Forecast)'!$M:$M,'Udgifter (Forecast)'!$A:$A,$A45,'Udgifter (Forecast)'!$B:$B,"<="&DATE($A$7,I$8,1),'Udgifter (Forecast)'!$C:$C,">="&DATE($A$7,I$8,1)) -> 0 | ... M45: =SUMIFS('Udgifter (Forecast)'!$M:$M,'Udgifter (Forecast)'!$A:$A,$A45,'Udgifter (Forecast)'!$B:$B,"<="&DATE($A$7,M$8,1),'Udgifter (Forecast)'!$C:$C,">="&DATE($A$7,M$8,1)) -> 1200 | N45: =SUM(B45:M45) -> 1200
B46: =SUMIFS('Udgifter (Forecast)'!$M:$M,'Udgifter (Forecast)'!$A:$A,$A46,'Udgifter (Forecast)'!$B:$B,"<="&DATE($A$7,B$8,1),'Udgifter (Forecast)'!$C:$C,">="&DATE($A$7,B$8,1)) -> 0 | C46: =SUMIFS('Udgifter (Forecast)'!$M:$M,'Udgifter (Forecast)'!$A:$A,$A46,'Udgifter (Forecast)'!$B:$B,"<="&DATE($A$7,C$8,1),'Udgifter (Forecast)'!$C:$C,">="&DATE($A$7,C$8,1)) -> 0 | D46: =SUMIFS('Udgifter (Forecast)'!$M:$M,'Udgifter (Forecast)'!$A:$A,$A46,'Udgifter (Forecast)'!$B:$B,"<="&DATE($A$7,D$8,1),'Udgifter (Forecast)'!$C:$C,">="&DATE($A$7,D$8,1)) -> 0 | E46: =SUMIFS('Udgifter (Forecast)'!$M:$M,'Udgifter (Forecast)'!$A:$A,$A46,'Udgifter (Forecast)'!$B:$B,"<="&DATE($A$7,E$8,1),'Udgifter (Forecast)'!$C:$C,">="&DATE($A$7,E$8,1)) -> 0 | F46: =SUMIFS('Udgifter (Forecast)'!$M:$M,'Udgifter (Forecast)'!$A:$A,$A46,'Udgifter (Forecast)'!$B:$B,"<="&DATE($A$7,F$8,1),'Udgifter (Forecast)'!$C:$C,">="&DATE($A$7,F$8,1)) -> 0 | G46: =SUMIFS('Udgifter (Forecast)'!$M:$M,'Udgifter (Forecast)'!$A:$A,$A46,'Udgifter (Forecast)'!$B:$B,"<="&DATE($A$7,G$8,1),'Udgifter (Forecast)'!$C:$C,">="&DATE($A$7,G$8,1)) -> 0 | H46: =SUMIFS('Udgifter (Forecast)'!$M:$M,'Udgifter (Forecast)'!$A:$A,$A46,'Udgifter (Forecast)'!$B:$B,"<="&DATE($A$7,H$8,1),'Udgifter (Forecast)'!$C:$C,">="&DATE($A$7,H$8,1)) -> 0 | I46: =SUMIFS('Udgifter (Forecast)'!$M:$M,'Udgifter (Forecast)'!$A:$A,$A46,'Udgifter (Forecast)'!$B:$B,"<="&DATE($A$7,I$8,1),'Udgifter (Forecast)'!$C:$C,">="&DATE($A$7,I$8,1)) -> 0 | ... M46: =SUMIFS('Udgifter (Forecast)'!$M:$M,'Udgifter (Forecast)'!$A:$A,$A46,'Udgifter (Forecast)'!$B:$B,"<="&DATE($A$7,M$8,1),'Udgifter (Forecast)'!$C:$C,">="&DATE($A$7,M$8,1)) -> 0
A48: Fasteomkostninger i alt: | B48: =SUM(B39:B47) -> 5646 | C48: =SUM(C39:C47) -> 5646 | D48: =SUM(D39:D47) -> 5646 | E48: =SUM(E39:E47) -> 5646 | F48: =SUM(F39:F47) -> 5646 | G48: =SUM(G39:G47) -> 6446 | H48: =SUM(H39:H47) -> 6446 | I48: =SUM(I39:I47) -> 6446 | ... N48: =SUM(N39:N47) -> 71352
A49: Resultat før renter og afskrivninger (Dækningsbidrag - faste omkostninger) | B49: =B36-B48 -> -6286 | C49: =C36-C48 -> -6286 | D49: =D36-D48 -> -6286 | E49: =E36-E48 -> -6286 | F49: =F36-F48 -> 4914 | G49: =G36-G48 -> -17366 | H49: =H36-H48 -> -8566 | I49: =I36-I48 -> -8566 | ... N49: =N36-N48 -> -77577.205
A51: Renter:
A52: Renter af banklån og kassekredit | B52: 0 | C52: 0 | D52: 0 | E52: 0 | F52: 0 | G52: 0 | H52: 0 | I52: 0 | J52: 0 | K52: 0 | L52: 0 | M52: 0 | N52: =SUM(B52:M52) -> 0
A53: Andre renter | B53: 0 | C53: 0 | D53: 0 | E53: 0 | F53: 0 | G53: 0 | H53: 0 | I53: 0 | J53: 0 | K53: 0 | L53: 0 | M53: 0 | N53: =SUM(B53:M53) -> 0
A54: Renter i alt: | B54: =SUM(B52:B53) -> 0 | C54: =SUM(C52:C53) -> 0 | D54: =SUM(D52:D53) -> 0 | E54: =SUM(E52:E53) -> 0 | F54: =SUM(F52:F53) -> 0 | G54: =SUM(G52:G53) -> 0 | H54: =SUM(H52:H53) -> 0 | I54: =SUM(I52:I53) -> 0 | ... N54: =SUM(N52:N53) -> 0
A56: Afskrivninger:
A57: Indkøb af blåbærbuske | B57: =SUMIFS(Etablering_2026!$L:$L,Etablering_2026!$A:$A,$A57,Etablering_2026!$B:$B,"<="&DATE($A$7,B$8,1),Etablering_2026!$C:$C,">="&DATE($A$7,B$8,1)) -> 0 | C57: =SUMIFS(Etablering_2026!$L:$L,Etablering_2026!$A:$A,$A57,Etablering_2026!$B:$B,"<="&DATE($A$7,C$8,1),Etablering_2026!$C:$C,">="&DATE($A$7,C$8,1)) -> 0 | D57: =SUMIFS(Etablering_2026!$L:$L,Etablering_2026!$A:$A,$A57,Etablering_2026!$B:$B,"<="&DATE($A$7,D$8,1),Etablering_2026!$C:$C,">="&DATE($A$7,D$8,1)) -> 0 | E57: =SUMIFS(Etablering_2026!$L:$L,Etablering_2026!$A:$A,$A57,Etablering_2026!$B:$B,"<="&DATE($A$7,E$8,1),Etablering_2026!$C:$C,">="&DATE($A$7,E$8,1)) -> 0 | F57: =SUMIFS(Etablering_2026!$L:$L,Etablering_2026!$A:$A,$A57,Etablering_2026!$B:$B,"<="&DATE($A$7,F$8,1),Etablering_2026!$C:$C,">="&DATE($A$7,F$8,1)) -> 0 | G57: =SUMIFS(Etablering_2026!$L:$L,Etablering_2026!$A:$A,$A57,Etablering_2026!$B:$B,"<="&DATE($A$7,G$8,1),Etablering_2026!$C:$C,">="&DATE($A$7,G$8,1)) -> 0 | H57: =SUMIFS(Etablering_2026!$L:$L,Etablering_2026!$A:$A,$A57,Etablering_2026!$B:$B,"<="&DATE($A$7,H$8,1),Etablering_2026!$C:$C,">="&DATE($A$7,H$8,1)) -> 0 | I57: =SUMIFS(Etablering_2026!$L:$L,Etablering_2026!$A:$A,$A57,Etablering_2026!$B:$B,"<="&DATE($A$7,I$8,1),Etablering_2026!$C:$C,">="&DATE($A$7,I$8,1)) -> 0 | ... M57: =SUMIFS(Etablering_2026!$L:$L,Etablering_2026!$A:$A,$A57,Etablering_2026!$B:$B,"<="&DATE($A$7,M$8,1),Etablering_2026!$C:$C,">="&DATE($A$7,M$8,1)) -> 0 | N57: =SUM(B57:M57) -> 0
A58: Indkøb af hindbærbuske | B58: =SUMIFS(Etablering_2026!$L:$L,Etablering_2026!$A:$A,$A58,Etablering_2026!$B:$B,"<="&DATE($A$7,B$8,1),Etablering_2026!$C:$C,">="&DATE($A$7,B$8,1)) -> 0 | C58: =SUMIFS(Etablering_2026!$L:$L,Etablering_2026!$A:$A,$A58,Etablering_2026!$B:$B,"<="&DATE($A$7,C$8,1),Etablering_2026!$C:$C,">="&DATE($A$7,C$8,1)) -> 0 | D58: =SUMIFS(Etablering_2026!$L:$L,Etablering_2026!$A:$A,$A58,Etablering_2026!$B:$B,"<="&DATE($A$7,D$8,1),Etablering_2026!$C:$C,">="&DATE($A$7,D$8,1)) -> 0 | E58: =SUMIFS(Etablering_2026!$L:$L,Etablering_2026!$A:$A,$A58,Etablering_2026!$B:$B,"<="&DATE($A$7,E$8,1),Etablering_2026!$C:$C,">="&DATE($A$7,E$8,1)) -> 0 | F58: =SUMIFS(Etablering_2026!$L:$L,Etablering_2026!$A:$A,$A58,Etablering_2026!$B:$B,"<="&DATE($A$7,F$8,1),Etablering_2026!$C:$C,">="&DATE($A$7,F$8,1)) -> 0 | G58: =SUMIFS(Etablering_2026!$L:$L,Etablering_2026!$A:$A,$A58,Etablering_2026!$B:$B,"<="&DATE($A$7,G$8,1),Etablering_2026!$C:$C,">="&DATE($A$7,G$8,1)) -> 0 | H58: =SUMIFS(Etablering_2026!$L:$L,Etablering_2026!$A:$A,$A58,Etablering_2026!$B:$B,"<="&DATE($A$7,H$8,1),Etablering_2026!$C:$C,">="&DATE($A$7,H$8,1)) -> 0 | I58: =SUMIFS(Etablering_2026!$L:$L,Etablering_2026!$A:$A,$A58,Etablering_2026!$B:$B,"<="&DATE($A$7,I$8,1),Etablering_2026!$C:$C,">="&DATE($A$7,I$8,1)) -> 0 | ... M58: =SUMIFS(Etablering_2026!$L:$L,Etablering_2026!$A:$A,$A58,Etablering_2026!$B:$B,"<="&DATE($A$7,M$8,1),Etablering_2026!$C:$C,">="&DATE($A$7,M$8,1)) -> 0 | N58: =SUM(B58:M58) -> 0
A59: Indkøb af kirsebærtræer | B59: =SUMIFS(Etablering_2026!$L:$L,Etablering_2026!$A:$A,$A59,Etablering_2026!$B:$B,"<="&DATE($A$7,B$8,1),Etablering_2026!$C:$C,">="&DATE($A$7,B$8,1)) -> 0 | C59: =SUMIFS(Etablering_2026!$L:$L,Etablering_2026!$A:$A,$A59,Etablering_2026!$B:$B,"<="&DATE($A$7,C$8,1),Etablering_2026!$C:$C,">="&DATE($A$7,C$8,1)) -> 0 | D59: =SUMIFS(Etablering_2026!$L:$L,Etablering_2026!$A:$A,$A59,Etablering_2026!$B:$B,"<="&DATE($A$7,D$8,1),Etablering_2026!$C:$C,">="&DATE($A$7,D$8,1)) -> 0 | E59: =SUMIFS(Etablering_2026!$L:$L,Etablering_2026!$A:$A,$A59,Etablering_2026!$B:$B,"<="&DATE($A$7,E$8,1),Etablering_2026!$C:$C,">="&DATE($A$7,E$8,1)) -> 0 | F59: =SUMIFS(Etablering_2026!$L:$L,Etablering_2026!$A:$A,$A59,Etablering_2026!$B:$B,"<="&DATE($A$7,F$8,1),Etablering_2026!$C:$C,">="&DATE($A$7,F$8,1)) -> 0 | G59: =SUMIFS(Etablering_2026!$L:$L,Etablering_2026!$A:$A,$A59,Etablering_2026!$B:$B,"<="&DATE($A$7,G$8,1),Etablering_2026!$C:$C,">="&DATE($A$7,G$8,1)) -> 0 | H59: =SUMIFS(Etablering_2026!$L:$L,Etablering_2026!$A:$A,$A59,Etablering_2026!$B:$B,"<="&DATE($A$7,H$8,1),Etablering_2026!$C:$C,">="&DATE($A$7,H$8,1)) -> 0 | I59: =SUMIFS(Etablering_2026!$L:$L,Etablering_2026!$A:$A,$A59,Etablering_2026!$B:$B,"<="&DATE($A$7,I$8,1),Etablering_2026!$C:$C,">="&DATE($A$7,I$8,1)) -> 0 | ... M59: =SUMIFS(Etablering_2026!$L:$L,Etablering_2026!$A:$A,$A59,Etablering_2026!$B:$B,"<="&DATE($A$7,M$8,1),Etablering_2026!$C:$C,">="&DATE($A$7,M$8,1)) -> 0 | N59: =SUM(B59:M59) -> 0
A60: Indkøb af jordbærplanter | B60: =SUMIFS(Etablering_2026!$L:$L,Etablering_2026!$A:$A,$A60,Etablering_2026!$B:$B,"<="&DATE($A$7,B$8,1),Etablering_2026!$C:$C,">="&DATE($A$7,B$8,1)) -> 0 | C60: =SUMIFS(Etablering_2026!$L:$L,Etablering_2026!$A:$A,$A60,Etablering_2026!$B:$B,"<="&DATE($A$7,C$8,1),Etablering_2026!$C:$C,">="&DATE($A$7,C$8,1)) -> 0 | D60: =SUMIFS(Etablering_2026!$L:$L,Etablering_2026!$A:$A,$A60,Etablering_2026!$B:$B,"<="&DATE($A$7,D$8,1),Etablering_2026!$C:$C,">="&DATE($A$7,D$8,1)) -> 0 | E60: =SUMIFS(Etablering_2026!$L:$L,Etablering_2026!$A:$A,$A60,Etablering_2026!$B:$B,"<="&DATE($A$7,E$8,1),Etablering_2026!$C:$C,">="&DATE($A$7,E$8,1)) -> 0 | F60: =SUMIFS(Etablering_2026!$L:$L,Etablering_2026!$A:$A,$A60,Etablering_2026!$B:$B,"<="&DATE($A$7,F$8,1),Etablering_2026!$C:$C,">="&DATE($A$7,F$8,1)) -> 0 | G60: =SUMIFS(Etablering_2026!$L:$L,Etablering_2026!$A:$A,$A60,Etablering_2026!$B:$B,"<="&DATE($A$7,G$8,1),Etablering_2026!$C:$C,">="&DATE($A$7,G$8,1)) -> 0 | H60: =SUMIFS(Etablering_2026!$L:$L,Etablering_2026!$A:$A,$A60,Etablering_2026!$B:$B,"<="&DATE($A$7,H$8,1),Etablering_2026!$C:$C,">="&DATE($A$7,H$8,1)) -> 3200 | I60: =SUMIFS(Etablering_2026!$L:$L,Etablering_2026!$A:$A,$A60,Etablering_2026!$B:$B,"<="&DATE($A$7,I$8,1),Etablering_2026!$C:$C,">="&DATE($A$7,I$8,1)) -> 0 | ... M60: =SUMIFS(Etablering_2026!$L:$L,Etablering_2026!$A:$A,$A60,Etablering_2026!$B:$B,"<="&DATE($A$7,M$8,1),Etablering_2026!$C:$C,">="&DATE($A$7,M$8,1)) -> 0 | N60: =SUM(B60:M60) -> 3200
A61: Indkøb af Galloway | B61: =SUMIFS(Etablering_2026!$L:$L,Etablering_2026!$A:$A,$A61,Etablering_2026!$B:$B,"<="&DATE($A$7,B$8,1),Etablering_2026!$C:$C,">="&DATE($A$7,B$8,1)) -> 0 | C61: =SUMIFS(Etablering_2026!$L:$L,Etablering_2026!$A:$A,$A61,Etablering_2026!$B:$B,"<="&DATE($A$7,C$8,1),Etablering_2026!$C:$C,">="&DATE($A$7,C$8,1)) -> 0 | D61: =SUMIFS(Etablering_2026!$L:$L,Etablering_2026!$A:$A,$A61,Etablering_2026!$B:$B,"<="&DATE($A$7,D$8,1),Etablering_2026!$C:$C,">="&DATE($A$7,D$8,1)) -> 0 | E61: =SUMIFS(Etablering_2026!$L:$L,Etablering_2026!$A:$A,$A61,Etablering_2026!$B:$B,"<="&DATE($A$7,E$8,1),Etablering_2026!$C:$C,">="&DATE($A$7,E$8,1)) -> 0 | F61: =SUMIFS(Etablering_2026!$L:$L,Etablering_2026!$A:$A,$A61,Etablering_2026!$B:$B,"<="&DATE($A$7,F$8,1),Etablering_2026!$C:$C,">="&DATE($A$7,F$8,1)) -> 0 | G61: =SUMIFS(Etablering_2026!$L:$L,Etablering_2026!$A:$A,$A61,Etablering_2026!$B:$B,"<="&DATE($A$7,G$8,1),Etablering_2026!$C:$C,">="&DATE($A$7,G$8,1)) -> 0 | H61: =SUMIFS(Etablering_2026!$L:$L,Etablering_2026!$A:$A,$A61,Etablering_2026!$B:$B,"<="&DATE($A$7,H$8,1),Etablering_2026!$C:$C,">="&DATE($A$7,H$8,1)) -> 25840 | I61: =SUMIFS(Etablering_2026!$L:$L,Etablering_2026!$A:$A,$A61,Etablering_2026!$B:$B,"<="&DATE($A$7,I$8,1),Etablering_2026!$C:$C,">="&DATE($A$7,I$8,1)) -> 0 | ... M61: =SUMIFS(Etablering_2026!$L:$L,Etablering_2026!$A:$A,$A61,Etablering_2026!$B:$B,"<="&DATE($A$7,M$8,1),Etablering_2026!$C:$C,">="&DATE($A$7,M$8,1)) -> 0 | N61: =SUM(B61:M61) -> 25840
A62: Indkøb af rendegraver | B62: =SUMIFS(Etablering_2026!$L:$L,Etablering_2026!$A:$A,$A62,Etablering_2026!$B:$B,"<="&DATE($A$7,B$8,1),Etablering_2026!$C:$C,">="&DATE($A$7,B$8,1)) -> 0 | C62: =SUMIFS(Etablering_2026!$L:$L,Etablering_2026!$A:$A,$A62,Etablering_2026!$B:$B,"<="&DATE($A$7,C$8,1),Etablering_2026!$C:$C,">="&DATE($A$7,C$8,1)) -> 0 | D62: =SUMIFS(Etablering_2026!$L:$L,Etablering_2026!$A:$A,$A62,Etablering_2026!$B:$B,"<="&DATE($A$7,D$8,1),Etablering_2026!$C:$C,">="&DATE($A$7,D$8,1)) -> 0 | E62: =SUMIFS(Etablering_2026!$L:$L,Etablering_2026!$A:$A,$A62,Etablering_2026!$B:$B,"<="&DATE($A$7,E$8,1),Etablering_2026!$C:$C,">="&DATE($A$7,E$8,1)) -> 0 | F62: =SUMIFS(Etablering_2026!$L:$L,Etablering_2026!$A:$A,$A62,Etablering_2026!$B:$B,"<="&DATE($A$7,F$8,1),Etablering_2026!$C:$C,">="&DATE($A$7,F$8,1)) -> 0 | G62: =SUMIFS(Etablering_2026!$L:$L,Etablering_2026!$A:$A,$A62,Etablering_2026!$B:$B,"<="&DATE($A$7,G$8,1),Etablering_2026!$C:$C,">="&DATE($A$7,G$8,1)) -> 0 | H62: =SUMIFS(Etablering_2026!$L:$L,Etablering_2026!$A:$A,$A62,Etablering_2026!$B:$B,"<="&DATE($A$7,H$8,1),Etablering_2026!$C:$C,">="&DATE($A$7,H$8,1)) -> 0 | I62: =SUMIFS(Etablering_2026!$L:$L,Etablering_2026!$A:$A,$A62,Etablering_2026!$B:$B,"<="&DATE($A$7,I$8,1),Etablering_2026!$C:$C,">="&DATE($A$7,I$8,1)) -> 0 | J62: =SUMIFS(Etablering_2026!$L:$L,Etablering_2026!$A:$A,$A62,Etablering_2026!$B:$B,"<="&DATE($A$7,J$8,1),Etablering_2026!$C:$C,">="&DATE($A$7,J$8,1))*0.25 -> 50000 | K62: =SUMIFS(Etablering_2026!$L:$L,Etablering_2026!$A:$A,$A62,Etablering_2026!$B:$B,"<="&DATE($A$7,K$8,1),Etablering_2026!$C:$C,">="&DATE($A$7,K$8,1)) -> 0 | L62: =SUMIFS(Etablering_2026!$L:$L,Etablering_2026!$A:$A,$A62,Etablering_2026!$B:$B,"<="&DATE($A$7,L$8,1),Etablering_2026!$C:$C,">="&DATE($A$7,L$8,1)) -> 0 | M62: =SUMIFS(Etablering_2026!$L:$L,Etablering_2026!$A:$A,$A62,Etablering_2026!$B:$B,"<="&DATE($A$7,M$8,1),Etablering_2026!$C:$C,">="&DATE($A$7,M$8,1)) -> 0 | N62: =SUM(B62:M62) -> 50000
A63: Hønsehus | B63: =SUMIFS(Etablering_2026!$L:$L,Etablering_2026!$A:$A,$A63,Etablering_2026!$B:$B,"<="&DATE($A$7,B$8,1),Etablering_2026!$C:$C,">="&DATE($A$7,B$8,1)) -> 0 | C63: =SUMIFS(Etablering_2026!$L:$L,Etablering_2026!$A:$A,$A63,Etablering_2026!$B:$B,"<="&DATE($A$7,C$8,1),Etablering_2026!$C:$C,">="&DATE($A$7,C$8,1)) -> 0 | D63: =SUMIFS(Etablering_2026!$L:$L,Etablering_2026!$A:$A,$A63,Etablering_2026!$B:$B,"<="&DATE($A$7,D$8,1),Etablering_2026!$C:$C,">="&DATE($A$7,D$8,1)) -> 0 | E63: =SUMIFS(Etablering_2026!$L:$L,Etablering_2026!$A:$A,$A63,Etablering_2026!$B:$B,"<="&DATE($A$7,E$8,1),Etablering_2026!$C:$C,">="&DATE($A$7,E$8,1)) -> 0 | F63: =SUMIFS(Etablering_2026!$L:$L,Etablering_2026!$A:$A,$A63,Etablering_2026!$B:$B,"<="&DATE($A$7,F$8,1),Etablering_2026!$C:$C,">="&DATE($A$7,F$8,1)) -> 0 | G63: =SUMIFS(Etablering_2026!$L:$L,Etablering_2026!$A:$A,$A63,Etablering_2026!$B:$B,"<="&DATE($A$7,G$8,1),Etablering_2026!$C:$C,">="&DATE($A$7,G$8,1)) -> 0 | H63: =SUMIFS(Etablering_2026!$L:$L,Etablering_2026!$A:$A,$A63,Etablering_2026!$B:$B,"<="&DATE($A$7,H$8,1),Etablering_2026!$C:$C,">="&DATE($A$7,H$8,1)) -> 16609.6 | I63: =SUMIFS(Etablering_2026!$L:$L,Etablering_2026!$A:$A,$A63,Etablering_2026!$B:$B,"<="&DATE($A$7,I$8,1),Etablering_2026!$C:$C,">="&DATE($A$7,I$8,1)) -> 0 | ... M63: =SUMIFS(Etablering_2026!$L:$L,Etablering_2026!$A:$A,$A63,Etablering_2026!$B:$B,"<="&DATE($A$7,M$8,1),Etablering_2026!$C:$C,">="&DATE($A$7,M$8,1)) -> 0 | N63: =SUM(B63:M63) -> 16609.6
A64: Lokale til ægpakkeri | B64: =SUMIFS(Etablering_2026!$L:$L,Etablering_2026!$A:$A,$A64,Etablering_2026!$B:$B,"<="&DATE($A$7,B$8,1),Etablering_2026!$C:$C,">="&DATE($A$7,B$8,1)) -> 0 | C64: =SUMIFS(Etablering_2026!$L:$L,Etablering_2026!$A:$A,$A64,Etablering_2026!$B:$B,"<="&DATE($A$7,C$8,1),Etablering_2026!$C:$C,">="&DATE($A$7,C$8,1)) -> 0 | D64: =SUMIFS(Etablering_2026!$L:$L,Etablering_2026!$A:$A,$A64,Etablering_2026!$B:$B,"<="&DATE($A$7,D$8,1),Etablering_2026!$C:$C,">="&DATE($A$7,D$8,1)) -> 0 | E64: =SUMIFS(Etablering_2026!$L:$L,Etablering_2026!$A:$A,$A64,Etablering_2026!$B:$B,"<="&DATE($A$7,E$8,1),Etablering_2026!$C:$C,">="&DATE($A$7,E$8,1)) -> 0 | F64: =SUMIFS(Etablering_2026!$L:$L,Etablering_2026!$A:$A,$A64,Etablering_2026!$B:$B,"<="&DATE($A$7,F$8,1),Etablering_2026!$C:$C,">="&DATE($A$7,F$8,1)) -> 0 | G64: =SUMIFS(Etablering_2026!$L:$L,Etablering_2026!$A:$A,$A64,Etablering_2026!$B:$B,"<="&DATE($A$7,G$8,1),Etablering_2026!$C:$C,">="&DATE($A$7,G$8,1)) -> 0 | H64: =SUMIFS(Etablering_2026!$L:$L,Etablering_2026!$A:$A,$A64,Etablering_2026!$B:$B,"<="&DATE($A$7,H$8,1),Etablering_2026!$C:$C,">="&DATE($A$7,H$8,1)) -> 0 | I64: =SUMIFS(Etablering_2026!$L:$L,Etablering_2026!$A:$A,$A64,Etablering_2026!$B:$B,"<="&DATE($A$7,I$8,1),Etablering_2026!$C:$C,">="&DATE($A$7,I$8,1)) -> 0 | ... M64: =SUMIFS(Etablering_2026!$L:$L,Etablering_2026!$A:$A,$A64,Etablering_2026!$B:$B,"<="&DATE($A$7,M$8,1),Etablering_2026!$C:$C,">="&DATE($A$7,M$8,1)) -> 0 | N64: =SUM(B64:M64) -> 1600
A65: Udekøkken til håndtering af frugt og grønt | B65: =SUMIFS(Etablering_2026!$L:$L,Etablering_2026!$A:$A,$A65,Etablering_2026!$B:$B,"<="&DATE($A$7,B$8,1),Etablering_2026!$C:$C,">="&DATE($A$7,B$8,1)) -> 0 | C65: =SUMIFS(Etablering_2026!$L:$L,Etablering_2026!$A:$A,$A65,Etablering_2026!$B:$B,"<="&DATE($A$7,C$8,1),Etablering_2026!$C:$C,">="&DATE($A$7,C$8,1)) -> 0 | D65: =SUMIFS(Etablering_2026!$L:$L,Etablering_2026!$A:$A,$A65,Etablering_2026!$B:$B,"<="&DATE($A$7,D$8,1),Etablering_2026!$C:$C,">="&DATE($A$7,D$8,1)) -> 0 | E65: =SUMIFS(Etablering_2026!$L:$L,Etablering_2026!$A:$A,$A65,Etablering_2026!$B:$B,"<="&DATE($A$7,E$8,1),Etablering_2026!$C:$C,">="&DATE($A$7,E$8,1)) -> 0 | F65: =SUMIFS(Etablering_2026!$L:$L,Etablering_2026!$A:$A,$A65,Etablering_2026!$B:$B,"<="&DATE($A$7,F$8,1),Etablering_2026!$C:$C,">="&DATE($A$7,F$8,1)) -> 0 | G65: =SUMIFS(Etablering_2026!$L:$L,Etablering_2026!$A:$A,$A65,Etablering_2026!$B:$B,"<="&DATE($A$7,G$8,1),Etablering_2026!$C:$C,">="&DATE($A$7,G$8,1)) -> 0 | H65: =SUMIFS(Etablering_2026!$L:$L,Etablering_2026!$A:$A,$A65,Etablering_2026!$B:$B,"<="&DATE($A$7,H$8,1),Etablering_2026!$C:$C,">="&DATE($A$7,H$8,1)) -> 0 | I65: =SUMIFS(Etablering_2026!$L:$L,Etablering_2026!$A:$A,$A65,Etablering_2026!$B:$B,"<="&DATE($A$7,I$8,1),Etablering_2026!$C:$C,">="&DATE($A$7,I$8,1)) -> 0 | ... M65: =SUMIFS(Etablering_2026!$L:$L,Etablering_2026!$A:$A,$A65,Etablering_2026!$B:$B,"<="&DATE($A$7,M$8,1),Etablering_2026!$C:$C,">="&DATE($A$7,M$8,1)) -> 0 | N65: =SUM(B65:M65) -> 8000
A66: Rugemaskine | B66: =SUMIFS(Etablering_2026!$L:$L,Etablering_2026!$A:$A,$A66,Etablering_2026!$B:$B,"<="&DATE($A$7,B$8,1),Etablering_2026!$C:$C,">="&DATE($A$7,B$8,1)) -> 0 | C66: =SUMIFS(Etablering_2026!$L:$L,Etablering_2026!$A:$A,$A66,Etablering_2026!$B:$B,"<="&DATE($A$7,C$8,1),Etablering_2026!$C:$C,">="&DATE($A$7,C$8,1)) -> 0 | D66: =SUMIFS(Etablering_2026!$L:$L,Etablering_2026!$A:$A,$A66,Etablering_2026!$B:$B,"<="&DATE($A$7,D$8,1),Etablering_2026!$C:$C,">="&DATE($A$7,D$8,1)) -> 0 | E66: =SUMIFS(Etablering_2026!$L:$L,Etablering_2026!$A:$A,$A66,Etablering_2026!$B:$B,"<="&DATE($A$7,E$8,1),Etablering_2026!$C:$C,">="&DATE($A$7,E$8,1)) -> 0 | F66: =SUMIFS(Etablering_2026!$L:$L,Etablering_2026!$A:$A,$A66,Etablering_2026!$B:$B,"<="&DATE($A$7,F$8,1),Etablering_2026!$C:$C,">="&DATE($A$7,F$8,1)) -> 0 | G66: =SUMIFS(Etablering_2026!$L:$L,Etablering_2026!$A:$A,$A66,Etablering_2026!$B:$B,"<="&DATE($A$7,G$8,1),Etablering_2026!$C:$C,">="&DATE($A$7,G$8,1)) -> 0 | H66: =SUMIFS(Etablering_2026!$L:$L,Etablering_2026!$A:$A,$A66,Etablering_2026!$B:$B,"<="&DATE($A$7,H$8,1),Etablering_2026!$C:$C,">="&DATE($A$7,H$8,1)) -> 0 | I66: =SUMIFS(Etablering_2026!$L:$L,Etablering_2026!$A:$A,$A66,Etablering_2026!$B:$B,"<="&DATE($A$7,I$8,1),Etablering_2026!$C:$C,">="&DATE($A$7,I$8,1)) -> 0 | ... M66: =SUMIFS(Etablering_2026!$L:$L,Etablering_2026!$A:$A,$A66,Etablering_2026!$B:$B,"<="&DATE($A$7,M$8,1),Etablering_2026!$C:$C,">="&DATE($A$7,M$8,1)) -> 0 | N66: =SUM(B66:M66) -> 0
A67: Køleskab til æg | B67: =SUMIFS(Etablering_2026!$L:$L,Etablering_2026!$A:$A,$A67,Etablering_2026!$B:$B,"<="&DATE($A$7,B$8,1),Etablering_2026!$C:$C,">="&DATE($A$7,B$8,1)) -> 0 | C67: =SUMIFS(Etablering_2026!$L:$L,Etablering_2026!$A:$A,$A67,Etablering_2026!$B:$B,"<="&DATE($A$7,C$8,1),Etablering_2026!$C:$C,">="&DATE($A$7,C$8,1)) -> 0 | D67: =SUMIFS(Etablering_2026!$L:$L,Etablering_2026!$A:$A,$A67,Etablering_2026!$B:$B,"<="&DATE($A$7,D$8,1),Etablering_2026!$C:$C,">="&DATE($A$7,D$8,1)) -> 0 | E67: =SUMIFS(Etablering_2026!$L:$L,Etablering_2026!$A:$A,$A67,Etablering_2026!$B:$B,"<="&DATE($A$7,E$8,1),Etablering_2026!$C:$C,">="&DATE($A$7,E$8,1)) -> 0 | F67: =SUMIFS(Etablering_2026!$L:$L,Etablering_2026!$A:$A,$A67,Etablering_2026!$B:$B,"<="&DATE($A$7,F$8,1),Etablering_2026!$C:$C,">="&DATE($A$7,F$8,1)) -> 0 | G67: =SUMIFS(Etablering_2026!$L:$L,Etablering_2026!$A:$A,$A67,Etablering_2026!$B:$B,"<="&DATE($A$7,G$8,1),Etablering_2026!$C:$C,">="&DATE($A$7,G$8,1)) -> 0 | H67: =SUMIFS(Etablering_2026!$L:$L,Etablering_2026!$A:$A,$A67,Etablering_2026!$B:$B,"<="&DATE($A$7,H$8,1),Etablering_2026!$C:$C,">="&DATE($A$7,H$8,1)) -> 0 | I67: =SUMIFS(Etablering_2026!$L:$L,Etablering_2026!$A:$A,$A67,Etablering_2026!$B:$B,"<="&DATE($A$7,I$8,1),Etablering_2026!$C:$C,">="&DATE($A$7,I$8,1)) -> 0 | ... M67: =SUMIFS(Etablering_2026!$L:$L,Etablering_2026!$A:$A,$A67,Etablering_2026!$B:$B,"<="&DATE($A$7,M$8,1),Etablering_2026!$C:$C,">="&DATE($A$7,M$8,1)) -> 0 | N67: =SUM(B67:M67) -> 3200
A68: Frysere | B68: =SUMIFS(Etablering_2026!$L:$L,Etablering_2026!$A:$A,$A68,Etablering_2026!$B:$B,"<="&DATE($A$7,B$8,1),Etablering_2026!$C:$C,">="&DATE($A$7,B$8,1)) -> 0 | C68: =SUMIFS(Etablering_2026!$L:$L,Etablering_2026!$A:$A,$A68,Etablering_2026!$B:$B,"<="&DATE($A$7,C$8,1),Etablering_2026!$C:$C,">="&DATE($A$7,C$8,1)) -> 0 | D68: =SUMIFS(Etablering_2026!$L:$L,Etablering_2026!$A:$A,$A68,Etablering_2026!$B:$B,"<="&DATE($A$7,D$8,1),Etablering_2026!$C:$C,">="&DATE($A$7,D$8,1)) -> 0 | E68: =SUMIFS(Etablering_2026!$L:$L,Etablering_2026!$A:$A,$A68,Etablering_2026!$B:$B,"<="&DATE($A$7,E$8,1),Etablering_2026!$C:$C,">="&DATE($A$7,E$8,1)) -> 0 | F68: =SUMIFS(Etablering_2026!$L:$L,Etablering_2026!$A:$A,$A68,Etablering_2026!$B:$B,"<="&DATE($A$7,F$8,1),Etablering_2026!$C:$C,">="&DATE($A$7,F$8,1)) -> 3920 | G68: =SUMIFS(Etablering_2026!$L:$L,Etablering_2026!$A:$A,$A68,Etablering_2026!$B:$B,"<="&DATE($A$7,G$8,1),Etablering_2026!$C:$C,">="&DATE($A$7,G$8,1)) -> 0 | H68: =SUMIFS(Etablering_2026!$L:$L,Etablering_2026!$A:$A,$A68,Etablering_2026!$B:$B,"<="&DATE($A$7,H$8,1),Etablering_2026!$C:$C,">="&DATE($A$7,H$8,1)) -> 0 | I68: =SUMIFS(Etablering_2026!$L:$L,Etablering_2026!$A:$A,$A68,Etablering_2026!$B:$B,"<="&DATE($A$7,I$8,1),Etablering_2026!$C:$C,">="&DATE($A$7,I$8,1)) -> 0 | ... M68: =SUMIFS(Etablering_2026!$L:$L,Etablering_2026!$A:$A,$A68,Etablering_2026!$B:$B,"<="&DATE($A$7,M$8,1),Etablering_2026!$C:$C,">="&DATE($A$7,M$8,1)) -> 0 | N68: =SUM(B68:M68) -> 3920
A69: Vejbod - Materialer | B69: =SUMIFS(Etablering_2026!$L:$L,Etablering_2026!$A:$A,$A69,Etablering_2026!$B:$B,"<="&DATE($A$7,B$8,1),Etablering_2026!$C:$C,">="&DATE($A$7,B$8,1)) -> 0 | C69: =SUMIFS(Etablering_2026!$L:$L,Etablering_2026!$A:$A,$A69,Etablering_2026!$B:$B,"<="&DATE($A$7,C$8,1),Etablering_2026!$C:$C,">="&DATE($A$7,C$8,1)) -> 0 | D69: =SUMIFS(Etablering_2026!$L:$L,Etablering_2026!$A:$A,$A69,Etablering_2026!$B:$B,"<="&DATE($A$7,D$8,1),Etablering_2026!$C:$C,">="&DATE($A$7,D$8,1)) -> 0 | E69: =SUMIFS(Etablering_2026!$L:$L,Etablering_2026!$A:$A,$A69,Etablering_2026!$B:$B,"<="&DATE($A$7,E$8,1),Etablering_2026!$C:$C,">="&DATE($A$7,E$8,1)) -> 0 | F69: =SUMIFS(Etablering_2026!$L:$L,Etablering_2026!$A:$A,$A69,Etablering_2026!$B:$B,"<="&DATE($A$7,F$8,1),Etablering_2026!$C:$C,">="&DATE($A$7,F$8,1)) -> 0 | G69: =SUMIFS(Etablering_2026!$L:$L,Etablering_2026!$A:$A,$A69,Etablering_2026!$B:$B,"<="&DATE($A$7,G$8,1),Etablering_2026!$C:$C,">="&DATE($A$7,G$8,1)) -> 0 | H69: =SUMIFS(Etablering_2026!$L:$L,Etablering_2026!$A:$A,$A69,Etablering_2026!$B:$B,"<="&DATE($A$7,H$8,1),Etablering_2026!$C:$C,">="&DATE($A$7,H$8,1)) -> 0 | I69: =SUMIFS(Etablering_2026!$L:$L,Etablering_2026!$A:$A,$A69,Etablering_2026!$B:$B,"<="&DATE($A$7,I$8,1),Etablering_2026!$C:$C,">="&DATE($A$7,I$8,1)) -> 0 | ... M69: =SUMIFS(Etablering_2026!$L:$L,Etablering_2026!$A:$A,$A69,Etablering_2026!$B:$B,"<="&DATE($A$7,M$8,1),Etablering_2026!$C:$C,">="&DATE($A$7,M$8,1)) -> 0 | N69: =SUM(B69:M69) -> 4000
A70: Hæve/sænke-fod til computerskærme | B70: =SUMIFS(Etablering_2026!$L:$L,Etablering_2026!$A:$A,$A70,Etablering_2026!$B:$B,"<="&DATE($A$7,B$8,1),Etablering_2026!$C:$C,">="&DATE($A$7,B$8,1)) -> 0 | C70: =SUMIFS(Etablering_2026!$L:$L,Etablering_2026!$A:$A,$A70,Etablering_2026!$B:$B,"<="&DATE($A$7,C$8,1),Etablering_2026!$C:$C,">="&DATE($A$7,C$8,1)) -> 0 | D70: =SUMIFS(Etablering_2026!$L:$L,Etablering_2026!$A:$A,$A70,Etablering_2026!$B:$B,"<="&DATE($A$7,D$8,1),Etablering_2026!$C:$C,">="&DATE($A$7,D$8,1)) -> 0 | E70: =SUMIFS(Etablering_2026!$L:$L,Etablering_2026!$A:$A,$A70,Etablering_2026!$B:$B,"<="&DATE($A$7,E$8,1),Etablering_2026!$C:$C,">="&DATE($A$7,E$8,1)) -> 0 | F70: =SUMIFS(Etablering_2026!$L:$L,Etablering_2026!$A:$A,$A70,Etablering_2026!$B:$B,"<="&DATE($A$7,F$8,1),Etablering_2026!$C:$C,">="&DATE($A$7,F$8,1)) -> 0 | G70: =SUMIFS(Etablering_2026!$L:$L,Etablering_2026!$A:$A,$A70,Etablering_2026!$B:$B,"<="&DATE($A$7,G$8,1),Etablering_2026!$C:$C,">="&DATE($A$7,G$8,1)) -> 0 | H70: =SUMIFS(Etablering_2026!$L:$L,Etablering_2026!$A:$A,$A70,Etablering_2026!$B:$B,"<="&DATE($A$7,H$8,1),Etablering_2026!$C:$C,">="&DATE($A$7,H$8,1)) -> 0 | I70: =SUMIFS(Etablering_2026!$L:$L,Etablering_2026!$A:$A,$A70,Etablering_2026!$B:$B,"<="&DATE($A$7,I$8,1),Etablering_2026!$C:$C,">="&DATE($A$7,I$8,1)) -> 0 | ... M70: =SUMIFS(Etablering_2026!$L:$L,Etablering_2026!$A:$A,$A70,Etablering_2026!$B:$B,"<="&DATE($A$7,M$8,1),Etablering_2026!$C:$C,">="&DATE($A$7,M$8,1)) -> 0 | N70: =SUM(B70:M70) -> 0
A71: Kontorartikler | B71: =SUMIFS(Etablering_2026!$L:$L,Etablering_2026!$A:$A,$A71,Etablering_2026!$B:$B,"<="&DATE($A$7,B$8,1),Etablering_2026!$C:$C,">="&DATE($A$7,B$8,1)) -> 0 | C71: =SUMIFS(Etablering_2026!$L:$L,Etablering_2026!$A:$A,$A71,Etablering_2026!$B:$B,"<="&DATE($A$7,C$8,1),Etablering_2026!$C:$C,">="&DATE($A$7,C$8,1)) -> 0 | D71: =SUMIFS(Etablering_2026!$L:$L,Etablering_2026!$A:$A,$A71,Etablering_2026!$B:$B,"<="&DATE($A$7,D$8,1),Etablering_2026!$C:$C,">="&DATE($A$7,D$8,1)) -> 0 | E71: =SUMIFS(Etablering_2026!$L:$L,Etablering_2026!$A:$A,$A71,Etablering_2026!$B:$B,"<="&DATE($A$7,E$8,1),Etablering_2026!$C:$C,">="&DATE($A$7,E$8,1)) -> 0 | F71: =SUMIFS(Etablering_2026!$L:$L,Etablering_2026!$A:$A,$A71,Etablering_2026!$B:$B,"<="&DATE($A$7,F$8,1),Etablering_2026!$C:$C,">="&DATE($A$7,F$8,1)) -> 0 | G71: =SUMIFS(Etablering_2026!$L:$L,Etablering_2026!$A:$A,$A71,Etablering_2026!$B:$B,"<="&DATE($A$7,G$8,1),Etablering_2026!$C:$C,">="&DATE($A$7,G$8,1)) -> 0 | H71: =SUMIFS(Etablering_2026!$L:$L,Etablering_2026!$A:$A,$A71,Etablering_2026!$B:$B,"<="&DATE($A$7,H$8,1),Etablering_2026!$C:$C,">="&DATE($A$7,H$8,1)) -> 0 | I71: =SUMIFS(Etablering_2026!$L:$L,Etablering_2026!$A:$A,$A71,Etablering_2026!$B:$B,"<="&DATE($A$7,I$8,1),Etablering_2026!$C:$C,">="&DATE($A$7,I$8,1)) -> 0 | ... M71: =SUMIFS(Etablering_2026!$L:$L,Etablering_2026!$A:$A,$A71,Etablering_2026!$B:$B,"<="&DATE($A$7,M$8,1),Etablering_2026!$C:$C,">="&DATE($A$7,M$8,1)) -> 0 | N71: =SUM(B71:M71) -> 0
A72: Hegnsmateriale (Kvæg) | B72: =SUMIFS(Etablering_2026!$L:$L,Etablering_2026!$A:$A,$A72,Etablering_2026!$B:$B,"<="&DATE($A$7,B$8,1),Etablering_2026!$C:$C,">="&DATE($A$7,B$8,1)) -> 0 | C72: =SUMIFS(Etablering_2026!$L:$L,Etablering_2026!$A:$A,$A72,Etablering_2026!$B:$B,"<="&DATE($A$7,C$8,1),Etablering_2026!$C:$C,">="&DATE($A$7,C$8,1)) -> 0 | D72: =SUMIFS(Etablering_2026!$L:$L,Etablering_2026!$A:$A,$A72,Etablering_2026!$B:$B,"<="&DATE($A$7,D$8,1),Etablering_2026!$C:$C,">="&DATE($A$7,D$8,1)) -> 0 | E72: =SUMIFS(Etablering_2026!$L:$L,Etablering_2026!$A:$A,$A72,Etablering_2026!$B:$B,"<="&DATE($A$7,E$8,1),Etablering_2026!$C:$C,">="&DATE($A$7,E$8,1)) -> 0 | F72: =SUMIFS(Etablering_2026!$L:$L,Etablering_2026!$A:$A,$A72,Etablering_2026!$B:$B,"<="&DATE($A$7,F$8,1),Etablering_2026!$C:$C,">="&DATE($A$7,F$8,1)) -> 941.6 | G72: =SUMIFS(Etablering_2026!$L:$L,Etablering_2026!$A:$A,$A72,Etablering_2026!$B:$B,"<="&DATE($A$7,G$8,1),Etablering_2026!$C:$C,">="&DATE($A$7,G$8,1)) -> 0 | H72: =SUMIFS(Etablering_2026!$L:$L,Etablering_2026!$A:$A,$A72,Etablering_2026!$B:$B,"<="&DATE($A$7,H$8,1),Etablering_2026!$C:$C,">="&DATE($A$7,H$8,1)) -> 0 | I72: =SUMIFS(Etablering_2026!$L:$L,Etablering_2026!$A:$A,$A72,Etablering_2026!$B:$B,"<="&DATE($A$7,I$8,1),Etablering_2026!$C:$C,">="&DATE($A$7,I$8,1)) -> 0 | ... M72: =SUMIFS(Etablering_2026!$L:$L,Etablering_2026!$A:$A,$A72,Etablering_2026!$B:$B,"<="&DATE($A$7,M$8,1),Etablering_2026!$C:$C,">="&DATE($A$7,M$8,1)) -> 0 | N72: =SUM(B72:M72) -> 941.6
A73: Hegnsmateriale (Høns) | B73: =SUMIFS(Etablering_2026!$L:$L,Etablering_2026!$A:$A,$A73,Etablering_2026!$B:$B,"<="&DATE($A$7,B$8,1),Etablering_2026!$C:$C,">="&DATE($A$7,B$8,1)) -> 0 | C73: =SUMIFS(Etablering_2026!$L:$L,Etablering_2026!$A:$A,$A73,Etablering_2026!$B:$B,"<="&DATE($A$7,C$8,1),Etablering_2026!$C:$C,">="&DATE($A$7,C$8,1)) -> 0 | D73: =SUMIFS(Etablering_2026!$L:$L,Etablering_2026!$A:$A,$A73,Etablering_2026!$B:$B,"<="&DATE($A$7,D$8,1),Etablering_2026!$C:$C,">="&DATE($A$7,D$8,1)) -> 0 | E73: =SUMIFS(Etablering_2026!$L:$L,Etablering_2026!$A:$A,$A73,Etablering_2026!$B:$B,"<="&DATE($A$7,E$8,1),Etablering_2026!$C:$C,">="&DATE($A$7,E$8,1)) -> 0 | F73: =SUMIFS(Etablering_2026!$L:$L,Etablering_2026!$A:$A,$A73,Etablering_2026!$B:$B,"<="&DATE($A$7,F$8,1),Etablering_2026!$C:$C,">="&DATE($A$7,F$8,1)) -> 2000 | G73: =SUMIFS(Etablering_2026!$L:$L,Etablering_2026!$A:$A,$A73,Etablering_2026!$B:$B,"<="&DATE($A$7,G$8,1),Etablering_2026!$C:$C,">="&DATE($A$7,G$8,1)) -> 0 | H73: =SUMIFS(Etablering_2026!$L:$L,Etablering_2026!$A:$A,$A73,Etablering_2026!$B:$B,"<="&DATE($A$7,H$8,1),Etablering_2026!$C:$C,">="&DATE($A$7,H$8,1)) -> 0 | I73: =SUMIFS(Etablering_2026!$L:$L,Etablering_2026!$A:$A,$A73,Etablering_2026!$B:$B,"<="&DATE($A$7,I$8,1),Etablering_2026!$C:$C,">="&DATE($A$7,I$8,1)) -> 0 | ... M73: =SUMIFS(Etablering_2026!$L:$L,Etablering_2026!$A:$A,$A73,Etablering_2026!$B:$B,"<="&DATE($A$7,M$8,1),Etablering_2026!$C:$C,">="&DATE($A$7,M$8,1)) -> 0 | N73: =SUM(B73:M73) -> 2000
A76: Afskrivninger i alt: | B76: =SUM(B57:B75) -> 0 | C76: =SUM(C57:C75) -> 0 | D76: =SUM(D57:D75) -> 0 | E76: =SUM(E57:E75) -> 0 | F76: =SUM(F57:F75) -> 6861.6 | G76: =SUM(G57:G75) -> 0 | H76: =SUM(H57:H75) -> 45649.6 | I76: =SUM(I57:I75) -> 0 | ... N76: =SUM(N57:N75) -> 119311.2
A77: Faste omkostninger, renter og afskrivninger i alt: | B77: =B48+B54+B76 -> 5646 | C77: =C48+C54+C76 -> 5646 | D77: =D48+D54+D76 -> 5646 | E77: =E48+E54+E76 -> 5646 | F77: =F48+F54+F76 -> 12507.6 | G77: =G48+G54+G76 -> 6446 | H77: =H48+H54+H76 -> 52095.6 | I77: =I48+I54+I76 -> 6446 | ... N77: =N48+N54+N76 -> 190663.2
A79: Nettooverskud (Dækningsbidrag - faste omkostninger, renter og afskrivninger): | B79: =B36-B77 -> -6286 | C79: =C36-C77 -> -6286 | D79: =D36-D77 -> -6286 | E79: =E36-E77 -> -6286 | F79: =F36-F77 -> -1947.6 | G79: =G36-G77 -> -17366 | H79: =H36-H77 -> -54215.6 | I79: =I36-I77 -> -8566 | ... N79: =N36-N77 -> -196888.41

Sheet Forsikringer
A1: Formidler | B1: Post | C1: Alexander | D1: Belæg | E1: Mette | F1: Belæg
B2: A-kasse | C2: =1563*4 -> 6252 | D2: A-kassen A&til | E2: 0 | F2: Ingen da jeg ikke skal have dagpenge eller barselsdagpenge fremadrettet
B3: Fagforening | C3: 528 | D3: Det faglige hus | E3: =97*12 -> 1164 | F3: IDA (På nuværende tidspunkt som "ledig")
A4: Vestjylland forsikring | B4: Indbo og ansvar | C4: 1177.4
A5: Vestjylland forsikring | B5: Knallert | C5: 829
A6: Vestjylland forsikring | B6: Hus | C6: 5903.4
A7: Vestjylland forsikring | B7: Hund | C7: 1871.3
A8: Vestjylland forsikring | B8: Hobbylandbrug | C8: 4453.68 | D8: Dækker ikke den erhvervsdrivende del - denne skal slettes og erstattes af en erhvervslandbrugsforsikring kombineret med indbo og hus. Dine maskiner, foderlagre, køleanlæg og afgrøder overstiger hurtigt beløbsgrænsen for hobbybrug.
A9: Vestjylland forsikring | B9: Landbrugsansvar | C9: 540.89 | D9: Skal ændres til erhvervslandbrugsansvar - ellers dækker den ikke
A10: Vestjylland forsikring | B10: Chevrolet | C10: 3872.88
A11: Vestjylland forsikring | B11: Skoda | C11: 6508.61 | D11: Dækker, hvis I kommer ud for en ulykke, der giver varigt mén (f.eks. hvis du kommer til skade under arbejde med motorsav i skoven eller med traktoren). Vælg en heltidsulykkesforsikring. Da du er selvstændig, dækker en almindelig fritidsulykkesforsikring dig ikke, mens du arbejder i din gårdbutik eller i skoven.
A12: Vestjylland forsikring | B12: Ulykkesforsikring (Alexander) | C12: 1853.9
A13: ? | B13: Kritisk sygdom | F13: 150.000kr. En forsikring, der udbetaler et skattefrit engangsbeløb (typisk mellem 100.000 og 300.000 kr.) med det samme, hvis en af jer diagnosticeres med en livstruende sygdom (f.eks. kræft, blodprop eller hjerteanfald). Pengene giver ro til, at din mand kan tage orlov for at passe dig, eller til at betale for ekstra hjælp til skovdriften og gårdbutikken i en svær periode.
A14: ? | B14: Kritisk sygdom af børn | F14: 100.000kr hvis hun får stillet diagnose under vis alder.
A15: Bank | B15: Livsforsikring (Krydslivsforsikring) | C15: 3456 | E15: 2880 | F15: 2.122.000kr (860.000 kr til nærmest pårørende, hvis ikke andet aftalt + 825.000kr til nærmeste pårørende + 362.000kr + 75.000 til ægtefælle) Krydslivsforsikring betyder, at du ejer og betaler for forsikringen på din mands liv, og han ejer din. Derved undgår I, at udbetalingen modregnes i boafgift
A16: Bank | B16: Tab af erhvervsevne (Udefineret på konto "Kundeforsikring - Lån og kredit") | C16: 1728 | D16: Vigtigt da han er vores faste indkomst | E16: 1728 | F16: 355.000kr om året indtil jeg er 70. Vigtigt da det er vores plan B (At jeg kan tjene en ingeniørløn, hvis andet går galt). Jeg skal oprette mig som civilingeniør.
A17: Bank | B17: Sundhedsforsikring (Udefineret på konto "Forsikr.præmie") | E17: 3100
B18: Ulykkesforsikring (Mette)
B19: Erhvervslandbrugsforsikring | F19: 1. Ansvar og produktansvar (Kritisk)Produktansvar: Dækker, hvis der er salmonella i dine æg, eller hvis dine kartofler/jordbær gør forbrugere syge.Erhvervsansvar: Dækker, hvis dine 5 kødkvæg bryder gennem hegnet og forårsager et trafikuheld, eller hvis en kunde kommer til skade på din gårdbutik.2. Dyr og besætningBesætningsforsikring: Dækker tab, hvis dine kødkvæg eller høns dør ved brand, el-svigt (f.eks. i ventilationsanlæg) eller akut sygdom.Salmonellaforsikring: Dækker driftstab og sanering, hvis dine 150 høns rammes af salmonella.3. Afgrøder og maskinerAfgrødedækning: Dækker dine kartofler og jordbær under opbevaring (f.eks. mod brand eller svigt i kølerum).Driftsherredømme: Dækker specialmaskiner til kartoffel- eller jordbærdyrkning samt traktor mod tyveri og kasko.4. Bygninger og driftstabUdvidet bygningsbrand: Stalden til hønsene og faciliteter til kvæget skal være godkendt til erhverv.Driftstab: Sikrer dig indkomst, hvis en brand midt i jordbærsæsonen ødelægger din mulighed for at sortere og sælge dine varer.
B20: Privat ulykkesforsikring (Hverdagsdækning for Mette)
B21: Kaskoforsikring på maskiner (Rendegraver, traktor, havetraktor)
B22: Erhvervs- og produktansvar (Gårdbutik) | F22: Når du åbner gårdbutik, er du ansvarlig for de varer, du sælger. Hvis en kunde f.eks. bliver syg af fødevarer eller falder på glat gulv, dækker denne forsikring erstatningskrav
B23: Løsøreforsikring (Gårdbutik) | F23: Sikrer varelager, butiksinventar og maskiner mod brand og tyveri
B24: Erhvervsulykkesforsikring
B25: Arbejdsskadeforsikring for indehaver og ansatte (Eller medhjælpere)
B26: Afgrødeforsikring
B27: Besætningsforsikring (Køer og høns)
